{
  "best_global_step": 630,
  "best_metric": 0.8474853662155335,
  "best_model_checkpoint": "./data/model-hub/hsa_synthetic/survival-moco_trial_1744456777/checkpoint-630",
  "epoch": 105.0,
  "eval_steps": 10,
  "global_step": 630,
  "is_hyper_param_search": false,
  "is_local_process_zero": true,
  "is_world_process_zero": true,
  "log_history": [
    {
      "epoch": 1.7272727272727273,
      "grad_norm": 38.942989349365234,
      "learning_rate": 6.932529975984943e-05,
      "loss": 2.4011,
      "step": 10
    },
    {
      "epoch": 3.3636363636363638,
      "grad_norm": 10.146122932434082,
      "learning_rate": 0.00013865059951969887,
      "loss": 1.8786,
      "step": 20
    },
    {
      "epoch": 5.0,
      "grad_norm": 2.3530898094177246,
      "learning_rate": 0.0002079758992795483,
      "loss": 1.6652,
      "step": 30
    },
    {
      "epoch": 6.7272727272727275,
      "grad_norm": 1.5962852239608765,
      "learning_rate": 0.00027730119903939774,
      "loss": 1.6282,
      "step": 40
    },
    {
      "epoch": 6.7272727272727275,
      "eval_brier_0th_event": 0.11643276905016468,
      "eval_brier_0th_event_n": 396,
      "eval_brier_1th_event": 0.13004983086745123,
      "eval_brier_1th_event_n": 392,
      "eval_brier_avg": 0.12324129995880795,
      "eval_brier_weighted_avg": 0.1232067388882057,
      "eval_ipcw": 0.5238139054350205,
      "eval_ipcw_0th_event": 0.4953646201993492,
      "eval_ipcw_0th_event_0.25": 0.45537751246652297,
      "eval_ipcw_0th_event_0.5": 0.49413447967784957,
      "eval_ipcw_0th_event_0.75": 0.48601356332006485,
      "eval_ipcw_0th_event_1.0": 0.4953646201993492,
      "eval_ipcw_0th_event_n": 396,
      "eval_ipcw_1th_event": 0.5525534894996273,
      "eval_ipcw_1th_event_0.25": 0.5129251550207554,
      "eval_ipcw_1th_event_0.5": 0.5224798559917709,
      "eval_ipcw_1th_event_0.75": 0.5254826233308812,
      "eval_ipcw_1th_event_1.0": 0.5525534894996273,
      "eval_ipcw_1th_event_n": 392,
      "eval_ipcw_avg": 0.5055414124383527,
      "eval_ipcw_avg_0th_event": 0.4827225439159466,
      "eval_ipcw_avg_1th_event": 0.5283602809607588,
      "eval_ipcw_weighted_avg": 0.505425580618442,
      "eval_loss": 0.6463096737861633,
      "eval_runtime": 0.3221,
      "eval_samples_per_second": 4138.862,
      "eval_steps_per_second": 9.315,
      "step": 40
    },
    {
      "epoch": 8.363636363636363,
      "grad_norm": 1.0454351902008057,
      "learning_rate": 0.0002772269637720055,
      "loss": 1.4839,
      "step": 50
    },
    {
      "epoch": 8.363636363636363,
      "eval_brier_0th_event": 0.11613692819562839,
      "eval_brier_0th_event_n": 396,
      "eval_brier_1th_event": 0.12776724364566255,
      "eval_brier_1th_event_n": 392,
      "eval_brier_avg": 0.12195208592064546,
      "eval_brier_weighted_avg": 0.12192256735351341,
      "eval_ipcw": 0.5102448579383254,
      "eval_ipcw_0th_event": 0.5030372032355285,
      "eval_ipcw_0th_event_0.25": 0.48650549609096727,
      "eval_ipcw_0th_event_0.5": 0.5084055193726181,
      "eval_ipcw_0th_event_0.75": 0.49203007518796993,
      "eval_ipcw_0th_event_1.0": 0.5030372032355285,
      "eval_ipcw_0th_event_n": 396,
      "eval_ipcw_1th_event": 0.5175260601380895,
      "eval_ipcw_1th_event_0.25": 0.499553923628776,
      "eval_ipcw_1th_event_0.5": 0.4899942334367159,
      "eval_ipcw_1th_event_0.75": 0.4945941728527163,
      "eval_ipcw_1th_event_1.0": 0.5175260601380895,
      "eval_ipcw_1th_event_n": 392,
      "eval_ipcw_avg": 0.4989558354929227,
      "eval_ipcw_avg_0th_event": 0.49749457347177095,
      "eval_ipcw_avg_1th_event": 0.5004170975140745,
      "eval_ipcw_weighted_avg": 0.4989484179192113,
      "eval_loss": 0.6195292472839355,
      "eval_runtime": 0.2988,
      "eval_samples_per_second": 4461.598,
      "eval_steps_per_second": 10.041,
      "step": 50
    },
    {
      "epoch": 10.0,
      "grad_norm": 0.5806007981300354,
      "learning_rate": 0.00027700433746281243,
      "loss": 1.4525,
      "step": 60
    },
    {
      "epoch": 10.0,
      "eval_brier_0th_event": 0.11562269300133658,
      "eval_brier_0th_event_n": 396,
      "eval_brier_1th_event": 0.12732516676882372,
      "eval_brier_1th_event_n": 392,
      "eval_brier_avg": 0.12147392988508016,
      "eval_brier_weighted_avg": 0.12144422817501038,
      "eval_ipcw": 0.5349563371494377,
      "eval_ipcw_0th_event": 0.5373323361423846,
      "eval_ipcw_0th_event_0.25": 0.5575984922946517,
      "eval_ipcw_0th_event_0.5": 0.5537802177881939,
      "eval_ipcw_0th_event_0.75": 0.5245673006044523,
      "eval_ipcw_0th_event_1.0": 0.5373323361423846,
      "eval_ipcw_0th_event_n": 396,
      "eval_ipcw_1th_event": 0.5325560932688077,
      "eval_ipcw_1th_event_0.25": 0.504073672646302,
      "eval_ipcw_1th_event_0.5": 0.513890404126989,
      "eval_ipcw_1th_event_0.75": 0.5185915869725138,
      "eval_ipcw_1th_event_1.0": 0.5325560932688077,
      "eval_ipcw_1th_event_n": 392,
      "eval_ipcw_avg": 0.5302987629805369,
      "eval_ipcw_avg_0th_event": 0.5433195867074206,
      "eval_ipcw_avg_1th_event": 0.5172779392536532,
      "eval_ipcw_weighted_avg": 0.5303648585324501,
      "eval_loss": 0.6051023602485657,
      "eval_runtime": 0.271,
      "eval_samples_per_second": 4918.094,
      "eval_steps_per_second": 11.068,
      "step": 60
    },
    {
      "epoch": 11.727272727272727,
      "grad_norm": 1.2961336374282837,
      "learning_rate": 0.0002766335585056466,
      "loss": 1.5032,
      "step": 70
    },
    {
      "epoch": 11.727272727272727,
      "eval_brier_0th_event": 0.11465546843013205,
      "eval_brier_0th_event_n": 396,
      "eval_brier_1th_event": 0.12719772719393557,
      "eval_brier_1th_event_n": 392,
      "eval_brier_avg": 0.12092659781203381,
      "eval_brier_weighted_avg": 0.12089476466796324,
      "eval_ipcw": 0.5769525790969823,
      "eval_ipcw_0th_event": 0.5868758096611777,
      "eval_ipcw_0th_event_0.25": 0.6614155477605346,
      "eval_ipcw_0th_event_0.5": 0.6221249670900718,
      "eval_ipcw_0th_event_0.75": 0.5919563614919652,
      "eval_ipcw_0th_event_1.0": 0.5868758096611777,
      "eval_ipcw_0th_event_n": 396,
      "eval_ipcw_1th_event": 0.5669280910780502,
      "eval_ipcw_1th_event_0.25": 0.5488840717556239,
      "eval_ipcw_1th_event_0.5": 0.5606989230553434,
      "eval_ipcw_1th_event_0.75": 0.5634961769098732,
      "eval_ipcw_1th_event_1.0": 0.5669280910780502,
      "eval_ipcw_1th_event_n": 392,
      "eval_ipcw_avg": 0.5877974936003301,
      "eval_ipcw_avg_0th_event": 0.6155931715009373,
      "eval_ipcw_avg_1th_event": 0.5600018156997227,
      "eval_ipcw_weighted_avg": 0.5879385884120082,
      "eval_loss": 0.5965057015419006,
      "eval_runtime": 0.2847,
      "eval_samples_per_second": 4681.5,
      "eval_steps_per_second": 10.536,
      "step": 70
    },
    {
      "epoch": 13.363636363636363,
      "grad_norm": 0.8838061094284058,
      "learning_rate": 0.0002761150239399024,
      "loss": 1.4229,
      "step": 80
    },
    {
      "epoch": 13.363636363636363,
      "eval_brier_0th_event": 0.11206400656595909,
      "eval_brier_0th_event_n": 396,
      "eval_brier_1th_event": 0.12674796574880823,
      "eval_brier_1th_event_n": 392,
      "eval_brier_avg": 0.11940598615738365,
      "eval_brier_weighted_avg": 0.1193687172254475,
      "eval_ipcw": 0.6035113012972192,
      "eval_ipcw_0th_event": 0.6222070862881793,
      "eval_ipcw_0th_event_0.25": 0.7268726836614156,
      "eval_ipcw_0th_event_0.5": 0.6748412770346968,
      "eval_ipcw_0th_event_0.75": 0.6392009435353089,
      "eval_ipcw_0th_event_1.0": 0.6222070862881793,
      "eval_ipcw_0th_event_n": 396,
      "eval_ipcw_1th_event": 0.5846247429900249,
      "eval_ipcw_1th_event_0.25": 0.6012519631046915,
      "eval_ipcw_1th_event_0.5": 0.5874647382447828,
      "eval_ipcw_1th_event_0.75": 0.5854914844289886,
      "eval_ipcw_1th_event_1.0": 0.5846247429900249,
      "eval_ipcw_1th_event_n": 392,
      "eval_ipcw_avg": 0.627744364911011,
      "eval_ipcw_avg_0th_event": 0.6657804976299001,
      "eval_ipcw_avg_1th_event": 0.589708232192122,
      "eval_ipcw_weighted_avg": 0.627937441726843,
      "eval_loss": 0.5919392704963684,
      "eval_runtime": 0.2655,
      "eval_samples_per_second": 5019.79,
      "eval_steps_per_second": 11.297,
      "step": 80
    },
    {
      "epoch": 15.0,
      "grad_norm": 1.2075104713439941,
      "learning_rate": 0.0002754492890253807,
      "loss": 1.4164,
      "step": 90
    },
    {
      "epoch": 15.0,
      "eval_brier_0th_event": 0.10952997941392288,
      "eval_brier_0th_event_n": 396,
      "eval_brier_1th_event": 0.12518500524239956,
      "eval_brier_1th_event_n": 392,
      "eval_brier_avg": 0.11735749232816123,
      "eval_brier_weighted_avg": 0.11731775876006864,
      "eval_ipcw": 0.6325108902984018,
      "eval_ipcw_0th_event": 0.6410580017896016,
      "eval_ipcw_0th_event_0.25": 0.7325987177290639,
      "eval_ipcw_0th_event_0.5": 0.69195875576733,
      "eval_ipcw_0th_event_0.75": 0.6553059118384196,
      "eval_ipcw_0th_event_1.0": 0.6410580017896016,
      "eval_ipcw_0th_event_n": 396,
      "eval_ipcw_1th_event": 0.6238765633838225,
      "eval_ipcw_1th_event_0.25": 0.6668436225825242,
      "eval_ipcw_1th_event_0.5": 0.6385338902482739,
      "eval_ipcw_1th_event_0.75": 0.6318297331639136,
      "eval_ipcw_1th_event_1.0": 0.6238765633838225,
      "eval_ipcw_1th_event_n": 392,
      "eval_ipcw_avg": 0.6602506495628686,
      "eval_ipcw_avg_0th_event": 0.6802303467811037,
      "eval_ipcw_avg_1th_event": 0.6402709523446335,
      "eval_ipcw_weighted_avg": 0.6603520693457022,
      "eval_loss": 0.5859017968177795,
      "eval_runtime": 0.2832,
      "eval_samples_per_second": 4707.269,
      "eval_steps_per_second": 10.594,
      "step": 90
    },
    {
      "epoch": 16.727272727272727,
      "grad_norm": 1.5022517442703247,
      "learning_rate": 0.0002746370666477027,
      "loss": 1.4788,
      "step": 100
    },
    {
      "epoch": 16.727272727272727,
      "eval_brier_0th_event": 0.10776989823435158,
      "eval_brier_0th_event_n": 396,
      "eval_brier_1th_event": 0.12173213939855214,
      "eval_brier_1th_event_n": 392,
      "eval_brier_avg": 0.11475101881645186,
      "eval_brier_weighted_avg": 0.11471558165613664,
      "eval_ipcw": 0.6626128187354114,
      "eval_ipcw_0th_event": 0.6601782478820821,
      "eval_ipcw_0th_event_0.25": 0.7411832601422942,
      "eval_ipcw_0th_event_0.5": 0.7083036604472297,
      "eval_ipcw_0th_event_0.75": 0.6741766180156273,
      "eval_ipcw_0th_event_1.0": 0.6601782478820821,
      "eval_ipcw_0th_event_n": 396,
      "eval_ipcw_1th_event": 0.6650722321484687,
      "eval_ipcw_1th_event_0.25": 0.7321772213497313,
      "eval_ipcw_1th_event_0.5": 0.684833938562723,
      "eval_ipcw_1th_event_0.75": 0.6792366080385207,
      "eval_ipcw_1th_event_1.0": 0.6650722321484687,
      "eval_ipcw_1th_event_n": 392,
      "eval_ipcw_avg": 0.6931452233233346,
      "eval_ipcw_avg_0th_event": 0.6959604466218083,
      "eval_ipcw_avg_1th_event": 0.690330000024861,
      "eval_ipcw_weighted_avg": 0.693159513796931,
      "eval_loss": 0.5786281824111938,
      "eval_runtime": 0.2768,
      "eval_samples_per_second": 4815.127,
      "eval_steps_per_second": 10.837,
      "step": 100
    },
    {
      "epoch": 18.363636363636363,
      "grad_norm": 1.5890262126922607,
      "learning_rate": 0.0002736792265549345,
      "loss": 1.4042,
      "step": 110
    },
    {
      "epoch": 18.363636363636363,
      "eval_brier_0th_event": 0.10312101402465271,
      "eval_brier_0th_event_n": 396,
      "eval_brier_1th_event": 0.12080341817258813,
      "eval_brier_1th_event_n": 392,
      "eval_brier_avg": 0.11196221609862042,
      "eval_brier_weighted_avg": 0.11191733690027542,
      "eval_ipcw": 0.6851468428339453,
      "eval_ipcw_0th_event": 0.695046542997182,
      "eval_ipcw_0th_event_0.25": 0.7828796090065556,
      "eval_ipcw_0th_event_0.5": 0.7421199604649256,
      "eval_ipcw_0th_event_0.75": 0.7139112487100103,
      "eval_ipcw_0th_event_1.0": 0.695046542997182,
      "eval_ipcw_0th_event_n": 396,
      "eval_ipcw_1th_event": 0.6751461253221042,
      "eval_ipcw_1th_event_0.25": 0.7465548895131501,
      "eval_ipcw_1th_event_0.5": 0.707150148839674,
      "eval_ipcw_1th_event_0.75": 0.6916839430214673,
      "eval_ipcw_1th_event_1.0": 0.6751461253221042,
      "eval_ipcw_1th_event_n": 392,
      "eval_ipcw_avg": 0.7193115584843837,
      "eval_ipcw_avg_0th_event": 0.7334893402946684,
      "eval_ipcw_avg_1th_event": 0.7051337766740988,
      "eval_ipcw_weighted_avg": 0.7193835269199688,
      "eval_loss": 0.5716139674186707,
      "eval_runtime": 0.2801,
      "eval_samples_per_second": 4759.491,
      "eval_steps_per_second": 10.712,
      "step": 110
    },
    {
      "epoch": 20.0,
      "grad_norm": 2.6334002017974854,
      "learning_rate": 0.0002725767944262387,
      "loss": 1.3893,
      "step": 120
    },
    {
      "epoch": 20.0,
      "eval_brier_0th_event": 0.09892986915926961,
      "eval_brier_0th_event_n": 396,
      "eval_brier_1th_event": 0.11666860624220045,
      "eval_brier_1th_event_n": 392,
      "eval_brier_avg": 0.10779923770073503,
      "eval_brier_weighted_avg": 0.10775421552539764,
      "eval_ipcw": 0.7133770146203015,
      "eval_ipcw_0th_event": 0.7314974335688307,
      "eval_ipcw_0th_event_0.25": 0.8223306311261801,
      "eval_ipcw_0th_event_0.5": 0.7845899530844695,
      "eval_ipcw_0th_event_0.75": 0.7515877930119417,
      "eval_ipcw_0th_event_1.0": 0.7314974335688307,
      "eval_ipcw_0th_event_n": 396,
      "eval_ipcw_1th_event": 0.6950716934376038,
      "eval_ipcw_1th_event_0.25": 0.7794908093521201,
      "eval_ipcw_1th_event_0.5": 0.731352181163599,
      "eval_ipcw_1th_event_0.75": 0.7156423460175215,
      "eval_ipcw_1th_event_1.0": 0.6950716934376038,
      "eval_ipcw_1th_event_n": 392,
      "eval_ipcw_avg": 0.7514453550952833,
      "eval_ipcw_avg_0th_event": 0.7725014526978555,
      "eval_ipcw_avg_1th_event": 0.7303892574927111,
      "eval_ipcw_weighted_avg": 0.7515522388394588,
      "eval_loss": 0.5592658519744873,
      "eval_runtime": 0.3854,
      "eval_samples_per_second": 3458.635,
      "eval_steps_per_second": 7.784,
      "step": 120
    },
    {
      "epoch": 21.727272727272727,
      "grad_norm": 1.642229676246643,
      "learning_rate": 0.00027133095077355154,
      "loss": 1.4501,
      "step": 130
    },
    {
      "epoch": 21.727272727272727,
      "eval_brier_0th_event": 0.09555416294291219,
      "eval_brier_0th_event_n": 396,
      "eval_brier_1th_event": 0.11469174746610236,
      "eval_brier_1th_event_n": 392,
      "eval_brier_avg": 0.10512295520450728,
      "eval_brier_weighted_avg": 0.10507438265495603,
      "eval_ipcw": 0.7242430432054341,
      "eval_ipcw_0th_event": 0.7481669938699467,
      "eval_ipcw_0th_event_0.25": 0.8514026529121618,
      "eval_ipcw_0th_event_0.5": 0.8036021804715723,
      "eval_ipcw_0th_event_0.75": 0.771593690107622,
      "eval_ipcw_0th_event_1.0": 0.7481669938699467,
      "eval_ipcw_0th_event_n": 396,
      "eval_ipcw_1th_event": 0.7000749705953653,
      "eval_ipcw_1th_event_0.25": 0.7811129052474802,
      "eval_ipcw_1th_event_0.5": 0.7386383117996353,
      "eval_ipcw_1th_event_0.75": 0.722143271138456,
      "eval_ipcw_1th_event_1.0": 0.7000749705953653,
      "eval_ipcw_1th_event_n": 392,
      "eval_ipcw_avg": 0.76459187201778,
      "eval_ipcw_avg_0th_event": 0.7936913793403256,
      "eval_ipcw_avg_1th_event": 0.7354923646952343,
      "eval_ipcw_weighted_avg": 0.7647395852529196,
      "eval_loss": 0.552369236946106,
      "eval_runtime": 0.2775,
      "eval_samples_per_second": 4802.825,
      "eval_steps_per_second": 10.809,
      "step": 130
    },
    {
      "epoch": 23.363636363636363,
      "grad_norm": 2.16448712348938,
      "learning_rate": 0.00026994302967746136,
      "loss": 1.3765,
      "step": 140
    },
    {
      "epoch": 23.363636363636363,
      "eval_brier_0th_event": 0.09449599742530548,
      "eval_brier_0th_event_n": 396,
      "eval_brier_1th_event": 0.11471367853645065,
      "eval_brier_1th_event_n": 392,
      "eval_brier_avg": 0.10460483798087807,
      "eval_brier_weighted_avg": 0.10455352406942846,
      "eval_ipcw": 0.7306886290740904,
      "eval_ipcw_0th_event": 0.7524874126901452,
      "eval_ipcw_0th_event_0.25": 0.8523584948195172,
      "eval_ipcw_0th_event_0.5": 0.8098949903536145,
      "eval_ipcw_0th_event_0.75": 0.7744213474863629,
      "eval_ipcw_0th_event_1.0": 0.7524874126901452,
      "eval_ipcw_0th_event_n": 396,
      "eval_ipcw_1th_event": 0.7086674088905249,
      "eval_ipcw_1th_event_0.25": 0.7974923872090366,
      "eval_ipcw_1th_event_0.5": 0.753187195112448,
      "eval_ipcw_1th_event_0.75": 0.7340611694420295,
      "eval_ipcw_1th_event_1.0": 0.7086674088905249,
      "eval_ipcw_1th_event_n": 392,
      "eval_ipcw_avg": 0.7728213007504598,
      "eval_ipcw_avg_0th_event": 0.7972905613374099,
      "eval_ipcw_avg_1th_event": 0.7483520401635098,
      "eval_ipcw_weighted_avg": 0.7729455101950636,
      "eval_loss": 0.5497974753379822,
      "eval_runtime": 0.2784,
      "eval_samples_per_second": 4788.662,
      "eval_steps_per_second": 10.777,
      "step": 140
    },
    {
      "epoch": 25.0,
      "grad_norm": 2.6980366706848145,
      "learning_rate": 0.00026841451735864146,
      "loss": 1.3753,
      "step": 150
    },
    {
      "epoch": 25.0,
      "eval_brier_0th_event": 0.09432669093872319,
      "eval_brier_0th_event_n": 396,
      "eval_brier_1th_event": 0.11197660343077648,
      "eval_brier_1th_event_n": 392,
      "eval_brier_avg": 0.10315164718474984,
      "eval_brier_weighted_avg": 0.1031068504525365,
      "eval_ipcw": 0.7389683560103111,
      "eval_ipcw_0th_event": 0.7575490471039171,
      "eval_ipcw_0th_event_0.25": 0.8658484900403077,
      "eval_ipcw_0th_event_0.5": 0.819468002917654,
      "eval_ipcw_0th_event_0.75": 0.7795577178239717,
      "eval_ipcw_0th_event_1.0": 0.7575490471039171,
      "eval_ipcw_0th_event_n": 396,
      "eval_ipcw_1th_event": 0.720198066027995,
      "eval_ipcw_1th_event_0.25": 0.7992730061123523,
      "eval_ipcw_1th_event_0.5": 0.7674789208734005,
      "eval_ipcw_1th_event_0.75": 0.7473333110412627,
      "eval_ipcw_1th_event_1.0": 0.720198066027995,
      "eval_ipcw_1th_event_n": 392,
      "eval_ipcw_avg": 0.7820883202426077,
      "eval_ipcw_avg_0th_event": 0.8056058144714626,
      "eval_ipcw_avg_1th_event": 0.7585708260137526,
      "eval_ipcw_weighted_avg": 0.7822076983859013,
      "eval_loss": 0.545927107334137,
      "eval_runtime": 0.2801,
      "eval_samples_per_second": 4759.232,
      "eval_steps_per_second": 10.711,
      "step": 150
    },
    {
      "epoch": 26.727272727272727,
      "grad_norm": 3.0480732917785645,
      "learning_rate": 0.0002667470505863679,
      "loss": 1.4261,
      "step": 160
    },
    {
      "epoch": 26.727272727272727,
      "eval_brier_0th_event": 0.0917921076354747,
      "eval_brier_0th_event_n": 396,
      "eval_brier_1th_event": 0.10967238012139909,
      "eval_brier_1th_event_n": 392,
      "eval_brier_avg": 0.10073224387843689,
      "eval_brier_weighted_avg": 0.10068686247618835,
      "eval_ipcw": 0.7458330623768917,
      "eval_ipcw_0th_event": 0.7667285459264305,
      "eval_ipcw_0th_event_0.25": 0.8693382147398035,
      "eval_ipcw_0th_event_0.5": 0.8251954094426677,
      "eval_ipcw_0th_event_0.75": 0.787421494913755,
      "eval_ipcw_0th_event_1.0": 0.7667285459264305,
      "eval_ipcw_0th_event_n": 396,
      "eval_ipcw_1th_event": 0.7247243596074594,
      "eval_ipcw_1th_event_0.25": 0.805178909804095,
      "eval_ipcw_1th_event_0.5": 0.7719791780309524,
      "eval_ipcw_1th_event_0.75": 0.7516412537060567,
      "eval_ipcw_1th_event_1.0": 0.7247243596074594,
      "eval_ipcw_1th_event_n": 392,
      "eval_ipcw_avg": 0.7877759207714026,
      "eval_ipcw_avg_0th_event": 0.8121709162556642,
      "eval_ipcw_avg_1th_event": 0.763380925287141,
      "eval_ipcw_weighted_avg": 0.7878997532357896,
      "eval_loss": 0.5415058135986328,
      "eval_runtime": 0.2661,
      "eval_samples_per_second": 5009.881,
      "eval_steps_per_second": 11.275,
      "step": 160
    },
    {
      "epoch": 28.363636363636363,
      "grad_norm": 2.005793809890747,
      "learning_rate": 0.0002649424149258259,
      "loss": 1.3673,
      "step": 170
    },
    {
      "epoch": 28.363636363636363,
      "eval_brier_0th_event": 0.09033671651186309,
      "eval_brier_0th_event_n": 396,
      "eval_brier_1th_event": 0.10818027704220962,
      "eval_brier_1th_event_n": 392,
      "eval_brier_avg": 0.09925849677703635,
      "eval_brier_weighted_avg": 0.09921320855234005,
      "eval_ipcw": 0.7515531789508689,
      "eval_ipcw_0th_event": 0.7707929893914909,
      "eval_ipcw_0th_event_0.25": 0.8690496586923001,
      "eval_ipcw_0th_event_0.5": 0.8279037346833957,
      "eval_ipcw_0th_event_0.75": 0.7911779448621554,
      "eval_ipcw_0th_event_1.0": 0.7707929893914909,
      "eval_ipcw_0th_event_n": 396,
      "eval_ipcw_1th_event": 0.732117043913914,
      "eval_ipcw_1th_event_0.25": 0.825182301459149,
      "eval_ipcw_1th_event_0.5": 0.7789808768293253,
      "eval_ipcw_1th_event_0.75": 0.7594267594016808,
      "eval_ipcw_1th_event_1.0": 0.732117043913914,
      "eval_ipcw_1th_event_n": 392,
      "eval_ipcw_avg": 0.7943289136541763,
      "eval_ipcw_avg_0th_event": 0.8147310819073355,
      "eval_ipcw_avg_1th_event": 0.7739267454010172,
      "eval_ipcw_weighted_avg": 0.79443247796003,
      "eval_loss": 0.5335142016410828,
      "eval_runtime": 0.279,
      "eval_samples_per_second": 4777.434,
      "eval_steps_per_second": 10.752,
      "step": 170
    },
    {
      "epoch": 30.0,
      "grad_norm": 2.4467971324920654,
      "learning_rate": 0.000263002542826082,
      "loss": 1.3542,
      "step": 180
    },
    {
      "epoch": 30.0,
      "eval_brier_0th_event": 0.08881048533741868,
      "eval_brier_0th_event_n": 396,
      "eval_brier_1th_event": 0.10596585222221167,
      "eval_brier_1th_event_n": 392,
      "eval_brier_avg": 0.09738816877981518,
      "eval_brier_weighted_avg": 0.09734462723949842,
      "eval_ipcw": 0.7574397042247076,
      "eval_ipcw_0th_event": 0.7742631248581007,
      "eval_ipcw_0th_event_0.25": 0.8787253036601531,
      "eval_ipcw_0th_event_0.5": 0.8343756608960996,
      "eval_ipcw_0th_event_0.75": 0.7969659442724458,
      "eval_ipcw_0th_event_1.0": 0.7742631248581007,
      "eval_ipcw_0th_event_n": 396,
      "eval_ipcw_1th_event": 0.740444616033831,
      "eval_ipcw_1th_event_0.25": 0.8333591394043959,
      "eval_ipcw_1th_event_0.5": 0.7859202344030048,
      "eval_ipcw_1th_event_0.75": 0.7672122650973049,
      "eval_ipcw_1th_event_1.0": 0.740444616033831,
      "eval_ipcw_1th_event_n": 392,
      "eval_ipcw_avg": 0.801408286078167,
      "eval_ipcw_avg_0th_event": 0.8210825084216998,
      "eval_ipcw_avg_1th_event": 0.7817340637346342,
      "eval_ipcw_weighted_avg": 0.8015081552271189,
      "eval_loss": 0.5295022130012512,
      "eval_runtime": 0.28,
      "eval_samples_per_second": 4759.884,
      "eval_steps_per_second": 10.712,
      "step": 180
    },
    {
      "epoch": 31.727272727272727,
      "grad_norm": 3.6001405715942383,
      "learning_rate": 0.0002609295115507691,
      "loss": 1.4162,
      "step": 190
    },
    {
      "epoch": 31.727272727272727,
      "eval_brier_0th_event": 0.08722740522695478,
      "eval_brier_0th_event_n": 396,
      "eval_brier_1th_event": 0.10534105787064432,
      "eval_brier_1th_event_n": 392,
      "eval_brier_avg": 0.09628423154879956,
      "eval_brier_weighted_avg": 0.09623825781112522,
      "eval_ipcw": 0.7618965851303416,
      "eval_ipcw_0th_event": 0.7754161268925482,
      "eval_ipcw_0th_event_0.25": 0.8849382760579637,
      "eval_ipcw_0th_event_0.5": 0.8362186168766428,
      "eval_ipcw_0th_event_0.75": 0.7984284240011794,
      "eval_ipcw_0th_event_1.0": 0.7754161268925482,
      "eval_ipcw_0th_event_n": 396,
      "eval_ipcw_1th_event": 0.7482390888603572,
      "eval_ipcw_1th_event_0.25": 0.8416465747970537,
      "eval_ipcw_1th_event_0.5": 0.7936505462649813,
      "eval_ipcw_1th_event_0.75": 0.7736100893912036,
      "eval_ipcw_1th_event_1.0": 0.7482390888603572,
      "eval_ipcw_1th_event_n": 392,
      "eval_ipcw_avg": 0.8065184678927413,
      "eval_ipcw_avg_0th_event": 0.8237503609570835,
      "eval_ipcw_avg_1th_event": 0.7892865748283989,
      "eval_ipcw_weighted_avg": 0.8066059394311388,
      "eval_loss": 0.5256743431091309,
      "eval_runtime": 0.287,
      "eval_samples_per_second": 4644.728,
      "eval_steps_per_second": 10.453,
      "step": 190
    },
    {
      "epoch": 33.36363636363637,
      "grad_norm": 3.7081809043884277,
      "learning_rate": 0.0002587255409537006,
      "loss": 1.3373,
      "step": 200
    },
    {
      "epoch": 33.36363636363637,
      "eval_brier_0th_event": 0.08656762856731862,
      "eval_brier_0th_event_n": 396,
      "eval_brier_1th_event": 0.10206978267097674,
      "eval_brier_1th_event_n": 392,
      "eval_brier_avg": 0.09431870561914768,
      "eval_brier_weighted_avg": 0.09427936005035667,
      "eval_ipcw": 0.7681181676820549,
      "eval_ipcw_0th_event": 0.7783364718137746,
      "eval_ipcw_0th_event_0.25": 0.8902044239249033,
      "eval_ipcw_0th_event_0.5": 0.8382903238336937,
      "eval_ipcw_0th_event_0.75": 0.8032935279374908,
      "eval_ipcw_0th_event_1.0": 0.7783364718137746,
      "eval_ipcw_0th_event_n": 396,
      "eval_ipcw_1th_event": 0.757795595140828,
      "eval_ipcw_1th_event_0.25": 0.8534805016700214,
      "eval_ipcw_1th_event_0.5": 0.8064616679394667,
      "eval_ipcw_1th_event_0.75": 0.7836192291401949,
      "eval_ipcw_1th_event_1.0": 0.757795595140828,
      "eval_ipcw_1th_event_n": 392,
      "eval_ipcw_avg": 0.8139352176750467,
      "eval_ipcw_avg_0th_event": 0.8275311868774656,
      "eval_ipcw_avg_1th_event": 0.8003392484726277,
      "eval_ipcw_weighted_avg": 0.8140042327471401,
      "eval_loss": 0.5197861790657043,
      "eval_runtime": 0.2819,
      "eval_samples_per_second": 4728.057,
      "eval_steps_per_second": 10.641,
      "step": 200
    },
    {
      "epoch": 35.0,
      "grad_norm": 2.9743149280548096,
      "learning_rate": 0.0002563929911017952,
      "loss": 1.3422,
      "step": 210
    },
    {
      "epoch": 35.0,
      "eval_brier_0th_event": 0.0862844210183371,
      "eval_brier_0th_event_n": 396,
      "eval_brier_1th_event": 0.10193892863595284,
      "eval_brier_1th_event_n": 392,
      "eval_brier_avg": 0.09411167482714497,
      "eval_brier_weighted_avg": 0.09407194257430838,
      "eval_ipcw": 0.7737441052905466,
      "eval_ipcw_0th_event": 0.7876495229954904,
      "eval_ipcw_0th_event_0.25": 0.8959575101220051,
      "eval_ipcw_0th_event_0.5": 0.8428480791392058,
      "eval_ipcw_0th_event_0.75": 0.8100928792569659,
      "eval_ipcw_0th_event_1.0": 0.7876495229954904,
      "eval_ipcw_0th_event_n": 396,
      "eval_ipcw_1th_event": 0.7596967955682052,
      "eval_ipcw_1th_event_0.25": 0.8551837023601495,
      "eval_ipcw_1th_event_0.5": 0.8078214859030906,
      "eval_ipcw_1th_event_0.75": 0.7835607124545799,
      "eval_ipcw_1th_event_1.0": 0.7596967955682052,
      "eval_ipcw_1th_event_n": 392,
      "eval_ipcw_avg": 0.8178513359749615,
      "eval_ipcw_avg_0th_event": 0.8341369978784168,
      "eval_ipcw_avg_1th_event": 0.8015656740715063,
      "eval_ipcw_weighted_avg": 0.8179340043094969,
      "eval_loss": 0.5157492756843567,
      "eval_runtime": 0.2729,
      "eval_samples_per_second": 4884.785,
      "eval_steps_per_second": 10.994,
      "step": 210
    },
    {
      "epoch": 36.72727272727273,
      "grad_norm": 2.463762044906616,
      "learning_rate": 0.0002539343597478584,
      "loss": 1.4056,
      "step": 220
    },
    {
      "epoch": 36.72727272727273,
      "eval_brier_0th_event": 0.0861232247588388,
      "eval_brier_0th_event_n": 396,
      "eval_brier_1th_event": 0.1035448177378141,
      "eval_brier_1th_event_n": 392,
      "eval_brier_avg": 0.09483402124832645,
      "eval_brier_weighted_avg": 0.09478980400726306,
      "eval_ipcw": 0.7759611771868085,
      "eval_ipcw_0th_event": 0.7883128330461958,
      "eval_ipcw_0th_event_0.25": 0.8900601459011516,
      "eval_ipcw_0th_event_0.5": 0.8419676036824592,
      "eval_ipcw_0th_event_0.75": 0.8100339083001622,
      "eval_ipcw_0th_event_1.0": 0.7883128330461958,
      "eval_ipcw_0th_event_n": 396,
      "eval_ipcw_1th_event": 0.7634834840227336,
      "eval_ipcw_1th_event_0.25": 0.8563044231605801,
      "eval_ipcw_1th_event_0.5": 0.809722893256238,
      "eval_ipcw_1th_event_0.75": 0.7869922980895695,
      "eval_ipcw_1th_event_1.0": 0.7634834840227336,
      "eval_ipcw_1th_event_n": 392,
      "eval_ipcw_avg": 0.8183596986823862,
      "eval_ipcw_avg_0th_event": 0.8325936227324922,
      "eval_ipcw_avg_1th_event": 0.8041257746322803,
      "eval_ipcw_weighted_avg": 0.8184319521039605,
      "eval_loss": 0.516413152217865,
      "eval_runtime": 0.3891,
      "eval_samples_per_second": 3425.564,
      "eval_steps_per_second": 7.709,
      "step": 220
    },
    {
      "epoch": 38.36363636363637,
      "grad_norm": 4.4268269538879395,
      "learning_rate": 0.0002513522796559259,
      "loss": 1.3296,
      "step": 230
    },
    {
      "epoch": 38.36363636363637,
      "eval_brier_0th_event": 0.08466478212821904,
      "eval_brier_0th_event_n": 396,
      "eval_brier_1th_event": 0.10259955901502542,
      "eval_brier_1th_event_n": 392,
      "eval_brier_avg": 0.09363217057162224,
      "eval_brier_weighted_avg": 0.09358665083333083,
      "eval_ipcw": 0.7769301957679883,
      "eval_ipcw_0th_event": 0.7893434120847078,
      "eval_ipcw_0th_event_0.25": 0.891962812339378,
      "eval_ipcw_0th_event_0.5": 0.845187381578209,
      "eval_ipcw_0th_event_0.75": 0.8110511573050273,
      "eval_ipcw_0th_event_1.0": 0.7893434120847078,
      "eval_ipcw_0th_event_n": 396,
      "eval_ipcw_1th_event": 0.7643903139786491,
      "eval_ipcw_1th_event_0.25": 0.8584942526193162,
      "eval_ipcw_1th_event_0.5": 0.8113437650982653,
      "eval_ipcw_1th_event_0.75": 0.788459394993201,
      "eval_ipcw_1th_event_1.0": 0.7643903139786491,
      "eval_ipcw_1th_event_n": 392,
      "eval_ipcw_avg": 0.8200290612495942,
      "eval_ipcw_avg_0th_event": 0.8343861908268305,
      "eval_ipcw_avg_1th_event": 0.8056719316723578,
      "eval_ipcw_weighted_avg": 0.8201019400799355,
      "eval_loss": 0.5157050490379333,
      "eval_runtime": 0.2861,
      "eval_samples_per_second": 4659.615,
      "eval_steps_per_second": 10.487,
      "step": 230
    },
    {
      "epoch": 40.0,
      "grad_norm": 2.3455421924591064,
      "learning_rate": 0.0002486495157820343,
      "loss": 1.3296,
      "step": 240
    },
    {
      "epoch": 40.0,
      "eval_brier_0th_event": 0.08414647021627925,
      "eval_brier_0th_event_n": 396,
      "eval_brier_1th_event": 0.09783552528226877,
      "eval_brier_1th_event_n": 392,
      "eval_brier_avg": 0.09099099774927401,
      "eval_brier_weighted_avg": 0.09095625395469029,
      "eval_ipcw": 0.7783469527783755,
      "eval_ipcw_0th_event": 0.7890829849842631,
      "eval_ipcw_0th_event_0.25": 0.9015663182953552,
      "eval_ipcw_0th_event_0.5": 0.850487498543331,
      "eval_ipcw_0th_event_0.75": 0.8137313872917588,
      "eval_ipcw_0th_event_1.0": 0.7890829849842631,
      "eval_ipcw_0th_event_n": 396,
      "eval_ipcw_1th_event": 0.7675013692234482,
      "eval_ipcw_1th_event_0.25": 0.8652628164008641,
      "eval_ipcw_1th_event_0.5": 0.8174493087916712,
      "eval_ipcw_1th_event_0.75": 0.792739472569607,
      "eval_ipcw_1th_event_1.0": 0.7675013692234482,
      "eval_ipcw_1th_event_n": 392,
      "eval_ipcw_avg": 0.8247276445125373,
      "eval_ipcw_avg_0th_event": 0.838717047278677,
      "eval_ipcw_avg_1th_event": 0.8107382417463977,
      "eval_ipcw_weighted_avg": 0.82479865670932,
      "eval_loss": 0.5067601203918457,
      "eval_runtime": 0.2839,
      "eval_samples_per_second": 4695.335,
      "eval_steps_per_second": 10.567,
      "step": 240
    },
    {
      "epoch": 41.72727272727273,
      "grad_norm": 3.6963050365448,
      "learning_rate": 0.0002458289623134366,
      "loss": 1.3953,
      "step": 250
    },
    {
      "epoch": 41.72727272727273,
      "eval_brier_0th_event": 0.08415031922320991,
      "eval_brier_0th_event_n": 396,
      "eval_brier_1th_event": 0.09756501236339638,
      "eval_brier_1th_event_n": 392,
      "eval_brier_avg": 0.09085766579330315,
      "eval_brier_weighted_avg": 0.09082361834878488,
      "eval_ipcw": 0.7825758021296473,
      "eval_ipcw_0th_event": 0.7912253874131353,
      "eval_ipcw_0th_event_0.25": 0.9002046944461978,
      "eval_ipcw_0th_event_0.5": 0.8504443379817258,
      "eval_ipcw_0th_event_0.75": 0.8140114993365767,
      "eval_ipcw_0th_event_1.0": 0.7912253874131353,
      "eval_ipcw_0th_event_n": 396,
      "eval_ipcw_1th_event": 0.773837955771838,
      "eval_ipcw_1th_event_0.25": 0.869841550723676,
      "eval_ipcw_1th_event_0.5": 0.825031560245001,
      "eval_ipcw_1th_event_0.75": 0.797824851200428,
      "eval_ipcw_1th_event_1.0": 0.773837955771838,
      "eval_ipcw_1th_event_n": 392,
      "eval_ipcw_avg": 0.8278027296398223,
      "eval_ipcw_avg_0th_event": 0.8389714797944089,
      "eval_ipcw_avg_1th_event": 0.8166339794852358,
      "eval_ipcw_weighted_avg": 0.8278594238030434,
      "eval_loss": 0.5047213435173035,
      "eval_runtime": 0.3289,
      "eval_samples_per_second": 4052.359,
      "eval_steps_per_second": 9.12,
      "step": 250
    },
    {
      "epoch": 43.36363636363637,
      "grad_norm": 4.492232799530029,
      "learning_rate": 0.00024289363956943405,
      "loss": 1.3206,
      "step": 260
    },
    {
      "epoch": 43.36363636363637,
      "eval_brier_0th_event": 0.0837141731441984,
      "eval_brier_0th_event_n": 396,
      "eval_brier_1th_event": 0.10041336624459603,
      "eval_brier_1th_event_n": 392,
      "eval_brier_avg": 0.09206376969439722,
      "eval_brier_weighted_avg": 0.09202138595556374,
      "eval_ipcw": 0.7853086869854548,
      "eval_ipcw_0th_event": 0.79497264402509,
      "eval_ipcw_0th_event_0.25": 0.8979683850780454,
      "eval_ipcw_0th_event_0.5": 0.8505220269926153,
      "eval_ipcw_0th_event_0.75": 0.8160047176765443,
      "eval_ipcw_0th_event_1.0": 0.79497264402509,
      "eval_ipcw_0th_event_n": 396,
      "eval_ipcw_1th_event": 0.7755461181392926,
      "eval_ipcw_1th_event_0.25": 0.870055372455337,
      "eval_ipcw_1th_event_0.5": 0.8247081651419043,
      "eval_ipcw_1th_event_0.75": 0.7981369401903743,
      "eval_ipcw_1th_event_1.0": 0.7755461181392926,
      "eval_ipcw_1th_event_n": 392,
      "eval_ipcw_avg": 0.8284892962124004,
      "eval_ipcw_avg_0th_event": 0.8398669434430738,
      "eval_ipcw_avg_1th_event": 0.8171116489817272,
      "eval_ipcw_weighted_avg": 0.828547050766871,
      "eval_loss": 0.5066754221916199,
      "eval_runtime": 0.2751,
      "eval_samples_per_second": 4846.002,
      "eval_steps_per_second": 10.906,
      "step": 260
    },
    {
      "epoch": 45.0,
      "grad_norm": 3.2801239490509033,
      "learning_rate": 0.00023984669076714286,
      "loss": 1.3192,
      "step": 270
    },
    {
      "epoch": 45.0,
      "eval_brier_0th_event": 0.08462747434673522,
      "eval_brier_0th_event_n": 396,
      "eval_brier_1th_event": 0.0993208806177238,
      "eval_brier_1th_event_n": 392,
      "eval_brier_avg": 0.09197417748222951,
      "eval_brier_weighted_avg": 0.09193688457291227,
      "eval_ipcw": 0.7856175485401672,
      "eval_ipcw_0th_event": 0.7957361183451972,
      "eval_ipcw_0th_event_0.25": 0.8967149697467018,
      "eval_ipcw_0th_event_0.5": 0.8495638625249792,
      "eval_ipcw_0th_event_0.75": 0.8159988205808639,
      "eval_ipcw_0th_event_1.0": 0.7957361183451972,
      "eval_ipcw_0th_event_n": 396,
      "eval_ipcw_1th_event": 0.7753957280228413,
      "eval_ipcw_1th_event_0.25": 0.8679761404440118,
      "eval_ipcw_1th_event_0.5": 0.8239250035066938,
      "eval_ipcw_1th_event_0.75": 0.7978582893064937,
      "eval_ipcw_1th_event_1.0": 0.7753957280228413,
      "eval_ipcw_1th_event_n": 392,
      "eval_ipcw_avg": 0.827896116559723,
      "eval_ipcw_avg_0th_event": 0.8395034427994357,
      "eval_ipcw_avg_1th_event": 0.8162887903200101,
      "eval_ipcw_weighted_avg": 0.8279550369974881,
      "eval_loss": 0.5063799023628235,
      "eval_runtime": 0.2777,
      "eval_samples_per_second": 4800.978,
      "eval_steps_per_second": 10.805,
      "step": 270
    },
    {
      "epoch": 46.72727272727273,
      "grad_norm": 2.4304444789886475,
      "learning_rate": 0.0002366913786556582,
      "loss": 1.3865,
      "step": 280
    },
    {
      "epoch": 46.72727272727273,
      "eval_brier_0th_event": 0.08447415998041666,
      "eval_brier_0th_event_n": 396,
      "eval_brier_1th_event": 0.0977514293947688,
      "eval_brier_1th_event_n": 392,
      "eval_brier_avg": 0.09111279468759273,
      "eval_brier_weighted_avg": 0.09107909603425682,
      "eval_ipcw": 0.7871527117645002,
      "eval_ipcw_0th_event": 0.796788956110243,
      "eval_ipcw_0th_event_0.25": 0.8976798290305419,
      "eval_ipcw_0th_event_0.5": 0.8497882974453264,
      "eval_ipcw_0th_event_0.75": 0.8155506413091552,
      "eval_ipcw_0th_event_1.0": 0.796788956110243,
      "eval_ipcw_0th_event_n": 396,
      "eval_ipcw_1th_event": 0.7774181383948212,
      "eval_ipcw_1th_event_0.25": 0.8711834664189284,
      "eval_ipcw_1th_event_0.5": 0.8275174165796487,
      "eval_ipcw_1th_event_0.75": 0.8019460977730222,
      "eval_ipcw_1th_event_1.0": 0.7774181383948212,
      "eval_ipcw_1th_event_n": 392,
      "eval_ipcw_avg": 0.8297341053827109,
      "eval_ipcw_avg_0th_event": 0.8399519309738166,
      "eval_ipcw_avg_1th_event": 0.8195162797916051,
      "eval_ipcw_weighted_avg": 0.829785972517691,
      "eval_loss": 0.5047199726104736,
      "eval_runtime": 0.3059,
      "eval_samples_per_second": 4357.048,
      "eval_steps_per_second": 9.806,
      "step": 280
    },
    {
      "epoch": 48.36363636363637,
      "grad_norm": 3.3453738689422607,
      "learning_rate": 0.000233431082022221,
      "loss": 1.305,
      "step": 290
    },
    {
      "epoch": 48.36363636363637,
      "eval_brier_0th_event": 0.08399948471905298,
      "eval_brier_0th_event_n": 396,
      "eval_brier_1th_event": 0.0980520470757526,
      "eval_brier_1th_event_n": 392,
      "eval_brier_avg": 0.0910257658974028,
      "eval_brier_weighted_avg": 0.09099009949548224,
      "eval_ipcw": 0.7865124461749012,
      "eval_ipcw_0th_event": 0.7937617693016548,
      "eval_ipcw_0th_event_0.25": 0.8924497506695402,
      "eval_ipcw_0th_event_0.5": 0.8465512553249342,
      "eval_ipcw_0th_event_0.75": 0.8120418693793306,
      "eval_ipcw_0th_event_1.0": 0.7937617693016548,
      "eval_ipcw_0th_event_n": 396,
      "eval_ipcw_1th_event": 0.7791891503631809,
      "eval_ipcw_1th_event_0.25": 0.8724516504825736,
      "eval_ipcw_1th_event_0.5": 0.8291110141358727,
      "eval_ipcw_1th_event_0.75": 0.8039050134867027,
      "eval_ipcw_1th_event_1.0": 0.7791891503631809,
      "eval_ipcw_1th_event_n": 392,
      "eval_ipcw_avg": 0.8286826841429737,
      "eval_ipcw_avg_0th_event": 0.836201161168865,
      "eval_ipcw_avg_1th_event": 0.8211642071170826,
      "eval_ipcw_weighted_avg": 0.8287208490009733,
      "eval_loss": 0.5038745999336243,
      "eval_runtime": 0.2857,
      "eval_samples_per_second": 4665.716,
      "eval_steps_per_second": 10.5,
      "step": 290
    },
    {
      "epoch": 50.0,
      "grad_norm": 2.4000730514526367,
      "learning_rate": 0.00023006929207412794,
      "loss": 1.3187,
      "step": 300
    },
    {
      "epoch": 50.0,
      "eval_brier_0th_event": 0.08418427209340286,
      "eval_brier_0th_event_n": 396,
      "eval_brier_1th_event": 0.09475599726278107,
      "eval_brier_1th_event_n": 392,
      "eval_brier_avg": 0.08947013467809196,
      "eval_brier_weighted_avg": 0.08944330288832197,
      "eval_ipcw": 0.7884683679141699,
      "eval_ipcw_0th_event": 0.7933188206436333,
      "eval_ipcw_0th_event_0.25": 0.8982479237490645,
      "eval_ipcw_0th_event_0.5": 0.8488560293146534,
      "eval_ipcw_0th_event_0.75": 0.8124988942945599,
      "eval_ipcw_0th_event_1.0": 0.7933188206436333,
      "eval_ipcw_0th_event_n": 396,
      "eval_ipcw_1th_event": 0.7835684207690995,
      "eval_ipcw_1th_event_0.25": 0.8751797208520428,
      "eval_ipcw_1th_event_0.5": 0.8323917210853607,
      "eval_ipcw_1th_event_0.75": 0.8068113422055775,
      "eval_ipcw_1th_event_1.0": 0.7835684207690995,
      "eval_ipcw_1th_event_n": 392,
      "eval_ipcw_avg": 0.8313591091142489,
      "eval_ipcw_avg_0th_event": 0.8382304170004777,
      "eval_ipcw_avg_1th_event": 0.8244878012280201,
      "eval_ipcw_weighted_avg": 0.8313939888497119,
      "eval_loss": 0.4990098774433136,
      "eval_runtime": 0.2784,
      "eval_samples_per_second": 4787.317,
      "eval_steps_per_second": 10.774,
      "step": 300
    },
    {
      "epoch": 51.72727272727273,
      "grad_norm": 2.575902223587036,
      "learning_rate": 0.000226609608700259,
      "loss": 1.3741,
      "step": 310
    },
    {
      "epoch": 51.72727272727273,
      "eval_brier_0th_event": 0.08291253607313256,
      "eval_brier_0th_event_n": 396,
      "eval_brier_1th_event": 0.09499800331194497,
      "eval_brier_1th_event_n": 392,
      "eval_brier_avg": 0.08895526969253877,
      "eval_brier_weighted_avg": 0.08892459591782097,
      "eval_ipcw": 0.7911174023912552,
      "eval_ipcw_0th_event": 0.7963170711077278,
      "eval_ipcw_0th_event_0.25": 0.9033337240863143,
      "eval_ipcw_0th_event_0.5": 0.853690012214439,
      "eval_ipcw_0th_event_0.75": 0.8154179566563468,
      "eval_ipcw_0th_event_1.0": 0.7963170711077278,
      "eval_ipcw_0th_event_n": 396,
      "eval_ipcw_1th_event": 0.785864675830737,
      "eval_ipcw_1th_event_0.25": 0.8769566531737781,
      "eval_ipcw_1th_event_0.5": 0.8356451537490454,
      "eval_ipcw_1th_event_0.75": 0.8085584832475089,
      "eval_ipcw_1th_event_1.0": 0.785864675830737,
      "eval_ipcw_1th_event_n": 392,
      "eval_ipcw_avg": 0.8344729662582372,
      "eval_ipcw_avg_0th_event": 0.842189691016207,
      "eval_ipcw_avg_1th_event": 0.8267562415002674,
      "eval_ipcw_weighted_avg": 0.834512137449902,
      "eval_loss": 0.4966501295566559,
      "eval_runtime": 0.28,
      "eval_samples_per_second": 4760.139,
      "eval_steps_per_second": 10.713,
      "step": 310
    },
    {
      "epoch": 53.36363636363637,
      "grad_norm": 2.540680170059204,
      "learning_rate": 0.0002230557366162266,
      "loss": 1.3159,
      "step": 320
    },
    {
      "epoch": 53.36363636363637,
      "eval_brier_0th_event": 0.08252196919588883,
      "eval_brier_0th_event_n": 396,
      "eval_brier_1th_event": 0.094028848090296,
      "eval_brier_1th_event_n": 392,
      "eval_brier_avg": 0.08827540864309241,
      "eval_brier_weighted_avg": 0.08824620336671067,
      "eval_ipcw": 0.7943097575394374,
      "eval_ipcw_0th_event": 0.7975190423405496,
      "eval_ipcw_0th_event_0.25": 0.8999882774105702,
      "eval_ipcw_0th_event_0.5": 0.8525333091634189,
      "eval_ipcw_0th_event_0.75": 0.8158985699542975,
      "eval_ipcw_0th_event_1.0": 0.7975190423405496,
      "eval_ipcw_0th_event_n": 396,
      "eval_ipcw_1th_event": 0.7910677249342324,
      "eval_ipcw_1th_event_0.25": 0.8823243159547878,
      "eval_ipcw_1th_event_0.5": 0.841119492542431,
      "eval_ipcw_1th_event_0.75": 0.814245747787512,
      "eval_ipcw_1th_event_1.0": 0.7910677249342324,
      "eval_ipcw_1th_event_n": 392,
      "eval_ipcw_avg": 0.8368370600109749,
      "eval_ipcw_avg_0th_event": 0.8414847997172091,
      "eval_ipcw_avg_1th_event": 0.8321893203047408,
      "eval_ipcw_weighted_avg": 0.8368606525983162,
      "eval_loss": 0.4940233528614044,
      "eval_runtime": 0.3768,
      "eval_samples_per_second": 3537.564,
      "eval_steps_per_second": 7.962,
      "step": 320
    },
    {
      "epoch": 55.0,
      "grad_norm": 1.8489787578582764,
      "learning_rate": 0.00021941148139727307,
      "loss": 1.312,
      "step": 330
    },
    {
      "epoch": 55.0,
      "eval_brier_0th_event": 0.08290821012249495,
      "eval_brier_0th_event_n": 396,
      "eval_brier_1th_event": 0.0952428194882564,
      "eval_brier_1th_event_n": 392,
      "eval_brier_avg": 0.08907551480537568,
      "eval_brier_weighted_avg": 0.08904420869023413,
      "eval_ipcw": 0.7949603093935941,
      "eval_ipcw_0th_event": 0.7995512640730799,
      "eval_ipcw_0th_event_0.25": 0.899149661397513,
      "eval_ipcw_0th_event_0.5": 0.8527188995783214,
      "eval_ipcw_0th_event_0.75": 0.817608727701607,
      "eval_ipcw_0th_event_1.0": 0.7995512640730799,
      "eval_ipcw_0th_event_n": 396,
      "eval_ipcw_1th_event": 0.7903225082377869,
      "eval_ipcw_1th_event_0.25": 0.8812846999491252,
      "eval_ipcw_1th_event_0.5": 0.8401220329473372,
      "eval_ipcw_1th_event_0.75": 0.8147723979580463,
      "eval_ipcw_1th_event_1.0": 0.7903225082377869,
      "eval_ipcw_1th_event_n": 392,
      "eval_ipcw_avg": 0.8369412739803521,
      "eval_ipcw_avg_0th_event": 0.8422571381876303,
      "eval_ipcw_avg_1th_event": 0.831625409773074,
      "eval_ipcw_weighted_avg": 0.8369682580626225,
      "eval_loss": 0.4955809712409973,
      "eval_runtime": 0.2657,
      "eval_samples_per_second": 5017.673,
      "eval_steps_per_second": 11.293,
      "step": 330
    },
    {
      "epoch": 56.72727272727273,
      "grad_norm": 4.406787872314453,
      "learning_rate": 0.0002156807454031655,
      "loss": 1.3758,
      "step": 340
    },
    {
      "epoch": 56.72727272727273,
      "eval_brier_0th_event": 0.08258784441761477,
      "eval_brier_0th_event_n": 396,
      "eval_brier_1th_event": 0.09538701220292013,
      "eval_brier_1th_event_n": 392,
      "eval_brier_avg": 0.08898742831026746,
      "eval_brier_weighted_avg": 0.08895494311284283,
      "eval_ipcw": 0.796765655613211,
      "eval_ipcw_0th_event": 0.8030859498466374,
      "eval_ipcw_0th_event_0.25": 0.9026123339675555,
      "eval_ipcw_0th_event_0.5": 0.8554423310156112,
      "eval_ipcw_0th_event_0.75": 0.8208373875866136,
      "eval_ipcw_0th_event_1.0": 0.8030859498466374,
      "eval_ipcw_0th_event_n": 396,
      "eval_ipcw_1th_event": 0.7903808685814845,
      "eval_ipcw_1th_event_0.25": 0.8835335147131471,
      "eval_ipcw_1th_event_0.5": 0.8396895407010271,
      "eval_ipcw_1th_event_0.75": 0.8145578367774583,
      "eval_ipcw_1th_event_1.0": 0.7903808685814845,
      "eval_ipcw_1th_event_n": 392,
      "eval_ipcw_avg": 0.8387674703986918,
      "eval_ipcw_avg_0th_event": 0.8454945006041044,
      "eval_ipcw_avg_1th_event": 0.8320404401932792,
      "eval_ipcw_weighted_avg": 0.8388016177601405,
      "eval_loss": 0.49448952078819275,
      "eval_runtime": 0.2648,
      "eval_samples_per_second": 5034.449,
      "eval_steps_per_second": 11.33,
      "step": 340
    },
    {
      "epoch": 58.36363636363637,
      "grad_norm": 3.314816474914551,
      "learning_rate": 0.0002118675235994512,
      "loss": 1.3086,
      "step": 350
    },
    {
      "epoch": 58.36363636363637,
      "eval_brier_0th_event": 0.08254868392631107,
      "eval_brier_0th_event_n": 396,
      "eval_brier_1th_event": 0.09198256371227731,
      "eval_brier_1th_event_n": 392,
      "eval_brier_avg": 0.08726562381929419,
      "eval_brier_weighted_avg": 0.08724167996196941,
      "eval_ipcw": 0.7978209580999639,
      "eval_ipcw_0th_event": 0.8013041387876116,
      "eval_ipcw_0th_event_0.25": 0.9037845929105386,
      "eval_ipcw_0th_event_0.5": 0.8559041490247871,
      "eval_ipcw_0th_event_0.75": 0.8189945451864956,
      "eval_ipcw_0th_event_1.0": 0.8013041387876116,
      "eval_ipcw_0th_event_n": 396,
      "eval_ipcw_1th_event": 0.7943022347522379,
      "eval_ipcw_1th_event_0.25": 0.8873380669040826,
      "eval_ipcw_1th_event_0.5": 0.8437650982653554,
      "eval_ipcw_1th_event_0.75": 0.8185676229965001,
      "eval_ipcw_1th_event_1.0": 0.7943022347522379,
      "eval_ipcw_1th_event_n": 392,
      "eval_ipcw_avg": 0.8404950561034511,
      "eval_ipcw_avg_0th_event": 0.8449968564773582,
      "eval_ipcw_avg_1th_event": 0.835993255729544,
      "eval_ipcw_weighted_avg": 0.8405179078819988,
      "eval_loss": 0.4913366138935089,
      "eval_runtime": 0.2812,
      "eval_samples_per_second": 4740.13,
      "eval_steps_per_second": 10.668,
      "step": 350
    },
    {
      "epoch": 60.0,
      "grad_norm": 2.7353882789611816,
      "learning_rate": 0.0002079758992795483,
      "loss": 1.2987,
      "step": 360
    },
    {
      "epoch": 60.0,
      "eval_brier_0th_event": 0.08238541082192151,
      "eval_brier_0th_event_n": 396,
      "eval_brier_1th_event": 0.09209382925001251,
      "eval_brier_1th_event_n": 392,
      "eval_brier_avg": 0.08723962003596701,
      "eval_brier_weighted_avg": 0.08721497938005816,
      "eval_ipcw": 0.7970324538162445,
      "eval_ipcw_0th_event": 0.7992151573024204,
      "eval_ipcw_0th_event_0.25": 0.9045150004057819,
      "eval_ipcw_0th_event_0.5": 0.8564134436517288,
      "eval_ipcw_0th_event_0.75": 0.8170809376382132,
      "eval_ipcw_0th_event_1.0": 0.7992151573024204,
      "eval_ipcw_0th_event_n": 396,
      "eval_ipcw_1th_event": 0.7948274778455157,
      "eval_ipcw_1th_event_0.25": 0.8865638847722062,
      "eval_ipcw_1th_event_0.5": 0.8440066705110422,
      "eval_ipcw_1th_event_0.75": 0.8194843844044674,
      "eval_ipcw_1th_event_1.0": 0.7948274778455157,
      "eval_ipcw_1th_event_n": 392,
      "eval_ipcw_avg": 0.8402633695664219,
      "eval_ipcw_avg_0th_event": 0.844306134749536,
      "eval_ipcw_avg_1th_event": 0.8362206043833079,
      "eval_ipcw_weighted_avg": 0.8402838912170977,
      "eval_loss": 0.49266982078552246,
      "eval_runtime": 0.2797,
      "eval_samples_per_second": 4766.641,
      "eval_steps_per_second": 10.728,
      "step": 360
    },
    {
      "epoch": 61.72727272727273,
      "grad_norm": 3.0660014152526855,
      "learning_rate": 0.0002040100396922532,
      "loss": 1.3644,
      "step": 370
    },
    {
      "epoch": 61.72727272727273,
      "eval_brier_0th_event": 0.08223130595183867,
      "eval_brier_0th_event_n": 396,
      "eval_brier_1th_event": 0.09247351954245885,
      "eval_brier_1th_event_n": 392,
      "eval_brier_avg": 0.08735241274714875,
      "eval_brier_weighted_avg": 0.0873264172811827,
      "eval_ipcw": 0.7985684029541021,
      "eval_ipcw_0th_event": 0.7998940484616994,
      "eval_ipcw_0th_event_0.25": 0.9023327952965364,
      "eval_ipcw_0th_event_0.5": 0.8570004272895599,
      "eval_ipcw_0th_event_0.75": 0.8187734040984815,
      "eval_ipcw_0th_event_1.0": 0.7998940484616994,
      "eval_ipcw_0th_event_n": 396,
      "eval_ipcw_1th_event": 0.7972292304515295,
      "eval_ipcw_1th_event_0.25": 0.8876108739410294,
      "eval_ipcw_1th_event_0.5": 0.8465353864376666,
      "eval_ipcw_1th_event_0.75": 0.8209445150360017,
      "eval_ipcw_1th_event_1.0": 0.7972292304515295,
      "eval_ipcw_1th_event_n": 392,
      "eval_ipcw_avg": 0.8412900851265631,
      "eval_ipcw_avg_0th_event": 0.8445001687865694,
      "eval_ipcw_avg_1th_event": 0.8380800014665568,
      "eval_ipcw_weighted_avg": 0.8413063799674768,
      "eval_loss": 0.4911866784095764,
      "eval_runtime": 0.2752,
      "eval_samples_per_second": 4843.429,
      "eval_steps_per_second": 10.9,
      "step": 370
    },
    {
      "epoch": 63.36363636363637,
      "grad_norm": 3.080862045288086,
      "learning_rate": 0.00019997419157934576,
      "loss": 1.2954,
      "step": 380
    },
    {
      "epoch": 63.36363636363637,
      "eval_brier_0th_event": 0.08174152529397054,
      "eval_brier_0th_event_n": 396,
      "eval_brier_1th_event": 0.09266324525243523,
      "eval_brier_1th_event_n": 392,
      "eval_brier_avg": 0.08720238527320288,
      "eval_brier_weighted_avg": 0.08717466517178545,
      "eval_ipcw": 0.7995686139854169,
      "eval_ipcw_0th_event": 0.8008422702120366,
      "eval_ipcw_0th_event_0.25": 0.9028558031326366,
      "eval_ipcw_0th_event_0.5": 0.8577902655669356,
      "eval_ipcw_0th_event_0.75": 0.8193542680229987,
      "eval_ipcw_0th_event_1.0": 0.8008422702120366,
      "eval_ipcw_0th_event_n": 396,
      "eval_ipcw_1th_event": 0.7982819612666888,
      "eval_ipcw_1th_event_0.25": 0.8879426662832621,
      "eval_ipcw_1th_event_0.5": 0.8481952215451273,
      "eval_ipcw_1th_event_0.75": 0.8213067611850465,
      "eval_ipcw_1th_event_1.0": 0.7982819612666888,
      "eval_ipcw_1th_event_n": 392,
      "eval_ipcw_avg": 0.8420711521518415,
      "eval_ipcw_avg_0th_event": 0.8452106517336518,
      "eval_ipcw_avg_1th_event": 0.8389316525700311,
      "eval_ipcw_weighted_avg": 0.8420870886979421,
      "eval_loss": 0.49104559421539307,
      "eval_runtime": 0.2719,
      "eval_samples_per_second": 4902.173,
      "eval_steps_per_second": 11.033,
      "step": 380
    },
    {
      "epoch": 65.0,
      "grad_norm": 2.140117883682251,
      "learning_rate": 0.00019587267662807243,
      "loss": 1.306,
      "step": 390
    },
    {
      "epoch": 65.0,
      "eval_brier_0th_event": 0.08228166850465984,
      "eval_brier_0th_event_n": 396,
      "eval_brier_1th_event": 0.09087305543845113,
      "eval_brier_1th_event_n": 392,
      "eval_brier_avg": 0.0865773619715555,
      "eval_brier_weighted_avg": 0.08655555642096212,
      "eval_ipcw": 0.7981913391642554,
      "eval_ipcw_0th_event": 0.7990304098721904,
      "eval_ipcw_0th_event_0.25": 0.9009711714473791,
      "eval_ipcw_0th_event_0.5": 0.8554725434087348,
      "eval_ipcw_0th_event_0.75": 0.8161344537815126,
      "eval_ipcw_0th_event_1.0": 0.7990304098721904,
      "eval_ipcw_0th_event_n": 396,
      "eval_ipcw_1th_event": 0.7973437065103208,
      "eval_ipcw_1th_event_0.25": 0.8893361941206397,
      "eval_ipcw_1th_event_0.5": 0.8484056231784673,
      "eval_ipcw_1th_event_0.75": 0.820465235515727,
      "eval_ipcw_1th_event_1.0": 0.7973437065103208,
      "eval_ipcw_1th_event_n": 392,
      "eval_ipcw_avg": 0.8408949172293715,
      "eval_ipcw_avg_0th_event": 0.8429021446274543,
      "eval_ipcw_avg_1th_event": 0.8388876898312887,
      "eval_ipcw_weighted_avg": 0.8409051062009353,
      "eval_loss": 0.49007201194763184,
      "eval_runtime": 0.2764,
      "eval_samples_per_second": 4822.894,
      "eval_steps_per_second": 10.854,
      "step": 390
    },
    {
      "epoch": 66.72727272727273,
      "grad_norm": 3.042804002761841,
      "learning_rate": 0.0001917098868433747,
      "loss": 1.3655,
      "step": 400
    },
    {
      "epoch": 66.72727272727273,
      "eval_brier_0th_event": 0.08390788659134205,
      "eval_brier_0th_event_n": 396,
      "eval_brier_1th_event": 0.08977073486329001,
      "eval_brier_1th_event_n": 392,
      "eval_brier_avg": 0.08683931072731603,
      "eval_brier_weighted_avg": 0.08682443040175272,
      "eval_ipcw": 0.7986156443784863,
      "eval_ipcw_0th_event": 0.7977572107144606,
      "eval_ipcw_0th_event_0.25": 0.8974904641243676,
      "eval_ipcw_0th_event_0.5": 0.8516377275101104,
      "eval_ipcw_0th_event_0.75": 0.8138758661359281,
      "eval_ipcw_0th_event_1.0": 0.7977572107144606,
      "eval_ipcw_0th_event_n": 396,
      "eval_ipcw_1th_event": 0.7994828375696957,
      "eval_ipcw_1th_event_0.25": 0.8902136005367662,
      "eval_ipcw_1th_event_0.5": 0.850194037061858,
      "eval_ipcw_1th_event_0.75": 0.822691656077933,
      "eval_ipcw_1th_event_1.0": 0.7994828375696957,
      "eval_ipcw_1th_event_n": 392,
      "eval_ipcw_avg": 0.8404179249663899,
      "eval_ipcw_avg_0th_event": 0.8401903171212166,
      "eval_ipcw_avg_1th_event": 0.8406455328115633,
      "eval_ipcw_weighted_avg": 0.8404167695966175,
      "eval_loss": 0.4903043806552887,
      "eval_runtime": 0.2841,
      "eval_samples_per_second": 4692.344,
      "eval_steps_per_second": 10.56,
      "step": 400
    },
    {
      "epoch": 68.36363636363636,
      "grad_norm": 2.6533565521240234,
      "learning_rate": 0.00018749027984482056,
      "loss": 1.3003,
      "step": 410
    },
    {
      "epoch": 68.36363636363636,
      "eval_brier_0th_event": 0.08382247039128066,
      "eval_brier_0th_event_n": 396,
      "eval_brier_1th_event": 0.08993782452130078,
      "eval_brier_1th_event_n": 392,
      "eval_brier_avg": 0.08688014745629072,
      "eval_brier_weighted_avg": 0.08686462625291504,
      "eval_ipcw": 0.7992275900146597,
      "eval_ipcw_0th_event": 0.797801728167528,
      "eval_ipcw_0th_event_0.25": 0.8983651496433628,
      "eval_ipcw_0th_event_0.5": 0.851609673145067,
      "eval_ipcw_0th_event_0.75": 0.8136016511867905,
      "eval_ipcw_0th_event_1.0": 0.797801728167528,
      "eval_ipcw_0th_event_n": 396,
      "eval_ipcw_1th_event": 0.8006680014724764,
      "eval_ipcw_1th_event_0.25": 0.8894836573838543,
      "eval_ipcw_1th_event_0.5": 0.849948568489628,
      "eval_ipcw_1th_event_0.75": 0.8236780802068704,
      "eval_ipcw_1th_event_1.0": 0.8006680014724764,
      "eval_ipcw_1th_event_n": 392,
      "eval_ipcw_avg": 0.8406445637119471,
      "eval_ipcw_avg_0th_event": 0.840344550535687,
      "eval_ipcw_avg_1th_event": 0.8409445768882072,
      "eval_ipcw_weighted_avg": 0.840643040802423,
      "eval_loss": 0.48960354924201965,
      "eval_runtime": 0.2927,
      "eval_samples_per_second": 4554.466,
      "eval_steps_per_second": 10.25,
      "step": 410
    },
    {
      "epoch": 70.0,
      "grad_norm": 3.4081621170043945,
      "learning_rate": 0.00018321837409327366,
      "loss": 1.2971,
      "step": 420
    },
    {
      "epoch": 70.0,
      "eval_brier_0th_event": 0.08408180054106817,
      "eval_brier_0th_event_n": 396,
      "eval_brier_1th_event": 0.09164343834820564,
      "eval_brier_1th_event_n": 392,
      "eval_brier_avg": 0.08786261944463691,
      "eval_brier_weighted_avg": 0.08784342747050711,
      "eval_ipcw": 0.7985119958193849,
      "eval_ipcw_0th_event": 0.797979797979798,
      "eval_ipcw_0th_event_0.25": 0.8999702426576012,
      "eval_ipcw_0th_event_0.5": 0.8532540905422261,
      "eval_ipcw_0th_event_0.75": 0.8138729175880879,
      "eval_ipcw_0th_event_1.0": 0.797979797979798,
      "eval_ipcw_0th_event_n": 396,
      "eval_ipcw_1th_event": 0.7990496242491717,
      "eval_ipcw_1th_event_0.25": 0.887809949346369,
      "eval_ipcw_1th_event_0.5": 0.8474159562364603,
      "eval_ipcw_1th_event_0.75": 0.8230204641209122,
      "eval_ipcw_1th_event_1.0": 0.7990496242491717,
      "eval_ipcw_1th_event_n": 392,
      "eval_ipcw_avg": 0.8402966303400783,
      "eval_ipcw_avg_0th_event": 0.8412692621919283,
      "eval_ipcw_avg_1th_event": 0.8393239984882284,
      "eval_ipcw_weighted_avg": 0.8403015675576003,
      "eval_loss": 0.4919056296348572,
      "eval_runtime": 0.2811,
      "eval_samples_per_second": 4741.26,
      "eval_steps_per_second": 10.671,
      "step": 420
    },
    {
      "epoch": 71.72727272727273,
      "grad_norm": 2.6216156482696533,
      "learning_rate": 0.00017889874405241235,
      "loss": 1.3613,
      "step": 430
    },
    {
      "epoch": 71.72727272727273,
      "eval_brier_0th_event": 0.08346854641896927,
      "eval_brier_0th_event_n": 396,
      "eval_brier_1th_event": 0.08927044109243763,
      "eval_brier_1th_event_n": 392,
      "eval_brier_avg": 0.08636949375570345,
      "eval_brier_weighted_avg": 0.0863547681347048,
      "eval_ipcw": 0.8003216894153824,
      "eval_ipcw_0th_event": 0.7988545659325739,
      "eval_ipcw_0th_event_0.25": 0.9011064320946464,
      "eval_ipcw_0th_event_0.5": 0.8545014307726172,
      "eval_ipcw_0th_event_0.75": 0.8146071060002948,
      "eval_ipcw_0th_event_1.0": 0.7988545659325739,
      "eval_ipcw_0th_event_n": 396,
      "eval_ipcw_1th_event": 0.8018037835459745,
      "eval_ipcw_1th_event_0.25": 0.8932218511063431,
      "eval_ipcw_1th_event_0.5": 0.852309742374889,
      "eval_ipcw_1th_event_0.75": 0.8268853518803362,
      "eval_ipcw_1th_event_1.0": 0.8018037835459745,
      "eval_ipcw_1th_event_n": 392,
      "eval_ipcw_avg": 0.8429112829634594,
      "eval_ipcw_avg_0th_event": 0.8422673837000332,
      "eval_ipcw_avg_1th_event": 0.8435551822268856,
      "eval_ipcw_weighted_avg": 0.8429080144392795,
      "eval_loss": 0.4884200394153595,
      "eval_runtime": 0.2835,
      "eval_samples_per_second": 4701.727,
      "eval_steps_per_second": 10.582,
      "step": 430
    },
    {
      "epoch": 73.36363636363636,
      "grad_norm": 3.7232794761657715,
      "learning_rate": 0.00017453601529027936,
      "loss": 1.2882,
      "step": 440
    },
    {
      "epoch": 73.36363636363636,
      "eval_brier_0th_event": 0.08219320287660994,
      "eval_brier_0th_event_n": 396,
      "eval_brier_1th_event": 0.08788909223497329,
      "eval_brier_1th_event_n": 392,
      "eval_brier_avg": 0.08504114755579162,
      "eval_brier_weighted_avg": 0.08502669098381609,
      "eval_ipcw": 0.8023681545934206,
      "eval_ipcw_0th_event": 0.801047050496147,
      "eval_ipcw_0th_event_0.25": 0.9036042453808489,
      "eval_ipcw_0th_event_0.5": 0.8577945816230961,
      "eval_ipcw_0th_event_0.75": 0.817249004865104,
      "eval_ipcw_0th_event_1.0": 0.801047050496147,
      "eval_ipcw_0th_event_n": 396,
      "eval_ipcw_1th_event": 0.803702739344748,
      "eval_ipcw_1th_event_0.25": 0.8964218039180989,
      "eval_ipcw_1th_event_0.5": 0.8553021211601702,
      "eval_ipcw_1th_event_0.75": 0.8289390088945362,
      "eval_ipcw_1th_event_1.0": 0.803702739344748,
      "eval_ipcw_1th_event_n": 392,
      "eval_ipcw_avg": 0.8455075694603438,
      "eval_ipcw_avg_0th_event": 0.844923720591299,
      "eval_ipcw_avg_1th_event": 0.8460914183293884,
      "eval_ipcw_weighted_avg": 0.8455046057605009,
      "eval_loss": 0.48574790358543396,
      "eval_runtime": 0.2622,
      "eval_samples_per_second": 5083.302,
      "eval_steps_per_second": 11.44,
      "step": 440
    },
    {
      "epoch": 75.0,
      "grad_norm": 3.1289496421813965,
      "learning_rate": 0.00017013485952610755,
      "loss": 1.3065,
      "step": 450
    },
    {
      "epoch": 75.0,
      "eval_brier_0th_event": 0.08191935154288338,
      "eval_brier_0th_event_n": 396,
      "eval_brier_1th_event": 0.08844536892819596,
      "eval_brier_1th_event_n": 392,
      "eval_brier_avg": 0.08518236023553967,
      "eval_brier_weighted_avg": 0.08516579673963787,
      "eval_ipcw": 0.802578856188621,
      "eval_ipcw_0th_event": 0.8019262701942297,
      "eval_ipcw_0th_event_0.25": 0.9044699135233595,
      "eval_ipcw_0th_event_0.5": 0.8576694159944409,
      "eval_ipcw_0th_event_0.75": 0.8177532065457762,
      "eval_ipcw_0th_event_1.0": 0.8019262701942297,
      "eval_ipcw_0th_event_n": 396,
      "eval_ipcw_1th_event": 0.8032381012237715,
      "eval_ipcw_1th_event_0.25": 0.8946301252700422,
      "eval_ipcw_1th_event_0.5": 0.8537241089101195,
      "eval_ipcw_1th_event_0.75": 0.8276237767226198,
      "eval_ipcw_1th_event_1.0": 0.8032381012237715,
      "eval_ipcw_1th_event_n": 392,
      "eval_ipcw_avg": 0.8451293647980449,
      "eval_ipcw_avg_0th_event": 0.8454547015644516,
      "eval_ipcw_avg_1th_event": 0.8448040280316382,
      "eval_ipcw_weighted_avg": 0.8451310162537119,
      "eval_loss": 0.485283762216568,
      "eval_runtime": 0.2644,
      "eval_samples_per_second": 5040.708,
      "eval_steps_per_second": 11.344,
      "step": 450
    },
    {
      "epoch": 76.72727272727273,
      "grad_norm": 3.378244638442993,
      "learning_rate": 0.00016569998962772618,
      "loss": 1.3582,
      "step": 460
    },
    {
      "epoch": 76.72727272727273,
      "eval_brier_0th_event": 0.08337414863408539,
      "eval_brier_0th_event_n": 396,
      "eval_brier_1th_event": 0.08977128127230705,
      "eval_brier_1th_event_n": 392,
      "eval_brier_avg": 0.08657271495319621,
      "eval_brier_weighted_avg": 0.08655647857594184,
      "eval_ipcw": 0.8007502470270893,
      "eval_ipcw_0th_event": 0.8011271819116684,
      "eval_ipcw_0th_event_0.25": 0.9011515189770688,
      "eval_ipcw_0th_event_0.5": 0.8539532916402308,
      "eval_ipcw_0th_event_0.75": 0.8174023293527938,
      "eval_ipcw_0th_event_1.0": 0.8011271819116684,
      "eval_ipcw_0th_event_n": 396,
      "eval_ipcw_1th_event": 0.8003694658681775,
      "eval_ipcw_1th_event_0.25": 0.891275336031911,
      "eval_ipcw_1th_event_0.5": 0.8494888019575144,
      "eval_ipcw_1th_event_0.75": 0.8242493145188257,
      "eval_ipcw_1th_event_1.0": 0.8003694658681775,
      "eval_ipcw_1th_event_n": 392,
      "eval_ipcw_avg": 0.8423771550322738,
      "eval_ipcw_avg_0th_event": 0.8434085804704405,
      "eval_ipcw_avg_1th_event": 0.8413457295941071,
      "eval_ipcw_weighted_avg": 0.8423823906943965,
      "eval_loss": 0.4878467619419098,
      "eval_runtime": 0.2792,
      "eval_samples_per_second": 4773.893,
      "eval_steps_per_second": 10.744,
      "step": 460
    },
    {
      "epoch": 78.36363636363636,
      "grad_norm": 2.529439687728882,
      "learning_rate": 0.00016123615456490378,
      "loss": 1.2876,
      "step": 470
    },
    {
      "epoch": 78.36363636363636,
      "eval_brier_0th_event": 0.08220131305744066,
      "eval_brier_0th_event_n": 396,
      "eval_brier_1th_event": 0.0892729082826163,
      "eval_brier_1th_event_n": 392,
      "eval_brier_avg": 0.08573711067002848,
      "eval_brier_weighted_avg": 0.08571916245879707,
      "eval_ipcw": 0.8015963373158131,
      "eval_ipcw_0th_event": 0.8020442414448584,
      "eval_ipcw_0th_event_0.25": 0.9038567319224144,
      "eval_ipcw_0th_event_0.5": 0.8569054740540284,
      "eval_ipcw_0th_event_0.75": 0.818328173374613,
      "eval_ipcw_0th_event_1.0": 0.8020442414448584,
      "eval_ipcw_0th_event_n": 396,
      "eval_ipcw_1th_event": 0.8011438627364716,
      "eval_ipcw_1th_event_0.25": 0.8927131028482529,
      "eval_ipcw_1th_event_0.5": 0.849843367672958,
      "eval_ipcw_1th_event_0.75": 0.8252928620789585,
      "eval_ipcw_1th_event_1.0": 0.8011438627364716,
      "eval_ipcw_1th_event_n": 392,
      "eval_ipcw_avg": 0.8437659770165694,
      "eval_ipcw_avg_0th_event": 0.8452836551989785,
      "eval_ipcw_avg_1th_event": 0.8422482988341603,
      "eval_ipcw_weighted_avg": 0.8437736809667339,
      "eval_loss": 0.48644885420799255,
      "eval_runtime": 0.2749,
      "eval_samples_per_second": 4848.574,
      "eval_steps_per_second": 10.912,
      "step": 470
    },
    {
      "epoch": 80.0,
      "grad_norm": 2.211064100265503,
      "learning_rate": 0.0001567481343240325,
      "loss": 1.2893,
      "step": 480
    },
    {
      "epoch": 80.0,
      "eval_brier_0th_event": 0.0819531303517967,
      "eval_brier_0th_event_n": 396,
      "eval_brier_1th_event": 0.08975196993177685,
      "eval_brier_1th_event_n": 392,
      "eval_brier_avg": 0.08585255014178678,
      "eval_brier_weighted_avg": 0.08583275613270054,
      "eval_ipcw": 0.8021138960663604,
      "eval_ipcw_0th_event": 0.8026830668963767,
      "eval_ipcw_0th_event_0.25": 0.9028738378856056,
      "eval_ipcw_0th_event_0.5": 0.8582520835761115,
      "eval_ipcw_0th_event_0.75": 0.819422084623323,
      "eval_ipcw_0th_event_1.0": 0.8026830668963767,
      "eval_ipcw_0th_event_n": 396,
      "eval_ipcw_1th_event": 0.8015389173707318,
      "eval_ipcw_1th_event_0.25": 0.8930965073326108,
      "eval_ipcw_1th_event_0.5": 0.8505992550223649,
      "eval_ipcw_1th_event_0.75": 0.8263782072716734,
      "eval_ipcw_1th_event_1.0": 0.8015389173707318,
      "eval_ipcw_1th_event_n": 392,
      "eval_ipcw_avg": 0.8443554949973497,
      "eval_ipcw_avg_0th_event": 0.8458077682453542,
      "eval_ipcw_avg_1th_event": 0.8429032217493452,
      "eval_ipcw_weighted_avg": 0.8443628669427711,
      "eval_loss": 0.4872369170188904,
      "eval_runtime": 0.2837,
      "eval_samples_per_second": 4699.356,
      "eval_steps_per_second": 10.576,
      "step": 480
    },
    {
      "epoch": 81.72727272727273,
      "grad_norm": 2.8144288063049316,
      "learning_rate": 0.00015224073478959895,
      "loss": 1.351,
      "step": 490
    },
    {
      "epoch": 81.72727272727273,
      "eval_brier_0th_event": 0.08226476322923366,
      "eval_brier_0th_event_n": 396,
      "eval_brier_1th_event": 0.08863235047100185,
      "eval_brier_1th_event_n": 392,
      "eval_brier_avg": 0.08544855685011776,
      "eval_brier_weighted_avg": 0.08543239546117926,
      "eval_ipcw": 0.8018158148633558,
      "eval_ipcw_0th_event": 0.8014833215362083,
      "eval_ipcw_0th_event_0.25": 0.9030541854152953,
      "eval_ipcw_0th_event_0.5": 0.8576348875451567,
      "eval_ipcw_0th_event_0.75": 0.8186967418546366,
      "eval_ipcw_0th_event_1.0": 0.8014833215362083,
      "eval_ipcw_0th_event_n": 396,
      "eval_ipcw_1th_event": 0.8021517009795559,
      "eval_ipcw_1th_event_0.25": 0.8948808128175069,
      "eval_ipcw_1th_event_0.5": 0.8518967317612954,
      "eval_ipcw_1th_event_0.75": 0.826801756615172,
      "eval_ipcw_1th_event_1.0": 0.8021517009795559,
      "eval_ipcw_1th_event_n": 392,
      "eval_ipcw_avg": 0.8445750173156035,
      "eval_ipcw_avg_0th_event": 0.8452172840878243,
      "eval_ipcw_avg_1th_event": 0.8439327505433826,
      "eval_ipcw_weighted_avg": 0.8445782775530258,
      "eval_loss": 0.48588719964027405,
      "eval_runtime": 0.2842,
      "eval_samples_per_second": 4690.076,
      "eval_steps_per_second": 10.555,
      "step": 490
    },
    {
      "epoch": 83.36363636363636,
      "grad_norm": 2.6207587718963623,
      "learning_rate": 0.00014771878259792255,
      "loss": 1.2919,
      "step": 500
    },
    {
      "epoch": 83.36363636363636,
      "eval_brier_0th_event": 0.08249217182786267,
      "eval_brier_0th_event_n": 396,
      "eval_brier_1th_event": 0.0887103417895911,
      "eval_brier_1th_event_n": 392,
      "eval_brier_avg": 0.08560125680872688,
      "eval_brier_weighted_avg": 0.0855854746514636,
      "eval_ipcw": 0.80211188231674,
      "eval_ipcw_0th_event": 0.8004059991719754,
      "eval_ipcw_0th_event_0.25": 0.9026393860970089,
      "eval_ipcw_0th_event_0.5": 0.8575226700849832,
      "eval_ipcw_0th_event_0.75": 0.8175025799793602,
      "eval_ipcw_0th_event_1.0": 0.8004059991719754,
      "eval_ipcw_0th_event_n": 396,
      "eval_ipcw_1th_event": 0.8038351724323693,
      "eval_ipcw_1th_event_0.25": 0.8946743642490065,
      "eval_ipcw_1th_event_0.5": 0.8528980876829325,
      "eval_ipcw_1th_event_0.75": 0.8277463831115273,
      "eval_ipcw_1th_event_1.0": 0.8038351724323693,
      "eval_ipcw_1th_event_n": 392,
      "eval_ipcw_avg": 0.8446530803511454,
      "eval_ipcw_avg_0th_event": 0.844517658833332,
      "eval_ipcw_avg_1th_event": 0.8447885018689589,
      "eval_ipcw_weighted_avg": 0.8446523929322733,
      "eval_loss": 0.48553943634033203,
      "eval_runtime": 0.285,
      "eval_samples_per_second": 4676.863,
      "eval_steps_per_second": 10.526,
      "step": 500
    },
    {
      "epoch": 85.0,
      "grad_norm": 2.772686243057251,
      "learning_rate": 0.00014318711996867282,
      "loss": 1.2959,
      "step": 510
    },
    {
      "epoch": 85.0,
      "eval_brier_0th_event": 0.08260398091818207,
      "eval_brier_0th_event_n": 396,
      "eval_brier_1th_event": 0.08911005884073764,
      "eval_brier_1th_event_n": 392,
      "eval_brier_avg": 0.08585701987945984,
      "eval_brier_weighted_avg": 0.08584050699133154,
      "eval_ipcw": 0.8017789728908248,
      "eval_ipcw_0th_event": 0.8002279293597054,
      "eval_ipcw_0th_event_0.25": 0.90043012885831,
      "eval_ipcw_0th_event_0.5": 0.8564091275955683,
      "eval_ipcw_0th_event_0.75": 0.8168244139761167,
      "eval_ipcw_0th_event_1.0": 0.8002279293597054,
      "eval_ipcw_0th_event_n": 396,
      "eval_ipcw_1th_event": 0.8033458433967515,
      "eval_ipcw_1th_event_0.25": 0.8940181527277017,
      "eval_ipcw_1th_event_0.5": 0.8524110468650157,
      "eval_ipcw_1th_event_0.75": 0.8267906105798167,
      "eval_ipcw_1th_event_1.0": 0.8033458433967515,
      "eval_ipcw_1th_event_n": 392,
      "eval_ipcw_avg": 0.8438071566698733,
      "eval_ipcw_avg_0th_event": 0.843472899947425,
      "eval_ipcw_avg_1th_event": 0.8441414133923215,
      "eval_ipcw_weighted_avg": 0.8438054599352416,
      "eval_loss": 0.4863605797290802,
      "eval_runtime": 0.2724,
      "eval_samples_per_second": 4893.776,
      "eval_steps_per_second": 11.014,
      "step": 510
    },
    {
      "epoch": 86.72727272727273,
      "grad_norm": 2.706429958343506,
      "learning_rate": 0.00013865059951969887,
      "loss": 1.345,
      "step": 520
    },
    {
      "epoch": 86.72727272727273,
      "eval_brier_0th_event": 0.08283641247057748,
      "eval_brier_0th_event_n": 396,
      "eval_brier_1th_event": 0.08855524965697799,
      "eval_brier_1th_event_n": 392,
      "eval_brier_avg": 0.08569583106377773,
      "eval_brier_weighted_avg": 0.08568131624858384,
      "eval_ipcw": 0.8016280248373359,
      "eval_ipcw_0th_event": 0.7999964386037546,
      "eval_ipcw_0th_event_0.25": 0.9003219203404962,
      "eval_ipcw_0th_event_0.5": 0.8552955851061534,
      "eval_ipcw_0th_event_0.75": 0.8169688928202861,
      "eval_ipcw_0th_event_1.0": 0.7999964386037546,
      "eval_ipcw_0th_event_n": 396,
      "eval_ipcw_1th_event": 0.8032762599100353,
      "eval_ipcw_1th_event_0.25": 0.8940623917066661,
      "eval_ipcw_1th_event_0.5": 0.8533033056434394,
      "eval_ipcw_1th_event_0.75": 0.8271110590962795,
      "eval_ipcw_1th_event_1.0": 0.8032762599100353,
      "eval_ipcw_1th_event_n": 392,
      "eval_ipcw_avg": 0.8437919816533888,
      "eval_ipcw_avg_0th_event": 0.8431457092176726,
      "eval_ipcw_avg_1th_event": 0.844438254089105,
      "eval_ipcw_weighted_avg": 0.8437887010826491,
      "eval_loss": 0.4866637587547302,
      "eval_runtime": 0.3322,
      "eval_samples_per_second": 4012.752,
      "eval_steps_per_second": 9.031,
      "step": 520
    },
    {
      "epoch": 88.36363636363636,
      "grad_norm": 2.47554874420166,
      "learning_rate": 0.00013411407907072494,
      "loss": 1.2887,
      "step": 530
    },
    {
      "epoch": 88.36363636363636,
      "eval_brier_0th_event": 0.08365569207000396,
      "eval_brier_0th_event_n": 396,
      "eval_brier_1th_event": 0.08820516060674569,
      "eval_brier_1th_event_n": 392,
      "eval_brier_avg": 0.08593042633837483,
      "eval_brier_weighted_avg": 0.08591887946391609,
      "eval_ipcw": 0.8032035484366709,
      "eval_ipcw_0th_event": 0.8018639457599351,
      "eval_ipcw_0th_event_0.25": 0.9028918726385745,
      "eval_ipcw_0th_event_0.5": 0.8573327636139202,
      "eval_ipcw_0th_event_0.75": 0.8188058381247236,
      "eval_ipcw_0th_event_1.0": 0.8018639457599351,
      "eval_ipcw_0th_event_n": 396,
      "eval_ipcw_1th_event": 0.8045568205284753,
      "eval_ipcw_1th_event_0.25": 0.8941951086435592,
      "eval_ipcw_1th_event_0.5": 0.8544020697286598,
      "eval_ipcw_1th_event_0.75": 0.8279302926948884,
      "eval_ipcw_1th_event_1.0": 0.8045568205284753,
      "eval_ipcw_1th_event_n": 392,
      "eval_ipcw_avg": 0.845247338966592,
      "eval_ipcw_avg_0th_event": 0.8452236050342884,
      "eval_ipcw_avg_1th_event": 0.8452710728988957,
      "eval_ipcw_weighted_avg": 0.8452472184897784,
      "eval_loss": 0.4864139258861542,
      "eval_runtime": 0.2991,
      "eval_samples_per_second": 4457.255,
      "eval_steps_per_second": 10.031,
      "step": 530
    },
    {
      "epoch": 90.0,
      "grad_norm": 2.725031614303589,
      "learning_rate": 0.00012958241644147518,
      "loss": 1.2886,
      "step": 540
    },
    {
      "epoch": 90.0,
      "eval_brier_0th_event": 0.08204837390326408,
      "eval_brier_0th_event_n": 396,
      "eval_brier_1th_event": 0.08792814948015679,
      "eval_brier_1th_event_n": 392,
      "eval_brier_avg": 0.08498826169171043,
      "eval_brier_weighted_avg": 0.08497333840344422,
      "eval_ipcw": 0.8037283789788283,
      "eval_ipcw_0th_event": 0.8025183523200271,
      "eval_ipcw_0th_event_0.25": 0.9031443591801401,
      "eval_ipcw_0th_event_0.5": 0.8576909962752436,
      "eval_ipcw_0th_event_0.75": 0.8191006929087424,
      "eval_ipcw_0th_event_1.0": 0.8025183523200271,
      "eval_ipcw_0th_event_n": 396,
      "eval_ipcw_1th_event": 0.8049507528484336,
      "eval_ipcw_1th_event_0.25": 0.8947997080227388,
      "eval_ipcw_1th_event_0.5": 0.8547293611583,
      "eval_ipcw_1th_event_0.75": 0.8285154595510377,
      "eval_ipcw_1th_event_1.0": 0.8049507528484336,
      "eval_ipcw_1th_event_n": 392,
      "eval_ipcw_avg": 0.8456812102830829,
      "eval_ipcw_avg_0th_event": 0.8456136001710383,
      "eval_ipcw_avg_1th_event": 0.8457488203951276,
      "eval_ipcw_weighted_avg": 0.8456808670845446,
      "eval_loss": 0.4839414954185486,
      "eval_runtime": 0.2948,
      "eval_samples_per_second": 4522.342,
      "eval_steps_per_second": 10.178,
      "step": 540
    },
    {
      "epoch": 91.72727272727273,
      "grad_norm": 2.8636631965637207,
      "learning_rate": 0.00012506046424979884,
      "loss": 1.3554,
      "step": 550
    },
    {
      "epoch": 91.72727272727273,
      "eval_brier_0th_event": 0.08307147060342035,
      "eval_brier_0th_event_n": 396,
      "eval_brier_1th_event": 0.08765829582331502,
      "eval_brier_1th_event_n": 392,
      "eval_brier_avg": 0.08536488321336769,
      "eval_brier_weighted_avg": 0.08535324152499234,
      "eval_ipcw": 0.8037338951370633,
      "eval_ipcw_0th_event": 0.8024426726498124,
      "eval_ipcw_0th_event_0.25": 0.9036944191456937,
      "eval_ipcw_0th_event_0.5": 0.858139866115938,
      "eval_ipcw_0th_event_0.75": 0.8194309302668435,
      "eval_ipcw_0th_event_1.0": 0.8024426726498124,
      "eval_ipcw_0th_event_n": 396,
      "eval_ipcw_1th_event": 0.80503829336398,
      "eval_ipcw_1th_event_0.25": 0.8955886364809367,
      "eval_ipcw_1th_event_0.5": 0.8552164019762168,
      "eval_ipcw_1th_event_0.75": 0.8287885374172407,
      "eval_ipcw_1th_event_1.0": 0.80503829336398,
      "eval_ipcw_1th_event_n": 392,
      "eval_ipcw_avg": 0.8460424696770827,
      "eval_ipcw_avg_0th_event": 0.8459269720445719,
      "eval_ipcw_avg_1th_event": 0.8461579673095936,
      "eval_ipcw_weighted_avg": 0.8460418833946841,
      "eval_loss": 0.485225647687912,
      "eval_runtime": 0.2754,
      "eval_samples_per_second": 4839.517,
      "eval_steps_per_second": 10.892,
      "step": 550
    },
    {
      "epoch": 93.36363636363636,
      "grad_norm": 3.0490825176239014,
      "learning_rate": 0.00012055306471536529,
      "loss": 1.2861,
      "step": 560
    },
    {
      "epoch": 93.36363636363636,
      "eval_brier_0th_event": 0.08221030568639369,
      "eval_brier_0th_event_n": 396,
      "eval_brier_1th_event": 0.08723871243575386,
      "eval_brier_1th_event_n": 392,
      "eval_brier_avg": 0.08472450906107377,
      "eval_brier_weighted_avg": 0.0847117466073952,
      "eval_ipcw": 0.8040656372574797,
      "eval_ipcw_0th_event": 0.8013007999786316,
      "eval_ipcw_0th_event_0.25": 0.9021073608844243,
      "eval_ipcw_0th_event_0.5": 0.8572119140414255,
      "eval_ipcw_0th_event_0.75": 0.8187291758808787,
      "eval_ipcw_0th_event_1.0": 0.8013007999786316,
      "eval_ipcw_0th_event_n": 396,
      "eval_ipcw_1th_event": 0.8068586871616222,
      "eval_ipcw_1th_event_0.25": 0.8954338000545614,
      "eval_ipcw_1th_event_0.5": 0.8564943970824307,
      "eval_ipcw_1th_event_0.75": 0.8301734323101273,
      "eval_ipcw_1th_event_1.0": 0.8068586871616222,
      "eval_ipcw_1th_event_n": 392,
      "eval_ipcw_avg": 0.8460386959242627,
      "eval_ipcw_avg_0th_event": 0.84483731269634,
      "eval_ipcw_avg_1th_event": 0.8472400791521854,
      "eval_ipcw_weighted_avg": 0.8460325975322428,
      "eval_loss": 0.4843260943889618,
      "eval_runtime": 0.2703,
      "eval_samples_per_second": 4931.925,
      "eval_steps_per_second": 11.1,
      "step": 560
    },
    {
      "epoch": 95.0,
      "grad_norm": 2.6824843883514404,
      "learning_rate": 0.000116065044474494,
      "loss": 1.2892,
      "step": 570
    },
    {
      "epoch": 95.0,
      "eval_brier_0th_event": 0.08255218373116321,
      "eval_brier_0th_event_n": 396,
      "eval_brier_1th_event": 0.08756070380674753,
      "eval_brier_1th_event_n": 392,
      "eval_brier_avg": 0.08505644376895538,
      "eval_brier_weighted_avg": 0.0850437317890681,
      "eval_ipcw": 0.80395278411067,
      "eval_ipcw_0th_event": 0.8012162168178034,
      "eval_ipcw_0th_event_0.25": 0.9020532566255174,
      "eval_ipcw_0th_event_0.5": 0.8574795095233779,
      "eval_ipcw_0th_event_0.75": 0.8189974937343358,
      "eval_ipcw_0th_event_1.0": 0.8012162168178034,
      "eval_ipcw_0th_event_n": 396,
      "eval_ipcw_1th_event": 0.806717275559586,
      "eval_ipcw_1th_event_0.25": 0.894689110575328,
      "eval_ipcw_1th_event_0.5": 0.8558807256518555,
      "eval_ipcw_1th_event_0.75": 0.8294990971711362,
      "eval_ipcw_1th_event_1.0": 0.806717275559586,
      "eval_ipcw_1th_event_n": 392,
      "eval_ipcw_avg": 0.8458165857073676,
      "eval_ipcw_avg_0th_event": 0.8449366191752586,
      "eval_ipcw_avg_1th_event": 0.8466965522394765,
      "eval_ipcw_weighted_avg": 0.8458121188721792,
      "eval_loss": 0.4840632379055023,
      "eval_runtime": 0.2735,
      "eval_samples_per_second": 4873.82,
      "eval_steps_per_second": 10.969,
      "step": 570
    },
    {
      "epoch": 96.72727272727273,
      "grad_norm": 3.6889519691467285,
      "learning_rate": 0.00011160120941167159,
      "loss": 1.3545,
      "step": 580
    },
    {
      "epoch": 96.72727272727273,
      "eval_brier_0th_event": 0.0829774671566927,
      "eval_brier_0th_event_n": 396,
      "eval_brier_1th_event": 0.08788062702246523,
      "eval_brier_1th_event_n": 392,
      "eval_brier_avg": 0.08542904708957896,
      "eval_brier_weighted_avg": 0.08541660252139173,
      "eval_ipcw": 0.8045647174438764,
      "eval_ipcw_0th_event": 0.8025094488294136,
      "eval_ipcw_0th_event_0.25": 0.9033697935922522,
      "eval_ipcw_0th_event_0.5": 0.8587139015852874,
      "eval_ipcw_0th_event_0.75": 0.8206545776205219,
      "eval_ipcw_0th_event_1.0": 0.8025094488294136,
      "eval_ipcw_0th_event_n": 396,
      "eval_ipcw_1th_event": 0.8066409581870584,
      "eval_ipcw_1th_event_0.25": 0.8948586933280247,
      "eval_ipcw_1th_event_0.5": 0.8550060003428768,
      "eval_ipcw_1th_event_0.75": 0.8293346931496467,
      "eval_ipcw_1th_event_1.0": 0.8066409581870584,
      "eval_ipcw_1th_event_n": 392,
      "eval_ipcw_avg": 0.8463860083293852,
      "eval_ipcw_avg_0th_event": 0.8463119304068687,
      "eval_ipcw_avg_1th_event": 0.8464600862519016,
      "eval_ipcw_weighted_avg": 0.8463856322993216,
      "eval_loss": 0.4845755398273468,
      "eval_runtime": 0.2665,
      "eval_samples_per_second": 5002.458,
      "eval_steps_per_second": 11.258,
      "step": 580
    },
    {
      "epoch": 98.36363636363636,
      "grad_norm": 3.1045961380004883,
      "learning_rate": 0.0001071663395132902,
      "loss": 1.279,
      "step": 590
    },
    {
      "epoch": 98.36363636363636,
      "eval_brier_0th_event": 0.0815938263437954,
      "eval_brier_0th_event_n": 396,
      "eval_brier_1th_event": 0.08831187329975153,
      "eval_brier_1th_event_n": 392,
      "eval_brier_avg": 0.08495284982177347,
      "eval_brier_weighted_avg": 0.0849357989411746,
      "eval_ipcw": 0.8033943258691112,
      "eval_ipcw_0th_event": 0.801047050496147,
      "eval_ipcw_0th_event_0.25": 0.90262135134404,
      "eval_ipcw_0th_event_0.5": 0.8581916587898641,
      "eval_ipcw_0th_event_0.75": 0.8188972431077695,
      "eval_ipcw_0th_event_1.0": 0.801047050496147,
      "eval_ipcw_0th_event_n": 396,
      "eval_ipcw_1th_event": 0.8057655530315954,
      "eval_ipcw_1th_event_0.25": 0.8952347246492217,
      "eval_ipcw_1th_event_0.5": 0.8540007480946963,
      "eval_ipcw_1th_event_0.75": 0.8289529414387302,
      "eval_ipcw_1th_event_1.0": 0.8057655530315954,
      "eval_ipcw_1th_event_n": 392,
      "eval_ipcw_avg": 0.845588908869008,
      "eval_ipcw_avg_0th_event": 0.8451893259344551,
      "eval_ipcw_avg_1th_event": 0.8459884918035608,
      "eval_ipcw_weighted_avg": 0.8455868805292386,
      "eval_loss": 0.48590952157974243,
      "eval_runtime": 0.28,
      "eval_samples_per_second": 4760.747,
      "eval_steps_per_second": 10.714,
      "step": 590
    },
    {
      "epoch": 100.0,
      "grad_norm": 2.7708308696746826,
      "learning_rate": 0.00010276518374911837,
      "loss": 1.2835,
      "step": 600
    },
    {
      "epoch": 100.0,
      "eval_brier_0th_event": 0.08208499794161773,
      "eval_brier_0th_event_n": 396,
      "eval_brier_1th_event": 0.08841784472994806,
      "eval_brier_1th_event_n": 392,
      "eval_brier_avg": 0.0852514213357829,
      "eval_brier_weighted_avg": 0.08523534812058409,
      "eval_ipcw": 0.804134341453663,
      "eval_ipcw_0th_event": 0.8019685617746437,
      "eval_ipcw_0th_event_0.25": 0.9012867796243361,
      "eval_ipcw_0th_event_0.5": 0.8581269179474563,
      "eval_ipcw_0th_event_0.75": 0.8192127377266696,
      "eval_ipcw_0th_event_1.0": 0.8019685617746437,
      "eval_ipcw_0th_event_n": 396,
      "eval_ipcw_1th_event": 0.8063222209253257,
      "eval_ipcw_1th_event_0.25": 0.8950135297544,
      "eval_ipcw_1th_event_0.5": 0.8540825709521064,
      "eval_ipcw_1th_event_0.75": 0.8293514122026795,
      "eval_ipcw_1th_event_1.0": 0.8063222209253257,
      "eval_ipcw_1th_event_n": 392,
      "eval_ipcw_avg": 0.8456705913634521,
      "eval_ipcw_avg_0th_event": 0.8451487492682764,
      "eval_ipcw_avg_1th_event": 0.8461924334586279,
      "eval_ipcw_weighted_avg": 0.8456679424188065,
      "eval_loss": 0.48522821068763733,
      "eval_runtime": 0.2825,
      "eval_samples_per_second": 4718.249,
      "eval_steps_per_second": 10.619,
      "step": 600
    },
    {
      "epoch": 101.72727272727273,
      "grad_norm": 4.160548686981201,
      "learning_rate": 9.84024549869854e-05,
      "loss": 1.3471,
      "step": 610
    },
    {
      "epoch": 101.72727272727273,
      "eval_brier_0th_event": 0.08165626226959288,
      "eval_brier_0th_event_n": 396,
      "eval_brier_1th_event": 0.08803780408379516,
      "eval_brier_1th_event_n": 392,
      "eval_brier_avg": 0.08484703317669402,
      "eval_brier_weighted_avg": 0.084830836370059,
      "eval_ipcw": 0.8042656099273738,
      "eval_ipcw_0th_event": 0.8020431285085318,
      "eval_ipcw_0th_event_0.25": 0.902918924768028,
      "eval_ipcw_0th_event_0.5": 0.8594131026832921,
      "eval_ipcw_0th_event_0.75": 0.8200058970956804,
      "eval_ipcw_0th_event_1.0": 0.8020431285085318,
      "eval_ipcw_0th_event_n": 396,
      "eval_ipcw_1th_event": 0.8065107697280408,
      "eval_ipcw_1th_event_0.25": 0.8948955591438283,
      "eval_ipcw_1th_event_0.5": 0.8540007480946963,
      "eval_ipcw_1th_event_0.75": 0.8287021556432377,
      "eval_ipcw_1th_event_1.0": 0.8065107697280408,
      "eval_ipcw_1th_event_n": 392,
      "eval_ipcw_avg": 0.8460612857081669,
      "eval_ipcw_avg_0th_event": 0.8460952632638831,
      "eval_ipcw_avg_1th_event": 0.8460273081524508,
      "eval_ipcw_weighted_avg": 0.8460614581830691,
      "eval_loss": 0.4841074049472809,
      "eval_runtime": 0.2746,
      "eval_samples_per_second": 4853.575,
      "eval_steps_per_second": 10.923,
      "step": 610
    },
    {
      "epoch": 103.36363636363636,
      "grad_norm": 3.3467698097229004,
      "learning_rate": 9.40828249461241e-05,
      "loss": 1.2859,
      "step": 620
    },
    {
      "epoch": 103.36363636363636,
      "eval_brier_0th_event": 0.08101745483267087,
      "eval_brier_0th_event_n": 396,
      "eval_brier_1th_event": 0.08807954040805127,
      "eval_brier_1th_event_n": 392,
      "eval_brier_avg": 0.08454849762036107,
      "eval_brier_weighted_avg": 0.08453057354529667,
      "eval_ipcw": 0.8052661829119745,
      "eval_ipcw_0th_event": 0.8040319457243212,
      "eval_ipcw_0th_event_0.25": 0.9045781220411734,
      "eval_ipcw_0th_event_0.5": 0.8602374694099519,
      "eval_ipcw_0th_event_0.75": 0.8213592805543269,
      "eval_ipcw_0th_event_1.0": 0.8040319457243212,
      "eval_ipcw_0th_event_n": 396,
      "eval_ipcw_1th_event": 0.8065130143566446,
      "eval_ipcw_1th_event_0.25": 0.8949766639385963,
      "eval_ipcw_1th_event_0.5": 0.8545968860558266,
      "eval_ipcw_1th_event_0.75": 0.8289919525624735,
      "eval_ipcw_1th_event_1.0": 0.8065130143566446,
      "eval_ipcw_1th_event_n": 392,
      "eval_ipcw_avg": 0.8469106668304143,
      "eval_ipcw_avg_0th_event": 0.8475517044324434,
      "eval_ipcw_avg_1th_event": 0.8462696292283852,
      "eval_ipcw_weighted_avg": 0.8469139208283942,
      "eval_loss": 0.4828783869743347,
      "eval_runtime": 0.2974,
      "eval_samples_per_second": 4481.636,
      "eval_steps_per_second": 10.086,
      "step": 620
    },
    {
      "epoch": 105.0,
      "grad_norm": 2.3397977352142334,
      "learning_rate": 8.981091919457719e-05,
      "loss": 1.2766,
      "step": 630
    },
    {
      "epoch": 105.0,
      "eval_brier_0th_event": 0.08160034840500954,
      "eval_brier_0th_event_n": 396,
      "eval_brier_1th_event": 0.08734483659432588,
      "eval_brier_1th_event_n": 392,
      "eval_brier_avg": 0.08447259249966771,
      "eval_brier_weighted_avg": 0.08445801258040549,
      "eval_ipcw": 0.8056587479479843,
      "eval_ipcw_0th_event": 0.8034843810515913,
      "eval_ipcw_0th_event_0.25": 0.9055429813250133,
      "eval_ipcw_0th_event_0.5": 0.8601036716689757,
      "eval_ipcw_0th_event_0.75": 0.8207076514816453,
      "eval_ipcw_0th_event_1.0": 0.8034843810515913,
      "eval_ipcw_0th_event_n": 396,
      "eval_ipcw_1th_event": 0.8078553022616878,
      "eval_ipcw_1th_event_0.25": 0.8959720409652945,
      "eval_ipcw_1th_event_0.5": 0.8556449978959837,
      "eval_ipcw_1th_event_0.75": 0.8305719030740766,
      "eval_ipcw_1th_event_1.0": 0.8078553022616878,
      "eval_ipcw_1th_event_n": 392,
      "eval_ipcw_avg": 0.8474853662155335,
      "eval_ipcw_avg_0th_event": 0.8474596713818063,
      "eval_ipcw_avg_1th_event": 0.8475110610492607,
      "eval_ipcw_weighted_avg": 0.8474852357849054,
      "eval_loss": 0.483237624168396,
      "eval_runtime": 0.2831,
      "eval_samples_per_second": 4708.264,
      "eval_steps_per_second": 10.596,
      "step": 630
    }
  ],
  "logging_steps": 10,
  "max_steps": 1000,
  "num_input_tokens_seen": 0,
  "num_train_epochs": 200,
  "save_steps": 10,
  "stateful_callbacks": {
    "EarlyStoppingCallback": {
      "args": {
        "early_stopping_patience": 10,
        "early_stopping_threshold": 0.0
      },
      "attributes": {
        "early_stopping_patience_counter": 0
      }
    },
    "TrainerControl": {
      "args": {
        "should_epoch_stop": false,
        "should_evaluate": false,
        "should_log": false,
        "should_save": true,
        "should_training_stop": false
      },
      "attributes": {}
    }
  },
  "total_flos": 943025384700.0,
  "train_batch_size": 256,
  "trial_name": null,
  "trial_params": null
}
