{
  "best_global_step": 420,
  "best_metric": 0.8413049704025202,
  "best_model_checkpoint": "./data/model-hub/hsa_synthetic/survival_trial_1744267658/checkpoint-420",
  "epoch": 86.72727272727273,
  "eval_steps": 10,
  "global_step": 520,
  "is_hyper_param_search": false,
  "is_local_process_zero": true,
  "is_world_process_zero": true,
  "log_history": [
    {
      "epoch": 1.7272727272727273,
      "grad_norm": 9.79626178741455,
      "learning_rate": 0.0009163864136235377,
      "loss": 2.7717,
      "step": 10
    },
    {
      "epoch": 3.3636363636363638,
      "grad_norm": 3.407816171646118,
      "learning_rate": 0.0018327728272470754,
      "loss": 1.4899,
      "step": 20
    },
    {
      "epoch": 5.0,
      "grad_norm": 0.7522991895675659,
      "learning_rate": 0.002749159240870613,
      "loss": 1.2273,
      "step": 30
    },
    {
      "epoch": 6.7272727272727275,
      "grad_norm": 0.7457550764083862,
      "learning_rate": 0.003665545654494151,
      "loss": 1.171,
      "step": 40
    },
    {
      "epoch": 6.7272727272727275,
      "eval_brier_0th_event": 0.11824911865089614,
      "eval_brier_0th_event_n": 398,
      "eval_brier_1th_event": 0.12745746850466033,
      "eval_brier_1th_event_n": 381,
      "eval_brier_avg": 0.12285329357777824,
      "eval_brier_weighted_avg": 0.12275281735986168,
      "eval_ipcw": 0.6164129983981874,
      "eval_ipcw_0th_event": 0.67576080668007,
      "eval_ipcw_0th_event_0.25": 0.7281477607754864,
      "eval_ipcw_0th_event_0.5": 0.7335216227121006,
      "eval_ipcw_0th_event_0.75": 0.6987951098922095,
      "eval_ipcw_0th_event_1.0": 0.67576080668007,
      "eval_ipcw_0th_event_n": 398,
      "eval_ipcw_1th_event": 0.5544171251798429,
      "eval_ipcw_1th_event_0.25": 0.6061926683716965,
      "eval_ipcw_1th_event_0.5": 0.6259227868469863,
      "eval_ipcw_1th_event_0.75": 0.5794463715473537,
      "eval_ipcw_1th_event_1.0": 0.5544171251798429,
      "eval_ipcw_1th_event_n": 381,
      "eval_ipcw_avg": 0.6502755315007183,
      "eval_ipcw_avg_0th_event": 0.7090563250149666,
      "eval_ipcw_avg_1th_event": 0.5914947379864699,
      "eval_ipcw_weighted_avg": 0.6515582959291422,
      "eval_loss": 0.5933226346969604,
      "eval_runtime": 0.2782,
      "eval_samples_per_second": 4791.174,
      "eval_steps_per_second": 10.783,
      "step": 40
    },
    {
      "epoch": 8.363636363636363,
      "grad_norm": 0.8415721654891968,
      "learning_rate": 0.003664564364969466,
      "loss": 1.0813,
      "step": 50
    },
    {
      "epoch": 8.363636363636363,
      "eval_brier_0th_event": 0.11073417569430147,
      "eval_brier_0th_event_n": 398,
      "eval_brier_1th_event": 0.12390675208122039,
      "eval_brier_1th_event_n": 381,
      "eval_brier_avg": 0.11732046388776093,
      "eval_brier_weighted_avg": 0.11717673230972653,
      "eval_ipcw": 0.6270318789098818,
      "eval_ipcw_0th_event": 0.6813024097106618,
      "eval_ipcw_0th_event_0.25": 0.7327558112215123,
      "eval_ipcw_0th_event_0.5": 0.7424674059673876,
      "eval_ipcw_0th_event_0.75": 0.7105853373192591,
      "eval_ipcw_0th_event_1.0": 0.6813024097106618,
      "eval_ipcw_0th_event_n": 398,
      "eval_ipcw_1th_event": 0.5703398283620852,
      "eval_ipcw_1th_event_0.25": 0.622693947144075,
      "eval_ipcw_1th_event_0.5": 0.6094630946677967,
      "eval_ipcw_1th_event_0.75": 0.5916631519752565,
      "eval_ipcw_1th_event_1.0": 0.5703398283620852,
      "eval_ipcw_1th_event_n": 381,
      "eval_ipcw_avg": 0.6576588732960043,
      "eval_ipcw_avg_0th_event": 0.7167777410547053,
      "eval_ipcw_avg_1th_event": 0.5985400055373034,
      "eval_ipcw_weighted_avg": 0.6589490154678886,
      "eval_loss": 0.5825510621070862,
      "eval_runtime": 0.2461,
      "eval_samples_per_second": 5415.439,
      "eval_steps_per_second": 12.188,
      "step": 50
    },
    {
      "epoch": 10.0,
      "grad_norm": 0.7188593149185181,
      "learning_rate": 0.003661621547184813,
      "loss": 1.084,
      "step": 60
    },
    {
      "epoch": 10.0,
      "eval_brier_0th_event": 0.11378231007571654,
      "eval_brier_0th_event_n": 398,
      "eval_brier_1th_event": 0.12178674078172096,
      "eval_brier_1th_event_n": 381,
      "eval_brier_avg": 0.11778452542871876,
      "eval_brier_weighted_avg": 0.11769718568417313,
      "eval_ipcw": 0.6663492609952898,
      "eval_ipcw_0th_event": 0.6947374720980287,
      "eval_ipcw_0th_event_0.25": 0.7294134588420758,
      "eval_ipcw_0th_event_0.5": 0.7460375682141446,
      "eval_ipcw_0th_event_0.75": 0.7249093907353681,
      "eval_ipcw_0th_event_1.0": 0.6947374720980287,
      "eval_ipcw_0th_event_n": 398,
      "eval_ipcw_1th_event": 0.6366943843052894,
      "eval_ipcw_1th_event_0.25": 0.6928354646206308,
      "eval_ipcw_1th_event_0.5": 0.6624248156473531,
      "eval_ipcw_1th_event_0.75": 0.651904962744271,
      "eval_ipcw_1th_event_1.0": 0.6366943843052894,
      "eval_ipcw_1th_event_n": 381,
      "eval_ipcw_avg": 0.6923696896508952,
      "eval_ipcw_avg_0th_event": 0.7237744724724043,
      "eval_ipcw_avg_1th_event": 0.660964906829386,
      "eval_ipcw_weighted_avg": 0.6930550315096443,
      "eval_loss": 0.5802362561225891,
      "eval_runtime": 0.2682,
      "eval_samples_per_second": 4970.615,
      "eval_steps_per_second": 11.187,
      "step": 60
    },
    {
      "epoch": 11.727272727272727,
      "grad_norm": 0.6559674143791199,
      "learning_rate": 0.0036567203523831856,
      "loss": 1.1277,
      "step": 70
    },
    {
      "epoch": 11.727272727272727,
      "eval_brier_0th_event": 0.1046938139933036,
      "eval_brier_0th_event_n": 398,
      "eval_brier_1th_event": 0.12160053927217097,
      "eval_brier_1th_event_n": 381,
      "eval_brier_avg": 0.1131471766327373,
      "eval_brier_weighted_avg": 0.11296270016948906,
      "eval_ipcw": 0.6701177291836297,
      "eval_ipcw_0th_event": 0.7206012417624071,
      "eval_ipcw_0th_event_0.25": 0.7717271852239225,
      "eval_ipcw_0th_event_0.5": 0.7865605399259069,
      "eval_ipcw_0th_event_0.75": 0.7575963338888938,
      "eval_ipcw_0th_event_1.0": 0.7206012417624071,
      "eval_ipcw_0th_event_n": 398,
      "eval_ipcw_1th_event": 0.6173816714241718,
      "eval_ipcw_1th_event_0.25": 0.6660051150895141,
      "eval_ipcw_1th_event_0.5": 0.6306436886088285,
      "eval_ipcw_1th_event_0.75": 0.6283378809136476,
      "eval_ipcw_1th_event_1.0": 0.6173816714241718,
      "eval_ipcw_1th_event_n": 381,
      "eval_ipcw_avg": 0.6973567071046616,
      "eval_ipcw_avg_0th_event": 0.7591213252002826,
      "eval_ipcw_avg_1th_event": 0.6355920890090405,
      "eval_ipcw_weighted_avg": 0.6987045870887766,
      "eval_loss": 0.5683110356330872,
      "eval_runtime": 0.2365,
      "eval_samples_per_second": 5636.011,
      "eval_steps_per_second": 12.684,
      "step": 70
    },
    {
      "epoch": 13.363636363636363,
      "grad_norm": 0.42617690563201904,
      "learning_rate": 0.003649866028886739,
      "loss": 1.0483,
      "step": 80
    },
    {
      "epoch": 13.363636363636363,
      "eval_brier_0th_event": 0.1078575462681902,
      "eval_brier_0th_event_n": 398,
      "eval_brier_1th_event": 0.119467325443879,
      "eval_brier_1th_event_n": 381,
      "eval_brier_avg": 0.11366243585603461,
      "eval_brier_weighted_avg": 0.11353575662241028,
      "eval_ipcw": 0.7016995046469507,
      "eval_ipcw_0th_event": 0.7237688220546934,
      "eval_ipcw_0th_event_0.25": 0.7520596014945847,
      "eval_ipcw_0th_event_0.5": 0.7731194496407422,
      "eval_ipcw_0th_event_0.75": 0.7503652295581678,
      "eval_ipcw_0th_event_1.0": 0.7237688220546934,
      "eval_ipcw_0th_event_n": 398,
      "eval_ipcw_1th_event": 0.6786454670399125,
      "eval_ipcw_1th_event_0.25": 0.7441023017902814,
      "eval_ipcw_1th_event_0.5": 0.7113801165280695,
      "eval_ipcw_1th_event_0.75": 0.7119201117815325,
      "eval_ipcw_1th_event_1.0": 0.6786454670399125,
      "eval_ipcw_1th_event_n": 381,
      "eval_ipcw_avg": 0.7306701374859981,
      "eval_ipcw_avg_0th_event": 0.749828275687047,
      "eval_ipcw_avg_1th_event": 0.711511999284949,
      "eval_ipcw_weighted_avg": 0.7310882226585498,
      "eval_loss": 0.5643471479415894,
      "eval_runtime": 0.2411,
      "eval_samples_per_second": 5529.585,
      "eval_steps_per_second": 12.445,
      "step": 80
    },
    {
      "epoch": 15.0,
      "grad_norm": 0.6691431999206543,
      "learning_rate": 0.0036410659164767545,
      "loss": 1.0488,
      "step": 90
    },
    {
      "epoch": 15.0,
      "eval_brier_0th_event": 0.10318406750023924,
      "eval_brier_0th_event_n": 398,
      "eval_brier_1th_event": 0.11555287963972749,
      "eval_brier_1th_event_n": 381,
      "eval_brier_avg": 0.10936847356998336,
      "eval_brier_weighted_avg": 0.1092335122051751,
      "eval_ipcw": 0.7158692324460296,
      "eval_ipcw_0th_event": 0.7490850813396492,
      "eval_ipcw_0th_event_0.25": 0.7791622139863426,
      "eval_ipcw_0th_event_0.5": 0.7986404039663035,
      "eval_ipcw_0th_event_0.75": 0.7808593256260343,
      "eval_ipcw_0th_event_1.0": 0.7490850813396492,
      "eval_ipcw_0th_event_n": 398,
      "eval_ipcw_1th_event": 0.681171311554532,
      "eval_ipcw_1th_event_0.25": 0.7545098039215686,
      "eval_ipcw_1th_event_0.5": 0.7112798024836938,
      "eval_ipcw_1th_event_0.75": 0.7001925190151979,
      "eval_ipcw_1th_event_1.0": 0.681171311554532,
      "eval_ipcw_1th_event_n": 381,
      "eval_ipcw_avg": 0.7443625577366653,
      "eval_ipcw_avg_0th_event": 0.7769367562295825,
      "eval_ipcw_avg_1th_event": 0.7117883592437481,
      "eval_ipcw_weighted_avg": 0.7450734195779742,
      "eval_loss": 0.5544032454490662,
      "eval_runtime": 0.2454,
      "eval_samples_per_second": 5431.532,
      "eval_steps_per_second": 12.224,
      "step": 90
    },
    {
      "epoch": 16.727272727272727,
      "grad_norm": 0.7126924395561218,
      "learning_rate": 0.0036303294385340197,
      "loss": 1.0898,
      "step": 100
    },
    {
      "epoch": 16.727272727272727,
      "eval_brier_0th_event": 0.10279629429487451,
      "eval_brier_0th_event_n": 398,
      "eval_brier_1th_event": 0.11476638331087517,
      "eval_brier_1th_event_n": 381,
      "eval_brier_avg": 0.10878133880287484,
      "eval_brier_weighted_avg": 0.10865072807548587,
      "eval_ipcw": 0.7286031464903087,
      "eval_ipcw_0th_event": 0.7608554461766264,
      "eval_ipcw_0th_event_0.25": 0.8122977346278317,
      "eval_ipcw_0th_event_0.5": 0.8143108078918518,
      "eval_ipcw_0th_event_0.75": 0.7950951948429881,
      "eval_ipcw_0th_event_1.0": 0.7608554461766264,
      "eval_ipcw_0th_event_n": 398,
      "eval_ipcw_1th_event": 0.6949117678153628,
      "eval_ipcw_1th_event_0.25": 0.766001705029838,
      "eval_ipcw_1th_event_0.5": 0.7330622806909796,
      "eval_ipcw_1th_event_0.75": 0.7170200007459753,
      "eval_ipcw_1th_event_1.0": 0.6949117678153628,
      "eval_ipcw_1th_event_n": 381,
      "eval_ipcw_avg": 0.7616943672276817,
      "eval_ipcw_avg_0th_event": 0.7956397958848245,
      "eval_ipcw_avg_1th_event": 0.7277489385705389,
      "eval_ipcw_weighted_avg": 0.7624351532189159,
      "eval_loss": 0.5524048805236816,
      "eval_runtime": 0.2457,
      "eval_samples_per_second": 5425.076,
      "eval_steps_per_second": 12.209,
      "step": 100
    },
    {
      "epoch": 18.363636363636363,
      "grad_norm": 1.1131818294525146,
      "learning_rate": 0.0036176680919480357,
      "loss": 1.0097,
      "step": 110
    },
    {
      "epoch": 18.363636363636363,
      "eval_brier_0th_event": 0.10092788934923515,
      "eval_brier_0th_event_n": 398,
      "eval_brier_1th_event": 0.11458630672621427,
      "eval_brier_1th_event_n": 381,
      "eval_brier_avg": 0.10775709803772471,
      "eval_brier_weighted_avg": 0.1076080652422121,
      "eval_ipcw": 0.725981761695523,
      "eval_ipcw_0th_event": 0.7555255323818032,
      "eval_ipcw_0th_event_0.25": 0.8194561287828835,
      "eval_ipcw_0th_event_0.5": 0.7997774761887295,
      "eval_ipcw_0th_event_0.75": 0.7847041567092008,
      "eval_ipcw_0th_event_1.0": 0.7555255323818032,
      "eval_ipcw_0th_event_n": 398,
      "eval_ipcw_1th_event": 0.6951197650206159,
      "eval_ipcw_1th_event_0.25": 0.7525933503836317,
      "eval_ipcw_1th_event_0.5": 0.7257618749309062,
      "eval_ipcw_1th_event_0.75": 0.7139442871201622,
      "eval_ipcw_1th_event_1.0": 0.6951197650206159,
      "eval_ipcw_1th_event_n": 381,
      "eval_ipcw_avg": 0.7558603214397417,
      "eval_ipcw_avg_0th_event": 0.7898658235156543,
      "eval_ipcw_avg_1th_event": 0.721854819363829,
      "eval_ipcw_weighted_avg": 0.756602418404171,
      "eval_loss": 0.5459306836128235,
      "eval_runtime": 0.2612,
      "eval_samples_per_second": 5104.283,
      "eval_steps_per_second": 11.488,
      "step": 110
    },
    {
      "epoch": 20.0,
      "grad_norm": 0.5844017267227173,
      "learning_rate": 0.003603095434805858,
      "loss": 1.0269,
      "step": 120
    },
    {
      "epoch": 20.0,
      "eval_brier_0th_event": 0.10011204680110804,
      "eval_brier_0th_event_n": 398,
      "eval_brier_1th_event": 0.11172747384784865,
      "eval_brier_1th_event_n": 381,
      "eval_brier_avg": 0.10591976032447833,
      "eval_brier_weighted_avg": 0.10579301946453316,
      "eval_ipcw": 0.7427271740985245,
      "eval_ipcw_0th_event": 0.7725282788002651,
      "eval_ipcw_0th_event_0.25": 0.8371569541392874,
      "eval_ipcw_0th_event_0.5": 0.8255429621750277,
      "eval_ipcw_0th_event_0.75": 0.8029582859343263,
      "eval_ipcw_0th_event_1.0": 0.7725282788002651,
      "eval_ipcw_0th_event_n": 398,
      "eval_ipcw_1th_event": 0.7115963613129794,
      "eval_ipcw_1th_event_0.25": 0.7814833759590792,
      "eval_ipcw_1th_event_0.5": 0.7573710350362154,
      "eval_ipcw_1th_event_0.75": 0.7359591664586543,
      "eval_ipcw_1th_event_1.0": 0.7115963613129794,
      "eval_ipcw_1th_event_n": 381,
      "eval_ipcw_avg": 0.7780745524769793,
      "eval_ipcw_avg_0th_event": 0.8095466202622266,
      "eval_ipcw_avg_1th_event": 0.7466024846917321,
      "eval_ipcw_weighted_avg": 0.7787613626853865,
      "eval_loss": 0.5444093942642212,
      "eval_runtime": 0.2574,
      "eval_samples_per_second": 5179.151,
      "eval_steps_per_second": 11.656,
      "step": 120
    },
    {
      "epoch": 21.727272727272727,
      "grad_norm": 0.6088608503341675,
      "learning_rate": 0.0035866270718737615,
      "loss": 1.0663,
      "step": 130
    },
    {
      "epoch": 21.727272727272727,
      "eval_brier_0th_event": 0.09942818754020767,
      "eval_brier_0th_event_n": 398,
      "eval_brier_1th_event": 0.11270690125244368,
      "eval_brier_1th_event_n": 381,
      "eval_brier_avg": 0.10606754439632568,
      "eval_brier_weighted_avg": 0.10592265470883658,
      "eval_ipcw": 0.7272880007954684,
      "eval_ipcw_0th_event": 0.7503685166015344,
      "eval_ipcw_0th_event_0.25": 0.8298735059836444,
      "eval_ipcw_0th_event_0.5": 0.8061516014786014,
      "eval_ipcw_0th_event_0.75": 0.783263814789666,
      "eval_ipcw_0th_event_1.0": 0.7503685166015344,
      "eval_ipcw_0th_event_n": 398,
      "eval_ipcw_1th_event": 0.7031776457014677,
      "eval_ipcw_1th_event_0.25": 0.7733128729752771,
      "eval_ipcw_1th_event_0.5": 0.7450344548034049,
      "eval_ipcw_1th_event_0.75": 0.7208718156178541,
      "eval_ipcw_1th_event_1.0": 0.7031776457014677,
      "eval_ipcw_1th_event_n": 381,
      "eval_ipcw_avg": 0.7640067784939313,
      "eval_ipcw_avg_0th_event": 0.7924143597133616,
      "eval_ipcw_avg_1th_event": 0.7355991972745008,
      "eval_ipcw_weighted_avg": 0.7646267128722757,
      "eval_loss": 0.5436171293258667,
      "eval_runtime": 0.2431,
      "eval_samples_per_second": 5482.939,
      "eval_steps_per_second": 12.34,
      "step": 130
    },
    {
      "epoch": 23.363636363636363,
      "grad_norm": 0.7062933444976807,
      "learning_rate": 0.0035682806378872596,
      "loss": 1.0135,
      "step": 140
    },
    {
      "epoch": 23.363636363636363,
      "eval_brier_0th_event": 0.09651300219399153,
      "eval_brier_0th_event_n": 398,
      "eval_brier_1th_event": 0.10892020016614279,
      "eval_brier_1th_event_n": 381,
      "eval_brier_avg": 0.10271660118006716,
      "eval_brier_weighted_avg": 0.1025812209711284,
      "eval_ipcw": 0.7413589654277081,
      "eval_ipcw_0th_event": 0.7636062979210122,
      "eval_ipcw_0th_event_0.25": 0.828024222580963,
      "eval_ipcw_0th_event_0.5": 0.8203466643843712,
      "eval_ipcw_0th_event_0.75": 0.8042369568220766,
      "eval_ipcw_0th_event_1.0": 0.7636062979210122,
      "eval_ipcw_0th_event_n": 398,
      "eval_ipcw_1th_event": 0.7181189698047814,
      "eval_ipcw_1th_event_0.25": 0.7855754475703325,
      "eval_ipcw_1th_event_0.5": 0.7629312992101804,
      "eval_ipcw_1th_event_0.75": 0.7384840060022322,
      "eval_ipcw_1th_event_1.0": 0.7181189698047814,
      "eval_ipcw_1th_event_n": 381,
      "eval_ipcw_avg": 0.7776654830369937,
      "eval_ipcw_avg_0th_event": 0.8040535354271058,
      "eval_ipcw_avg_1th_event": 0.7512774306468816,
      "eval_ipcw_weighted_avg": 0.778241345541014,
      "eval_loss": 0.5349341630935669,
      "eval_runtime": 0.2427,
      "eval_samples_per_second": 5491.949,
      "eval_steps_per_second": 12.36,
      "step": 140
    },
    {
      "epoch": 25.0,
      "grad_norm": 0.6569605469703674,
      "learning_rate": 0.0035480757786673935,
      "loss": 0.9993,
      "step": 150
    },
    {
      "epoch": 25.0,
      "eval_brier_0th_event": 0.0947450142976971,
      "eval_brier_0th_event_n": 398,
      "eval_brier_1th_event": 0.10919795341632657,
      "eval_brier_1th_event_n": 381,
      "eval_brier_avg": 0.10197148385701184,
      "eval_brier_weighted_avg": 0.10181378169718085,
      "eval_ipcw": 0.7415838767205765,
      "eval_ipcw_0th_event": 0.7683609933212601,
      "eval_ipcw_0th_event_0.25": 0.8397717196061936,
      "eval_ipcw_0th_event_0.5": 0.8188590967815558,
      "eval_ipcw_0th_event_0.75": 0.8004553244149714,
      "eval_ipcw_0th_event_1.0": 0.7683609933212601,
      "eval_ipcw_0th_event_n": 398,
      "eval_ipcw_1th_event": 0.7136119806390225,
      "eval_ipcw_1th_event_0.25": 0.7829156010230179,
      "eval_ipcw_1th_event_0.5": 0.7652528528085886,
      "eval_ipcw_1th_event_0.75": 0.7322924108487765,
      "eval_ipcw_1th_event_1.0": 0.7136119806390225,
      "eval_ipcw_1th_event_n": 381,
      "eval_ipcw_avg": 0.7776899974304233,
      "eval_ipcw_avg_0th_event": 0.8068617835309952,
      "eval_ipcw_avg_1th_event": 0.7485182113298514,
      "eval_ipcw_weighted_avg": 0.7783266089371109,
      "eval_loss": 0.531845211982727,
      "eval_runtime": 0.2449,
      "eval_samples_per_second": 5443.754,
      "eval_steps_per_second": 12.252,
      "step": 150
    },
    {
      "epoch": 26.727272727272727,
      "grad_norm": 1.3988261222839355,
      "learning_rate": 0.0035260341300834925,
      "loss": 1.048,
      "step": 160
    },
    {
      "epoch": 26.727272727272727,
      "eval_brier_0th_event": 0.09817407607592757,
      "eval_brier_0th_event_n": 398,
      "eval_brier_1th_event": 0.11096814922034236,
      "eval_brier_1th_event_n": 381,
      "eval_brier_avg": 0.10457111264813496,
      "eval_brier_weighted_avg": 0.10443151107980696,
      "eval_ipcw": 0.7416210922796487,
      "eval_ipcw_0th_event": 0.7630720873888631,
      "eval_ipcw_0th_event_0.25": 0.8314802604154824,
      "eval_ipcw_0th_event_0.5": 0.8148732307115464,
      "eval_ipcw_0th_event_0.75": 0.7957712737031779,
      "eval_ipcw_0th_event_1.0": 0.7630720873888631,
      "eval_ipcw_0th_event_n": 398,
      "eval_ipcw_1th_event": 0.7192129661550625,
      "eval_ipcw_1th_event_0.25": 0.8035669224211424,
      "eval_ipcw_1th_event_0.5": 0.774403950326123,
      "eval_ipcw_1th_event_0.75": 0.7426413838416007,
      "eval_ipcw_1th_event_1.0": 0.7192129661550625,
      "eval_ipcw_1th_event_n": 381,
      "eval_ipcw_avg": 0.7806277593703748,
      "eval_ipcw_avg_0th_event": 0.8012992130547675,
      "eval_ipcw_avg_1th_event": 0.759956305685982,
      "eval_ipcw_weighted_avg": 0.7810788693994307,
      "eval_loss": 0.5396407246589661,
      "eval_runtime": 0.2601,
      "eval_samples_per_second": 5125.523,
      "eval_steps_per_second": 11.535,
      "step": 160
    },
    {
      "epoch": 28.363636363636363,
      "grad_norm": 0.6037663817405701,
      "learning_rate": 0.003502179294884944,
      "loss": 0.9834,
      "step": 170
    },
    {
      "epoch": 28.363636363636363,
      "eval_brier_0th_event": 0.09527886344555775,
      "eval_brier_0th_event_n": 398,
      "eval_brier_1th_event": 0.10420130683748982,
      "eval_brier_1th_event_n": 381,
      "eval_brier_avg": 0.09974008514152378,
      "eval_brier_weighted_avg": 0.099642728570495,
      "eval_ipcw": 0.7559508244218436,
      "eval_ipcw_0th_event": 0.7677979664533519,
      "eval_ipcw_0th_event_0.25": 0.8311240459895561,
      "eval_ipcw_0th_event_0.5": 0.8178605925002139,
      "eval_ipcw_0th_event_0.75": 0.8022939649673572,
      "eval_ipcw_0th_event_1.0": 0.7677979664533519,
      "eval_ipcw_0th_event_n": 398,
      "eval_ipcw_1th_event": 0.7435750697537589,
      "eval_ipcw_1th_event_0.25": 0.8253640238704177,
      "eval_ipcw_1th_event_0.5": 0.8044121801722126,
      "eval_ipcw_1th_event_0.75": 0.7671208508709262,
      "eval_ipcw_1th_event_1.0": 0.7435750697537589,
      "eval_ipcw_1th_event_n": 381,
      "eval_ipcw_avg": 0.7949435868222243,
      "eval_ipcw_avg_0th_event": 0.8047691424776198,
      "eval_ipcw_avg_1th_event": 0.7851180311668289,
      "eval_ipcw_weighted_avg": 0.7951580084475668,
      "eval_loss": 0.5264806151390076,
      "eval_runtime": 0.2489,
      "eval_samples_per_second": 5355.992,
      "eval_steps_per_second": 12.054,
      "step": 170
    },
    {
      "epoch": 30.0,
      "grad_norm": 0.7634719610214233,
      "learning_rate": 0.003476536817426776,
      "loss": 0.988,
      "step": 180
    },
    {
      "epoch": 30.0,
      "eval_brier_0th_event": 0.09410060118240493,
      "eval_brier_0th_event_n": 398,
      "eval_brier_1th_event": 0.10364009697598389,
      "eval_brier_1th_event_n": 381,
      "eval_brier_avg": 0.09887034907919441,
      "eval_brier_weighted_avg": 0.09876625958722339,
      "eval_ipcw": 0.7611835244148045,
      "eval_ipcw_0th_event": 0.7746274380282533,
      "eval_ipcw_0th_event_0.25": 0.8415906868875196,
      "eval_ipcw_0th_event_0.5": 0.8233829325051861,
      "eval_ipcw_0th_event_0.75": 0.8095368271913038,
      "eval_ipcw_0th_event_1.0": 0.7746274380282533,
      "eval_ipcw_0th_event_n": 398,
      "eval_ipcw_1th_event": 0.7471397511388135,
      "eval_ipcw_1th_event_0.25": 0.8286854219948849,
      "eval_ipcw_1th_event_0.5": 0.7971772856247927,
      "eval_ipcw_1th_event_0.75": 0.7691780212717731,
      "eval_ipcw_1th_event_1.0": 0.7471397511388135,
      "eval_ipcw_1th_event_n": 381,
      "eval_ipcw_avg": 0.798914795580316,
      "eval_ipcw_avg_0th_event": 0.8122844711530658,
      "eval_ipcw_avg_1th_event": 0.7855451200075662,
      "eval_ipcw_weighted_avg": 0.7992065600023144,
      "eval_loss": 0.522951066493988,
      "eval_runtime": 0.2574,
      "eval_samples_per_second": 5179.712,
      "eval_steps_per_second": 11.657,
      "step": 180
    },
    {
      "epoch": 31.727272727272727,
      "grad_norm": 1.0013526678085327,
      "learning_rate": 0.0034491341563161254,
      "loss": 1.0254,
      "step": 190
    },
    {
      "epoch": 31.727272727272727,
      "eval_brier_0th_event": 0.09491116523348446,
      "eval_brier_0th_event_n": 398,
      "eval_brier_1th_event": 0.09968772190937746,
      "eval_brier_1th_event_n": 381,
      "eval_brier_avg": 0.09729944357143096,
      "eval_brier_weighted_avg": 0.09724732453196357,
      "eval_ipcw": 0.7705188194438651,
      "eval_ipcw_0th_event": 0.7766512314550255,
      "eval_ipcw_0th_event_0.25": 0.846687584790402,
      "eval_ipcw_0th_event_0.5": 0.8251476359901698,
      "eval_ipcw_0th_event_0.75": 0.8114460151030138,
      "eval_ipcw_0th_event_1.0": 0.7766512314550255,
      "eval_ipcw_0th_event_n": 398,
      "eval_ipcw_1th_event": 0.764112782749792,
      "eval_ipcw_1th_event_0.25": 0.8472702472293265,
      "eval_ipcw_1th_event_0.5": 0.8203027436914749,
      "eval_ipcw_1th_event_0.75": 0.7911584709801255,
      "eval_ipcw_1th_event_1.0": 0.764112782749792,
      "eval_ipcw_1th_event_n": 381,
      "eval_ipcw_avg": 0.8103470889986663,
      "eval_ipcw_avg_0th_event": 0.8149831168346527,
      "eval_ipcw_avg_1th_event": 0.8057110611626798,
      "eval_ipcw_weighted_avg": 0.8104482603378342,
      "eval_loss": 0.5195974707603455,
      "eval_runtime": 0.2538,
      "eval_samples_per_second": 5253.037,
      "eval_steps_per_second": 11.822,
      "step": 190
    },
    {
      "epoch": 33.36363636363637,
      "grad_norm": 1.3816457986831665,
      "learning_rate": 0.0034200006550088712,
      "loss": 0.9693,
      "step": 200
    },
    {
      "epoch": 33.36363636363637,
      "eval_brier_0th_event": 0.09304151248311031,
      "eval_brier_0th_event_n": 398,
      "eval_brier_1th_event": 0.09911386106632657,
      "eval_brier_1th_event_n": 381,
      "eval_brier_avg": 0.09607768677471844,
      "eval_brier_weighted_avg": 0.09601142879916344,
      "eval_ipcw": 0.7645141654714757,
      "eval_ipcw_0th_event": 0.7731489383396914,
      "eval_ipcw_0th_event_0.25": 0.8479570723721607,
      "eval_ipcw_0th_event_0.5": 0.8273524964644797,
      "eval_ipcw_0th_event_0.75": 0.8079201168734587,
      "eval_ipcw_0th_event_1.0": 0.7731489383396914,
      "eval_ipcw_0th_event_n": 398,
      "eval_ipcw_1th_event": 0.755494114023838,
      "eval_ipcw_1th_event_0.25": 0.8454424552429668,
      "eval_ipcw_1th_event_0.5": 0.8129818656774473,
      "eval_ipcw_1th_event_0.75": 0.7776620559653638,
      "eval_ipcw_1th_event_1.0": 0.755494114023838,
      "eval_ipcw_1th_event_n": 381,
      "eval_ipcw_avg": 0.8059948893699258,
      "eval_ipcw_avg_0th_event": 0.8140946560124476,
      "eval_ipcw_avg_1th_event": 0.797895122727404,
      "eval_ipcw_weighted_avg": 0.806171649360841,
      "eval_loss": 0.5174790620803833,
      "eval_runtime": 0.2427,
      "eval_samples_per_second": 5493.395,
      "eval_steps_per_second": 12.363,
      "step": 200
    },
    {
      "epoch": 35.0,
      "grad_norm": 1.0939666032791138,
      "learning_rate": 0.0033891675103879275,
      "loss": 0.9674,
      "step": 210
    },
    {
      "epoch": 35.0,
      "eval_brier_0th_event": 0.09337421006607462,
      "eval_brier_0th_event_n": 398,
      "eval_brier_1th_event": 0.1014516261373638,
      "eval_brier_1th_event_n": 381,
      "eval_brier_avg": 0.0974129181017192,
      "eval_brier_weighted_avg": 0.09732478198284122,
      "eval_ipcw": 0.7766909491342835,
      "eval_ipcw_0th_event": 0.7788202148811991,
      "eval_ipcw_0th_event_0.25": 0.8505718378390669,
      "eval_ipcw_0th_event_0.5": 0.8300749489540158,
      "eval_ipcw_0th_event_0.75": 0.8118178584761182,
      "eval_ipcw_0th_event_1.0": 0.7788202148811991,
      "eval_ipcw_0th_event_n": 398,
      "eval_ipcw_1th_event": 0.774466676779238,
      "eval_ipcw_1th_event_0.25": 0.8618721227621483,
      "eval_ipcw_1th_event_0.5": 0.8346660770657528,
      "eval_ipcw_1th_event_0.75": 0.7994646192513277,
      "eval_ipcw_1th_event_1.0": 0.774466676779238,
      "eval_ipcw_1th_event_n": 381,
      "eval_ipcw_avg": 0.8177192945011084,
      "eval_ipcw_avg_0th_event": 0.8178212150376,
      "eval_ipcw_avg_1th_event": 0.8176173739646168,
      "eval_ipcw_weighted_avg": 0.8177215186976684,
      "eval_loss": 0.5184785723686218,
      "eval_runtime": 0.2574,
      "eval_samples_per_second": 5177.971,
      "eval_steps_per_second": 11.653,
      "step": 210
    },
    {
      "epoch": 36.72727272727273,
      "grad_norm": 0.7718287706375122,
      "learning_rate": 0.003356667739356841,
      "loss": 1.0117,
      "step": 220
    },
    {
      "epoch": 36.72727272727273,
      "eval_brier_0th_event": 0.09371767119877708,
      "eval_brier_0th_event_n": 398,
      "eval_brier_1th_event": 0.09654479846600961,
      "eval_brier_1th_event_n": 381,
      "eval_brier_avg": 0.09513123483239334,
      "eval_brier_weighted_avg": 0.09510038684552367,
      "eval_ipcw": 0.7792909796705287,
      "eval_ipcw_0th_event": 0.7733617358960662,
      "eval_ipcw_0th_event_0.25": 0.8365961058942119,
      "eval_ipcw_0th_event_0.5": 0.8195519364869767,
      "eval_ipcw_0th_event_0.75": 0.803801914772911,
      "eval_ipcw_0th_event_1.0": 0.7733617358960662,
      "eval_ipcw_0th_event_n": 398,
      "eval_ipcw_1th_event": 0.7854847828784974,
      "eval_ipcw_1th_event_0.25": 0.8781040068201194,
      "eval_ipcw_1th_event_0.5": 0.8463680174259826,
      "eval_ipcw_1th_event_0.75": 0.8143496960150572,
      "eval_ipcw_1th_event_1.0": 0.7854847828784974,
      "eval_ipcw_1th_event_n": 381,
      "eval_ipcw_avg": 0.8197022745237278,
      "eval_ipcw_avg_0th_event": 0.8083279232625414,
      "eval_ipcw_avg_1th_event": 0.8310766257849141,
      "eval_ipcw_weighted_avg": 0.8194540537644979,
      "eval_loss": 0.5117059946060181,
      "eval_runtime": 0.2514,
      "eval_samples_per_second": 5302.498,
      "eval_steps_per_second": 11.934,
      "step": 220
    },
    {
      "epoch": 38.36363636363637,
      "grad_norm": 1.0084576606750488,
      "learning_rate": 0.0033225361434844622,
      "loss": 0.9474,
      "step": 230
    },
    {
      "epoch": 38.36363636363637,
      "eval_brier_0th_event": 0.09055916187827218,
      "eval_brier_0th_event_n": 398,
      "eval_brier_1th_event": 0.09768213377640403,
      "eval_brier_1th_event_n": 381,
      "eval_brier_avg": 0.0941206478273381,
      "eval_brier_weighted_avg": 0.09404292605438032,
      "eval_ipcw": 0.7855903815649513,
      "eval_ipcw_0th_event": 0.7908200020836428,
      "eval_ipcw_0th_event_0.25": 0.8612431125561796,
      "eval_ipcw_0th_event_0.5": 0.8380792853154663,
      "eval_ipcw_0th_event_0.75": 0.8193193943509202,
      "eval_ipcw_0th_event_1.0": 0.7908200020836428,
      "eval_ipcw_0th_event_n": 398,
      "eval_ipcw_1th_event": 0.7801274183984445,
      "eval_ipcw_1th_event_0.25": 0.8682421142369992,
      "eval_ipcw_1th_event_0.5": 0.8433995406026212,
      "eval_ipcw_1th_event_0.75": 0.8060406786080101,
      "eval_ipcw_1th_event_1.0": 0.7801274183984445,
      "eval_ipcw_1th_event_n": 381,
      "eval_ipcw_avg": 0.8259089432690354,
      "eval_ipcw_avg_0th_event": 0.8273654485765521,
      "eval_ipcw_avg_1th_event": 0.8244524379615188,
      "eval_ipcw_weighted_avg": 0.8259407283656052,
      "eval_loss": 0.5071797370910645,
      "eval_runtime": 0.3486,
      "eval_samples_per_second": 3823.965,
      "eval_steps_per_second": 8.606,
      "step": 230
    },
    {
      "epoch": 40.0,
      "grad_norm": 0.6544005870819092,
      "learning_rate": 0.0032868092717385534,
      "loss": 0.9564,
      "step": 240
    },
    {
      "epoch": 40.0,
      "eval_brier_0th_event": 0.09241452133046,
      "eval_brier_0th_event_n": 398,
      "eval_brier_1th_event": 0.09694900404908886,
      "eval_brier_1th_event_n": 381,
      "eval_brier_avg": 0.09468176268977443,
      "eval_brier_weighted_avg": 0.0946322850221129,
      "eval_ipcw": 0.7782206804220405,
      "eval_ipcw_0th_event": 0.7833654376868906,
      "eval_ipcw_0th_event_0.25": 0.8533912371251222,
      "eval_ipcw_0th_event_0.5": 0.8332294073775202,
      "eval_ipcw_0th_event_0.75": 0.8158449369042055,
      "eval_ipcw_0th_event_1.0": 0.7833654376868906,
      "eval_ipcw_0th_event_n": 398,
      "eval_ipcw_1th_event": 0.7728463670587586,
      "eval_ipcw_1th_event_0.25": 0.8585882352941177,
      "eval_ipcw_1th_event_0.5": 0.8299410808531198,
      "eval_ipcw_1th_event_0.75": 0.7971779179828827,
      "eval_ipcw_1th_event_1.0": 0.7728463670587586,
      "eval_ipcw_1th_event_n": 381,
      "eval_ipcw_avg": 0.8180480775353272,
      "eval_ipcw_avg_0th_event": 0.8214577547734346,
      "eval_ipcw_avg_1th_event": 0.8146384002972198,
      "eval_ipcw_weighted_avg": 0.8181224864095863,
      "eval_loss": 0.5102157592773438,
      "eval_runtime": 0.2527,
      "eval_samples_per_second": 5274.719,
      "eval_steps_per_second": 11.871,
      "step": 240
    },
    {
      "epoch": 41.72727272727273,
      "grad_norm": 0.9824110269546509,
      "learning_rate": 0.003249525381348242,
      "loss": 1.0,
      "step": 250
    },
    {
      "epoch": 41.72727272727273,
      "eval_brier_0th_event": 0.09140386005078795,
      "eval_brier_0th_event_n": 398,
      "eval_brier_1th_event": 0.0941665245819319,
      "eval_brier_1th_event_n": 381,
      "eval_brier_avg": 0.09278519231635993,
      "eval_brier_weighted_avg": 0.09275504770979418,
      "eval_ipcw": 0.7883121477129337,
      "eval_ipcw_0th_event": 0.7915093775006483,
      "eval_ipcw_0th_event_0.25": 0.8583024487847025,
      "eval_ipcw_0th_event_0.5": 0.834835165283025,
      "eval_ipcw_0th_event_0.75": 0.8187344391631908,
      "eval_ipcw_0th_event_1.0": 0.7915093775006483,
      "eval_ipcw_0th_event_n": 398,
      "eval_ipcw_1th_event": 0.7849722593782608,
      "eval_ipcw_1th_event_0.25": 0.8720341005967605,
      "eval_ipcw_1th_event_0.5": 0.8483620149611232,
      "eval_ipcw_1th_event_0.75": 0.8143611725584371,
      "eval_ipcw_1th_event_1.0": 0.7849722593782608,
      "eval_ipcw_1th_event_n": 381,
      "eval_ipcw_avg": 0.8278888722782686,
      "eval_ipcw_avg_0th_event": 0.8258453576828917,
      "eval_ipcw_avg_1th_event": 0.8299323868736455,
      "eval_ipcw_weighted_avg": 0.8278442769661744,
      "eval_loss": 0.5033738017082214,
      "eval_runtime": 0.2545,
      "eval_samples_per_second": 5237.576,
      "eval_steps_per_second": 11.787,
      "step": 250
    },
    {
      "epoch": 43.36363636363637,
      "grad_norm": 0.7321155667304993,
      "learning_rate": 0.0032107243968372175,
      "loss": 0.9291,
      "step": 260
    },
    {
      "epoch": 43.36363636363637,
      "eval_brier_0th_event": 0.0904923065163342,
      "eval_brier_0th_event_n": 398,
      "eval_brier_1th_event": 0.09254105384677393,
      "eval_brier_1th_event_n": 381,
      "eval_brier_avg": 0.09151668018155407,
      "eval_brier_weighted_avg": 0.09149432542891127,
      "eval_ipcw": 0.7913262351232184,
      "eval_ipcw_0th_event": 0.7936927690947015,
      "eval_ipcw_0th_event_0.25": 0.8610687948583858,
      "eval_ipcw_0th_event_0.5": 0.8410055141889496,
      "eval_ipcw_0th_event_0.75": 0.8219149492793881,
      "eval_ipcw_0th_event_1.0": 0.7936927690947015,
      "eval_ipcw_0th_event_n": 398,
      "eval_ipcw_1th_event": 0.7888541077724304,
      "eval_ipcw_1th_event_0.25": 0.8814867860187553,
      "eval_ipcw_1th_event_0.5": 0.8550032141438708,
      "eval_ipcw_1th_event_0.75": 0.8134287034088203,
      "eval_ipcw_1th_event_1.0": 0.7888541077724304,
      "eval_ipcw_1th_event_n": 381,
      "eval_ipcw_avg": 0.8320568548456626,
      "eval_ipcw_avg_0th_event": 0.8294205068553562,
      "eval_ipcw_avg_1th_event": 0.8346932028359692,
      "eval_ipcw_weighted_avg": 0.83199932221943,
      "eval_loss": 0.5010040998458862,
      "eval_runtime": 0.2367,
      "eval_samples_per_second": 5631.452,
      "eval_steps_per_second": 12.674,
      "step": 260
    },
    {
      "epoch": 45.0,
      "grad_norm": 0.7124826908111572,
      "learning_rate": 0.0031704478672715526,
      "loss": 0.9396,
      "step": 270
    },
    {
      "epoch": 45.0,
      "eval_brier_0th_event": 0.08943582841793479,
      "eval_brier_0th_event_n": 398,
      "eval_brier_1th_event": 0.09290714005478438,
      "eval_brier_1th_event_n": 381,
      "eval_brier_avg": 0.0911714842363596,
      "eval_brier_weighted_avg": 0.09113360728011669,
      "eval_ipcw": 0.7908441955801149,
      "eval_ipcw_0th_event": 0.8008370037217406,
      "eval_ipcw_0th_event_0.25": 0.8635319797185148,
      "eval_ipcw_0th_event_0.5": 0.8424237978212229,
      "eval_ipcw_0th_event_0.75": 0.8274426288297663,
      "eval_ipcw_0th_event_1.0": 0.8008370037217406,
      "eval_ipcw_0th_event_n": 398,
      "eval_ipcw_1th_event": 0.7804055141093352,
      "eval_ipcw_1th_event_0.25": 0.8718226768968457,
      "eval_ipcw_1th_event_0.5": 0.8402631912968354,
      "eval_ipcw_1th_event_0.75": 0.8043564958670099,
      "eval_ipcw_1th_event_1.0": 0.7804055141093352,
      "eval_ipcw_1th_event_n": 381,
      "eval_ipcw_avg": 0.8288854110326589,
      "eval_ipcw_avg_0th_event": 0.8335588525228113,
      "eval_ipcw_avg_1th_event": 0.8242119695425065,
      "eval_ipcw_weighted_avg": 0.8289873988443824,
      "eval_loss": 0.5033213496208191,
      "eval_runtime": 0.2469,
      "eval_samples_per_second": 5398.028,
      "eval_steps_per_second": 12.149,
      "step": 270
    },
    {
      "epoch": 46.72727272727273,
      "grad_norm": 0.6080222725868225,
      "learning_rate": 0.003128738921767923,
      "loss": 0.983,
      "step": 280
    },
    {
      "epoch": 46.72727272727273,
      "eval_brier_0th_event": 0.09009288169562411,
      "eval_brier_0th_event_n": 398,
      "eval_brier_1th_event": 0.09376231300249138,
      "eval_brier_1th_event_n": 381,
      "eval_brier_avg": 0.09192759734905775,
      "eval_brier_weighted_avg": 0.0918875586249135,
      "eval_ipcw": 0.7881768140798523,
      "eval_ipcw_0th_event": 0.791983738720067,
      "eval_ipcw_0th_event_0.25": 0.8598334129131519,
      "eval_ipcw_0th_event_0.5": 0.8363634881626298,
      "eval_ipcw_0th_event_0.75": 0.8204687284132429,
      "eval_ipcw_0th_event_1.0": 0.791983738720067,
      "eval_ipcw_0th_event_n": 398,
      "eval_ipcw_1th_event": 0.7842000266604152,
      "eval_ipcw_1th_event_0.25": 0.873159420289855,
      "eval_ipcw_1th_event_0.5": 0.8428508841966483,
      "eval_ipcw_1th_event_0.75": 0.8099541799005557,
      "eval_ipcw_1th_event_1.0": 0.7842000266604152,
      "eval_ipcw_1th_event_n": 381,
      "eval_ipcw_avg": 0.8273517349070707,
      "eval_ipcw_avg_0th_event": 0.8271623420522729,
      "eval_ipcw_avg_1th_event": 0.8275411277618685,
      "eval_ipcw_weighted_avg": 0.8273476018152459,
      "eval_loss": 0.502345860004425,
      "eval_runtime": 0.2634,
      "eval_samples_per_second": 5061.324,
      "eval_steps_per_second": 11.391,
      "step": 280
    },
    {
      "epoch": 48.36363636363637,
      "grad_norm": 0.6946607232093811,
      "learning_rate": 0.0030856422233098697,
      "loss": 0.9154,
      "step": 290
    },
    {
      "epoch": 48.36363636363637,
      "eval_brier_0th_event": 0.08786399010900509,
      "eval_brier_0th_event_n": 398,
      "eval_brier_1th_event": 0.09287275286493651,
      "eval_brier_1th_event_n": 381,
      "eval_brier_avg": 0.0903683714869708,
      "eval_brier_weighted_avg": 0.0903137187482989,
      "eval_ipcw": 0.796706216106477,
      "eval_ipcw_0th_event": 0.8028940467666963,
      "eval_ipcw_0th_event_0.25": 0.8702735272049295,
      "eval_ipcw_0th_event_0.5": 0.848928339996821,
      "eval_ipcw_0th_event_0.75": 0.8324735373915702,
      "eval_ipcw_0th_event_1.0": 0.8028940467666963,
      "eval_ipcw_0th_event_n": 398,
      "eval_ipcw_1th_event": 0.790242288015224,
      "eval_ipcw_1th_event_0.25": 0.8784313725490196,
      "eval_ipcw_1th_event_0.5": 0.851264980571831,
      "eval_ipcw_1th_event_0.75": 0.8129753799453143,
      "eval_ipcw_1th_event_1.0": 0.790242288015224,
      "eval_ipcw_1th_event_n": 381,
      "eval_ipcw_avg": 0.8359354340551757,
      "eval_ipcw_avg_0th_event": 0.8386423628400042,
      "eval_ipcw_avg_1th_event": 0.8332285052703472,
      "eval_ipcw_weighted_avg": 0.8359945069554864,
      "eval_loss": 0.49713364243507385,
      "eval_runtime": 0.2605,
      "eval_samples_per_second": 5116.531,
      "eval_steps_per_second": 11.515,
      "step": 290
    },
    {
      "epoch": 50.0,
      "grad_norm": 0.7756429314613342,
      "learning_rate": 0.003041203920921556,
      "loss": 0.9253,
      "step": 300
    },
    {
      "epoch": 50.0,
      "eval_brier_0th_event": 0.09265660007673583,
      "eval_brier_0th_event_n": 398,
      "eval_brier_1th_event": 0.09004888770899427,
      "eval_brier_1th_event_n": 381,
      "eval_brier_avg": 0.09135274389286505,
      "eval_brier_weighted_avg": 0.09138119775053617,
      "eval_ipcw": 0.7995701436571553,
      "eval_ipcw_0th_event": 0.8049045403461951,
      "eval_ipcw_0th_event_0.25": 0.8694587814435021,
      "eval_ipcw_0th_event_0.5": 0.8507990072014574,
      "eval_ipcw_0th_event_0.75": 0.832410338715509,
      "eval_ipcw_0th_event_1.0": 0.8049045403461951,
      "eval_ipcw_0th_event_n": 398,
      "eval_ipcw_1th_event": 0.7939977292680797,
      "eval_ipcw_1th_event_0.25": 0.8815481670929242,
      "eval_ipcw_1th_event_0.5": 0.851084824737034,
      "eval_ipcw_1th_event_0.75": 0.8188972763293424,
      "eval_ipcw_1th_event_1.0": 0.7939977292680797,
      "eval_ipcw_1th_event_n": 381,
      "eval_ipcw_avg": 0.8378875831417555,
      "eval_ipcw_avg_0th_event": 0.8393931669266659,
      "eval_ipcw_avg_1th_event": 0.8363819993568451,
      "eval_ipcw_weighted_avg": 0.8379204392705661,
      "eval_loss": 0.5002680420875549,
      "eval_runtime": 0.2669,
      "eval_samples_per_second": 4994.339,
      "eval_steps_per_second": 11.24,
      "step": 300
    },
    {
      "epoch": 51.72727272727273,
      "grad_norm": 1.0726089477539062,
      "learning_rate": 0.002995471600250237,
      "loss": 0.9768,
      "step": 310
    },
    {
      "epoch": 51.72727272727273,
      "eval_brier_0th_event": 0.09273812857100878,
      "eval_brier_0th_event_n": 398,
      "eval_brier_1th_event": 0.08961399147824899,
      "eval_brier_1th_event_n": 381,
      "eval_brier_avg": 0.09117606002462889,
      "eval_brier_weighted_avg": 0.09121014881190548,
      "eval_ipcw": 0.7959231854716075,
      "eval_ipcw_0th_event": 0.7991700895301386,
      "eval_ipcw_0th_event_0.25": 0.8651690502717082,
      "eval_ipcw_0th_event_0.5": 0.8484474277307055,
      "eval_ipcw_0th_event_0.75": 0.8285993115753519,
      "eval_ipcw_0th_event_1.0": 0.7991700895301386,
      "eval_ipcw_0th_event_n": 398,
      "eval_ipcw_1th_event": 0.7925314064288373,
      "eval_ipcw_1th_event_0.25": 0.8806547314578005,
      "eval_ipcw_1th_event_0.5": 0.851969226107856,
      "eval_ipcw_1th_event_0.75": 0.8179389849571208,
      "eval_ipcw_1th_event_1.0": 0.7925314064288373,
      "eval_ipcw_1th_event_n": 381,
      "eval_ipcw_avg": 0.8355600285074398,
      "eval_ipcw_avg_0th_event": 0.835346469776976,
      "eval_ipcw_avg_1th_event": 0.8357735872379037,
      "eval_ipcw_weighted_avg": 0.8355553680473399,
      "eval_loss": 0.5001786351203918,
      "eval_runtime": 0.2582,
      "eval_samples_per_second": 5162.165,
      "eval_steps_per_second": 11.618,
      "step": 310
    },
    {
      "epoch": 53.36363636363637,
      "grad_norm": 1.351828694343567,
      "learning_rate": 0.0029484942326103583,
      "loss": 0.9349,
      "step": 320
    },
    {
      "epoch": 53.36363636363637,
      "eval_brier_0th_event": 0.08730912995964217,
      "eval_brier_0th_event_n": 398,
      "eval_brier_1th_event": 0.08855442092709769,
      "eval_brier_1th_event_n": 381,
      "eval_brier_avg": 0.08793177544336993,
      "eval_brier_weighted_avg": 0.08791818754449526,
      "eval_ipcw": 0.796413058355624,
      "eval_ipcw_0th_event": 0.7997020834210754,
      "eval_ipcw_0th_event_0.25": 0.8682461365892847,
      "eval_ipcw_0th_event_0.5": 0.8519442304792413,
      "eval_ipcw_0th_event_0.75": 0.8320208585025735,
      "eval_ipcw_0th_event_1.0": 0.7997020834210754,
      "eval_ipcw_0th_event_n": 398,
      "eval_ipcw_1th_event": 0.7929772788909267,
      "eval_ipcw_1th_event_0.25": 0.8814322250639386,
      "eval_ipcw_1th_event_0.5": 0.8529682721008217,
      "eval_ipcw_1th_event_0.75": 0.8184152615073866,
      "eval_ipcw_1th_event_1.0": 0.7929772788909267,
      "eval_ipcw_1th_event_n": 381,
      "eval_ipcw_avg": 0.8372132933194061,
      "eval_ipcw_avg_0th_event": 0.8379783272480437,
      "eval_ipcw_avg_1th_event": 0.8364482593907685,
      "eval_ipcw_weighted_avg": 0.8372299885399284,
      "eval_loss": 0.4942961633205414,
      "eval_runtime": 0.2555,
      "eval_samples_per_second": 5216.523,
      "eval_steps_per_second": 11.74,
      "step": 320
    },
    {
      "epoch": 55.0,
      "grad_norm": 0.7555848360061646,
      "learning_rate": 0.002900322122543842,
      "loss": 0.9153,
      "step": 330
    },
    {
      "epoch": 55.0,
      "eval_brier_0th_event": 0.08857512336966572,
      "eval_brier_0th_event_n": 398,
      "eval_brier_1th_event": 0.09021115107207194,
      "eval_brier_1th_event_n": 381,
      "eval_brier_avg": 0.08939313722086883,
      "eval_brier_weighted_avg": 0.0893752858274536,
      "eval_ipcw": 0.7923648504464632,
      "eval_ipcw_0th_event": 0.7969357151882039,
      "eval_ipcw_0th_event_0.25": 0.8744154672851155,
      "eval_ipcw_0th_event_0.5": 0.8490220771334368,
      "eval_ipcw_0th_event_0.75": 0.8308156744474525,
      "eval_ipcw_0th_event_1.0": 0.7969357151882039,
      "eval_ipcw_0th_event_n": 398,
      "eval_ipcw_1th_event": 0.7875900363592905,
      "eval_ipcw_1th_event_0.25": 0.8788064791133845,
      "eval_ipcw_1th_event_0.5": 0.849619011353912,
      "eval_ipcw_1th_event_0.75": 0.8126942046325067,
      "eval_ipcw_1th_event_1.0": 0.7875900363592905,
      "eval_ipcw_1th_event_n": 381,
      "eval_ipcw_avg": 0.8349873331891629,
      "eval_ipcw_avg_0th_event": 0.8377972335135522,
      "eval_ipcw_avg_1th_event": 0.8321774328647735,
      "eval_ipcw_weighted_avg": 0.8350486532219158,
      "eval_loss": 0.4983217716217041,
      "eval_runtime": 0.2451,
      "eval_samples_per_second": 5439.353,
      "eval_steps_per_second": 12.242,
      "step": 330
    },
    {
      "epoch": 56.72727272727273,
      "grad_norm": 1.6791609525680542,
      "learning_rate": 0.002851006853952728,
      "loss": 0.9611,
      "step": 340
    },
    {
      "epoch": 56.72727272727273,
      "eval_brier_0th_event": 0.09011722984075822,
      "eval_brier_0th_event_n": 398,
      "eval_brier_1th_event": 0.09097289710430072,
      "eval_brier_1th_event_n": 381,
      "eval_brier_avg": 0.09054506347252947,
      "eval_brier_weighted_avg": 0.09053572692344075,
      "eval_ipcw": 0.7979566747583059,
      "eval_ipcw_0th_event": 0.8018389255496716,
      "eval_ipcw_0th_event_0.25": 0.8682537156196236,
      "eval_ipcw_0th_event_0.5": 0.8492095514066684,
      "eval_ipcw_0th_event_0.75": 0.833131979411929,
      "eval_ipcw_0th_event_1.0": 0.8018389255496716,
      "eval_ipcw_0th_event_n": 398,
      "eval_ipcw_1th_event": 0.793901200178349,
      "eval_ipcw_1th_event_0.25": 0.8846649616368286,
      "eval_ipcw_1th_event_0.5": 0.8545323523029238,
      "eval_ipcw_1th_event_0.75": 0.819508402264322,
      "eval_ipcw_1th_event_1.0": 0.793901200178349,
      "eval_ipcw_1th_event_n": 381,
      "eval_ipcw_avg": 0.8381301360462896,
      "eval_ipcw_avg_0th_event": 0.8381085429969732,
      "eval_ipcw_avg_1th_event": 0.8381517290956059,
      "eval_ipcw_weighted_avg": 0.8381296648244175,
      "eval_loss": 0.5028798580169678,
      "eval_runtime": 0.2647,
      "eval_samples_per_second": 5036.422,
      "eval_steps_per_second": 11.335,
      "step": 340
    },
    {
      "epoch": 58.36363636363637,
      "grad_norm": 0.9621945023536682,
      "learning_rate": 0.002800601234861837,
      "loss": 0.914,
      "step": 350
    },
    {
      "epoch": 58.36363636363637,
      "eval_brier_0th_event": 0.0880967349248966,
      "eval_brier_0th_event_n": 398,
      "eval_brier_1th_event": 0.08944925704593508,
      "eval_brier_1th_event_n": 381,
      "eval_brier_avg": 0.08877299598541584,
      "eval_brier_weighted_avg": 0.08875823804186149,
      "eval_ipcw": 0.794319888313199,
      "eval_ipcw_0th_event": 0.7981881174731177,
      "eval_ipcw_0th_event_0.25": 0.8680149761639496,
      "eval_ipcw_0th_event_0.5": 0.8454885946357905,
      "eval_ipcw_0th_event_0.75": 0.827582253811762,
      "eval_ipcw_0th_event_1.0": 0.7981881174731177,
      "eval_ipcw_0th_event_n": 398,
      "eval_ipcw_1th_event": 0.7902790610017881,
      "eval_ipcw_1th_event_0.25": 0.8812583120204603,
      "eval_ipcw_1th_event_0.5": 0.8538322012176897,
      "eval_ipcw_1th_event_0.75": 0.8166708269136419,
      "eval_ipcw_1th_event_1.0": 0.7902790610017881,
      "eval_ipcw_1th_event_n": 381,
      "eval_ipcw_avg": 0.8351642929047749,
      "eval_ipcw_avg_0th_event": 0.8348184855211549,
      "eval_ipcw_avg_1th_event": 0.835510100288395,
      "eval_ipcw_weighted_avg": 0.83515674640218,
      "eval_loss": 0.49732667207717896,
      "eval_runtime": 0.2437,
      "eval_samples_per_second": 5469.615,
      "eval_steps_per_second": 12.31,
      "step": 350
    },
    {
      "epoch": 60.0,
      "grad_norm": 1.0445270538330078,
      "learning_rate": 0.002749159240870613,
      "loss": 0.9131,
      "step": 360
    },
    {
      "epoch": 60.0,
      "eval_brier_0th_event": 0.08951490571019129,
      "eval_brier_0th_event_n": 398,
      "eval_brier_1th_event": 0.08835106381701102,
      "eval_brier_1th_event_n": 381,
      "eval_brier_avg": 0.08893298476360115,
      "eval_brier_weighted_avg": 0.08894568393701839,
      "eval_ipcw": 0.7957692398443172,
      "eval_ipcw_0th_event": 0.7997752325810792,
      "eval_ipcw_0th_event_0.25": 0.8579613924194539,
      "eval_ipcw_0th_event_0.5": 0.8423259851569282,
      "eval_ipcw_0th_event_0.75": 0.8270502091435257,
      "eval_ipcw_0th_event_1.0": 0.7997752325810792,
      "eval_ipcw_0th_event_n": 398,
      "eval_ipcw_1th_event": 0.7915845020248126,
      "eval_ipcw_1th_event_0.25": 0.8816368286445013,
      "eval_ipcw_1th_event_0.5": 0.8561332825621435,
      "eval_ipcw_1th_event_0.75": 0.8152534738062243,
      "eval_ipcw_1th_event_1.0": 0.7915845020248126,
      "eval_ipcw_1th_event_n": 381,
      "eval_ipcw_avg": 0.8339651132923336,
      "eval_ipcw_avg_0th_event": 0.8317782048252467,
      "eval_ipcw_avg_1th_event": 0.8361520217594204,
      "eval_ipcw_weighted_avg": 0.8339173887173138,
      "eval_loss": 0.4974704086780548,
      "eval_runtime": 0.2632,
      "eval_samples_per_second": 5065.415,
      "eval_steps_per_second": 11.4,
      "step": 360
    },
    {
      "epoch": 61.72727272727273,
      "grad_norm": 0.6784003376960754,
      "learning_rate": 0.002696735957354705,
      "loss": 0.966,
      "step": 370
    },
    {
      "epoch": 61.72727272727273,
      "eval_brier_0th_event": 0.08871146382394449,
      "eval_brier_0th_event_n": 398,
      "eval_brier_1th_event": 0.09022959990918439,
      "eval_brier_1th_event_n": 381,
      "eval_brier_avg": 0.08947053186656444,
      "eval_brier_weighted_avg": 0.0894539668386767,
      "eval_ipcw": 0.7955441386432597,
      "eval_ipcw_0th_event": 0.7979265538100737,
      "eval_ipcw_0th_event_0.25": 0.8684431913780951,
      "eval_ipcw_0th_event_0.5": 0.8440173291436909,
      "eval_ipcw_0th_event_0.75": 0.8250498975593553,
      "eval_ipcw_0th_event_1.0": 0.7979265538100737,
      "eval_ipcw_0th_event_n": 398,
      "eval_ipcw_1th_event": 0.7930554214873754,
      "eval_ipcw_1th_event_0.25": 0.8836283034953112,
      "eval_ipcw_1th_event_0.5": 0.8527635495612796,
      "eval_ipcw_1th_event_0.75": 0.8186333158316047,
      "eval_ipcw_1th_event_1.0": 0.7930554214873754,
      "eval_ipcw_1th_event_n": 381,
      "eval_ipcw_avg": 0.8354396952833483,
      "eval_ipcw_avg_0th_event": 0.8338592429728038,
      "eval_ipcw_avg_1th_event": 0.8370201475938928,
      "eval_ipcw_weighted_avg": 0.8354052053099474,
      "eval_loss": 0.4992225170135498,
      "eval_runtime": 0.2396,
      "eval_samples_per_second": 5563.534,
      "eval_steps_per_second": 12.521,
      "step": 370
    },
    {
      "epoch": 63.36363636363637,
      "grad_norm": 1.0898654460906982,
      "learning_rate": 0.0026433875204791603,
      "loss": 0.8998,
      "step": 380
    },
    {
      "epoch": 63.36363636363637,
      "eval_brier_0th_event": 0.08992063762562182,
      "eval_brier_0th_event_n": 398,
      "eval_brier_1th_event": 0.09012587489294434,
      "eval_brier_1th_event_n": 381,
      "eval_brier_avg": 0.09002325625928308,
      "eval_brier_weighted_avg": 0.09002101682825324,
      "eval_ipcw": 0.7953957737383379,
      "eval_ipcw_0th_event": 0.7991124568586204,
      "eval_ipcw_0th_event_0.25": 0.8684810865297894,
      "eval_ipcw_0th_event_0.5": 0.8474652255600794,
      "eval_ipcw_0th_event_0.75": 0.8281495721596605,
      "eval_ipcw_0th_event_1.0": 0.7991124568586204,
      "eval_ipcw_0th_event_n": 398,
      "eval_ipcw_1th_event": 0.7915132543633446,
      "eval_ipcw_1th_event_0.25": 0.8807092924126172,
      "eval_ipcw_1th_event_0.5": 0.8500530231377414,
      "eval_ipcw_1th_event_0.75": 0.8175573898897391,
      "eval_ipcw_1th_event_1.0": 0.7915132543633446,
      "eval_ipcw_1th_event_n": 381,
      "eval_ipcw_avg": 0.835380162613949,
      "eval_ipcw_avg_0th_event": 0.8358020852770374,
      "eval_ipcw_avg_1th_event": 0.8349582399508606,
      "eval_ipcw_weighted_avg": 0.8353893701688558,
      "eval_loss": 0.4996928870677948,
      "eval_runtime": 0.2573,
      "eval_samples_per_second": 5181.051,
      "eval_steps_per_second": 11.66,
      "step": 380
    },
    {
      "epoch": 65.0,
      "grad_norm": 0.7744889259338379,
      "learning_rate": 0.002589171057086419,
      "loss": 0.8955,
      "step": 390
    },
    {
      "epoch": 65.0,
      "eval_brier_0th_event": 0.08872441564438088,
      "eval_brier_0th_event_n": 398,
      "eval_brier_1th_event": 0.08928524223194416,
      "eval_brier_1th_event_n": 381,
      "eval_brier_avg": 0.08900482893816253,
      "eval_brier_weighted_avg": 0.08899870952096832,
      "eval_ipcw": 0.7969143753153635,
      "eval_ipcw_0th_event": 0.7985139637313164,
      "eval_ipcw_0th_event_0.25": 0.8681627672555573,
      "eval_ipcw_0th_event_0.5": 0.8443678245240802,
      "eval_ipcw_0th_event_0.75": 0.8270296328303894,
      "eval_ipcw_0th_event_1.0": 0.7985139637313164,
      "eval_ipcw_0th_event_n": 398,
      "eval_ipcw_1th_event": 0.7952434141879375,
      "eval_ipcw_1th_event_0.25": 0.8819710144927536,
      "eval_ipcw_1th_event_0.5": 0.8555805317053797,
      "eval_ipcw_1th_event_0.75": 0.8219959430419153,
      "eval_ipcw_1th_event_1.0": 0.7952434141879375,
      "eval_ipcw_1th_event_n": 381,
      "eval_ipcw_avg": 0.8366081364711662,
      "eval_ipcw_avg_0th_event": 0.8345185470853358,
      "eval_ipcw_avg_1th_event": 0.8386977258569965,
      "eval_ipcw_weighted_avg": 0.8365625356758398,
      "eval_loss": 0.4970442056655884,
      "eval_runtime": 0.2428,
      "eval_samples_per_second": 5489.231,
      "eval_steps_per_second": 12.354,
      "step": 390
    },
    {
      "epoch": 66.72727272727273,
      "grad_norm": 0.8498528003692627,
      "learning_rate": 0.002534144623523456,
      "loss": 0.9509,
      "step": 400
    },
    {
      "epoch": 66.72727272727273,
      "eval_brier_0th_event": 0.08755587664696977,
      "eval_brier_0th_event_n": 398,
      "eval_brier_1th_event": 0.08864278636137954,
      "eval_brier_1th_event_n": 381,
      "eval_brier_avg": 0.08809933150417465,
      "eval_brier_weighted_avg": 0.08808747177044875,
      "eval_ipcw": 0.8005242800827732,
      "eval_ipcw_0th_event": 0.8060328107232235,
      "eval_ipcw_0th_event_0.25": 0.8717931227878705,
      "eval_ipcw_0th_event_0.5": 0.8524862756605411,
      "eval_ipcw_0th_event_0.75": 0.8355835001484434,
      "eval_ipcw_0th_event_1.0": 0.8060328107232235,
      "eval_ipcw_0th_event_n": 398,
      "eval_ipcw_1th_event": 0.7947699619859251,
      "eval_ipcw_1th_event_0.25": 0.8857289002557545,
      "eval_ipcw_1th_event_0.5": 0.8554167536737459,
      "eval_ipcw_1th_event_0.75": 0.8225611628033752,
      "eval_ipcw_1th_event_1.0": 0.7947699619859251,
      "eval_ipcw_1th_event_n": 381,
      "eval_ipcw_avg": 0.8405465610048599,
      "eval_ipcw_avg_0th_event": 0.8414739273300196,
      "eval_ipcw_avg_1th_event": 0.8396191946797001,
      "eval_ipcw_weighted_avg": 0.8405667987808904,
      "eval_loss": 0.49297842383384705,
      "eval_runtime": 0.2433,
      "eval_samples_per_second": 5477.728,
      "eval_steps_per_second": 12.328,
      "step": 400
    },
    {
      "epoch": 68.36363636363636,
      "grad_norm": 0.4785284101963043,
      "learning_rate": 0.0024783671434735924,
      "loss": 0.9014,
      "step": 410
    },
    {
      "epoch": 68.36363636363636,
      "eval_brier_0th_event": 0.08833017136293303,
      "eval_brier_0th_event_n": 398,
      "eval_brier_1th_event": 0.08704175737402552,
      "eval_brier_1th_event_n": 381,
      "eval_brier_avg": 0.08768596436847928,
      "eval_brier_weighted_avg": 0.08770002280096416,
      "eval_ipcw": 0.8002027414703871,
      "eval_ipcw_0th_event": 0.8040976829449409,
      "eval_ipcw_0th_event_0.25": 0.8747186284986699,
      "eval_ipcw_0th_event_0.5": 0.8531016803400621,
      "eval_ipcw_0th_event_0.75": 0.8363183684747367,
      "eval_ipcw_0th_event_1.0": 0.8040976829449409,
      "eval_ipcw_0th_event_n": 398,
      "eval_ipcw_1th_event": 0.7961340099562861,
      "eval_ipcw_1th_event_0.25": 0.8848422847399829,
      "eval_ipcw_1th_event_0.5": 0.8546920358837667,
      "eval_ipcw_1th_event_0.75": 0.8236284813377059,
      "eval_ipcw_1th_event_1.0": 0.7961340099562861,
      "eval_ipcw_1th_event_n": 381,
      "eval_ipcw_avg": 0.8409416465220189,
      "eval_ipcw_avg_0th_event": 0.8420590900646023,
      "eval_ipcw_avg_1th_event": 0.8398242029794354,
      "eval_ipcw_weighted_avg": 0.840966032324617,
      "eval_loss": 0.4952029883861542,
      "eval_runtime": 0.244,
      "eval_samples_per_second": 5463.858,
      "eval_steps_per_second": 12.297,
      "step": 410
    },
    {
      "epoch": 70.0,
      "grad_norm": 0.8456340432167053,
      "learning_rate": 0.002421898344859539,
      "loss": 0.902,
      "step": 420
    },
    {
      "epoch": 70.0,
      "eval_brier_0th_event": 0.0881561356596156,
      "eval_brier_0th_event_n": 398,
      "eval_brier_1th_event": 0.08679309499824633,
      "eval_brier_1th_event_n": 381,
      "eval_brier_avg": 0.08747461532893097,
      "eval_brier_weighted_avg": 0.0874894880447482,
      "eval_ipcw": 0.8024658847962401,
      "eval_ipcw_0th_event": 0.8080388710202978,
      "eval_ipcw_0th_event_0.25": 0.8734832465534359,
      "eval_ipcw_0th_event_0.5": 0.8536029702445724,
      "eval_ipcw_0th_event_0.75": 0.836153757969647,
      "eval_ipcw_0th_event_1.0": 0.8080388710202978,
      "eval_ipcw_0th_event_n": 398,
      "eval_ipcw_1th_event": 0.7966442351448626,
      "eval_ipcw_1th_event_0.25": 0.8841057118499573,
      "eval_ipcw_1th_event_0.5": 0.8559817878828824,
      "eval_ipcw_1th_event_0.75": 0.8224291825545064,
      "eval_ipcw_1th_event_1.0": 0.7966442351448626,
      "eval_ipcw_1th_event_n": 381,
      "eval_ipcw_avg": 0.8413049704025202,
      "eval_ipcw_avg_0th_event": 0.8428197114469883,
      "eval_ipcw_avg_1th_event": 0.8397902293580521,
      "eval_ipcw_weighted_avg": 0.8413380263688308,
      "eval_loss": 0.49300408363342285,
      "eval_runtime": 0.2446,
      "eval_samples_per_second": 5449.293,
      "eval_steps_per_second": 12.264,
      "step": 420
    },
    {
      "epoch": 71.72727272727273,
      "grad_norm": 1.0741568803787231,
      "learning_rate": 0.002364798695885241,
      "loss": 0.948,
      "step": 430
    },
    {
      "epoch": 71.72727272727273,
      "eval_brier_0th_event": 0.08598318141846424,
      "eval_brier_0th_event_n": 398,
      "eval_brier_1th_event": 0.08802285607465549,
      "eval_brier_1th_event_n": 381,
      "eval_brier_avg": 0.08700301874655986,
      "eval_brier_weighted_avg": 0.08698076298972081,
      "eval_ipcw": 0.7987423467532868,
      "eval_ipcw_0th_event": 0.805961878204432,
      "eval_ipcw_0th_event_0.25": 0.8711943793911007,
      "eval_ipcw_0th_event_0.5": 0.8530446229525568,
      "eval_ipcw_0th_event_0.75": 0.836306610581516,
      "eval_ipcw_0th_event_1.0": 0.805961878204432,
      "eval_ipcw_0th_event_n": 398,
      "eval_ipcw_1th_event": 0.7912006839775501,
      "eval_ipcw_1th_event_0.25": 0.881616368286445,
      "eval_ipcw_1th_event_0.5": 0.8525342603169924,
      "eval_ipcw_1th_event_0.75": 0.8160137948051427,
      "eval_ipcw_1th_event_1.0": 0.7912006839775501,
      "eval_ipcw_1th_event_n": 381,
      "eval_ipcw_avg": 0.838484074814467,
      "eval_ipcw_avg_0th_event": 0.8416268727824014,
      "eval_ipcw_avg_1th_event": 0.8353412768465325,
      "eval_ipcw_weighted_avg": 0.8385526596224963,
      "eval_loss": 0.49199178814888,
      "eval_runtime": 0.2511,
      "eval_samples_per_second": 5308.303,
      "eval_steps_per_second": 11.947,
      "step": 430
    },
    {
      "epoch": 73.36363636363636,
      "grad_norm": 0.9361284375190735,
      "learning_rate": 0.0023071293402850104,
      "loss": 0.8999,
      "step": 440
    },
    {
      "epoch": 73.36363636363636,
      "eval_brier_0th_event": 0.08810790786055367,
      "eval_brier_0th_event_n": 398,
      "eval_brier_1th_event": 0.09047505245906981,
      "eval_brier_1th_event_n": 381,
      "eval_brier_avg": 0.08929148015981174,
      "eval_brier_weighted_avg": 0.08926565123928877,
      "eval_ipcw": 0.7958997345374084,
      "eval_ipcw_0th_event": 0.7989151757907313,
      "eval_ipcw_0th_event_0.25": 0.8716188050900767,
      "eval_ipcw_0th_event_0.5": 0.8482844066235475,
      "eval_ipcw_0th_event_0.75": 0.829007898364771,
      "eval_ipcw_0th_event_1.0": 0.7989151757907313,
      "eval_ipcw_0th_event_n": 398,
      "eval_ipcw_1th_event": 0.7927497460365616,
      "eval_ipcw_1th_event_0.25": 0.8806683716965047,
      "eval_ipcw_1th_event_0.5": 0.8534104727862328,
      "eval_ipcw_1th_event_0.75": 0.8171298886488378,
      "eval_ipcw_1th_event_1.0": 0.7927497460365616,
      "eval_ipcw_1th_event_n": 381,
      "eval_ipcw_avg": 0.836473095629658,
      "eval_ipcw_avg_0th_event": 0.8369565714672816,
      "eval_ipcw_avg_1th_event": 0.8359896197920342,
      "eval_ipcw_weighted_avg": 0.836483646450248,
      "eval_loss": 0.49754226207733154,
      "eval_runtime": 0.3601,
      "eval_samples_per_second": 3702.171,
      "eval_steps_per_second": 8.332,
      "step": 440
    },
    {
      "epoch": 75.0,
      "grad_norm": 0.7631444931030273,
      "learning_rate": 0.0022489520318492843,
      "loss": 0.883,
      "step": 450
    },
    {
      "epoch": 75.0,
      "eval_brier_0th_event": 0.08682922141908013,
      "eval_brier_0th_event_n": 398,
      "eval_brier_1th_event": 0.08675663283702707,
      "eval_brier_1th_event_n": 381,
      "eval_brier_avg": 0.0867929271280536,
      "eval_brier_weighted_avg": 0.08679371917291555,
      "eval_ipcw": 0.800354116891156,
      "eval_ipcw_0th_event": 0.8065116052250667,
      "eval_ipcw_0th_event_0.25": 0.8743851511637601,
      "eval_ipcw_0th_event_0.5": 0.853631498938325,
      "eval_ipcw_0th_event_0.75": 0.8343136476806086,
      "eval_ipcw_0th_event_1.0": 0.8065116052250667,
      "eval_ipcw_0th_event_n": 398,
      "eval_ipcw_1th_event": 0.7939218849832913,
      "eval_ipcw_1th_event_0.25": 0.8849718670076726,
      "eval_ipcw_1th_event_0.5": 0.856198793774797,
      "eval_ipcw_1th_event_0.75": 0.8217262442724875,
      "eval_ipcw_1th_event_1.0": 0.7939218849832913,
      "eval_ipcw_1th_event_n": 381,
      "eval_ipcw_avg": 0.8407075866307512,
      "eval_ipcw_avg_0th_event": 0.8422104757519402,
      "eval_ipcw_avg_1th_event": 0.8392046975095621,
      "eval_ipcw_weighted_avg": 0.84074038395432,
      "eval_loss": 0.4931829273700714,
      "eval_runtime": 0.2529,
      "eval_samples_per_second": 5270.066,
      "eval_steps_per_second": 11.861,
      "step": 450
    },
    {
      "epoch": 76.72727272727273,
      "grad_norm": 0.9222921133041382,
      "learning_rate": 0.0021903290682971175,
      "loss": 0.9438,
      "step": 460
    },
    {
      "epoch": 76.72727272727273,
      "eval_brier_0th_event": 0.09085689785989531,
      "eval_brier_0th_event_n": 398,
      "eval_brier_1th_event": 0.08772059770364186,
      "eval_brier_1th_event_n": 381,
      "eval_brier_avg": 0.0892887477817686,
      "eval_brier_weighted_avg": 0.08932296928539908,
      "eval_ipcw": 0.797729133509734,
      "eval_ipcw_0th_event": 0.8014177637193466,
      "eval_ipcw_0th_event_0.25": 0.8687008784096163,
      "eval_ipcw_0th_event_0.5": 0.8465115520832059,
      "eval_ipcw_0th_event_0.75": 0.8296046114457212,
      "eval_ipcw_0th_event_1.0": 0.8014177637193466,
      "eval_ipcw_0th_event_n": 398,
      "eval_ipcw_1th_event": 0.7938759187500862,
      "eval_ipcw_1th_event_0.25": 0.8833964194373402,
      "eval_ipcw_1th_event_0.5": 0.8555764372545889,
      "eval_ipcw_1th_event_0.75": 0.8209028022849798,
      "eval_ipcw_1th_event_1.0": 0.7938759187500862,
      "eval_ipcw_1th_event_n": 381,
      "eval_ipcw_avg": 0.8374982979231106,
      "eval_ipcw_avg_0th_event": 0.8365587014144725,
      "eval_ipcw_avg_1th_event": 0.8384378944317487,
      "eval_ipcw_weighted_avg": 0.837477793249623,
      "eval_loss": 0.4974971413612366,
      "eval_runtime": 0.2688,
      "eval_samples_per_second": 4958.747,
      "eval_steps_per_second": 11.16,
      "step": 460
    },
    {
      "epoch": 78.36363636363636,
      "grad_norm": 0.7055100202560425,
      "learning_rate": 0.002131323224566227,
      "loss": 0.8981,
      "step": 470
    },
    {
      "epoch": 78.36363636363636,
      "eval_brier_0th_event": 0.08692498054486938,
      "eval_brier_0th_event_n": 398,
      "eval_brier_1th_event": 0.08789913881991224,
      "eval_brier_1th_event_n": 381,
      "eval_brier_avg": 0.08741205968239081,
      "eval_brier_weighted_avg": 0.08740143022752833,
      "eval_ipcw": 0.7981195897047362,
      "eval_ipcw_0th_event": 0.8027056322636562,
      "eval_ipcw_0th_event_0.25": 0.8687994058040215,
      "eval_ipcw_0th_event_0.5": 0.8483740682324844,
      "eval_ipcw_0th_event_0.75": 0.8326499057898805,
      "eval_ipcw_0th_event_1.0": 0.8027056322636562,
      "eval_ipcw_0th_event_n": 398,
      "eval_ipcw_1th_event": 0.7933289205749456,
      "eval_ipcw_1th_event_0.25": 0.8833964194373402,
      "eval_ipcw_1th_event_0.5": 0.8540410182080227,
      "eval_ipcw_1th_event_0.75": 0.818260328171758,
      "eval_ipcw_1th_event_1.0": 0.7933289205749456,
      "eval_ipcw_1th_event_n": 381,
      "eval_ipcw_avg": 0.8376944623102637,
      "eval_ipcw_avg_0th_event": 0.8381322530225106,
      "eval_ipcw_avg_1th_event": 0.8372566715980168,
      "eval_ipcw_weighted_avg": 0.8377040161512241,
      "eval_loss": 0.49350014328956604,
      "eval_runtime": 0.249,
      "eval_samples_per_second": 5352.51,
      "eval_steps_per_second": 12.046,
      "step": 470
    },
    {
      "epoch": 80.0,
      "grad_norm": 0.771087646484375,
      "learning_rate": 0.002071997685592015,
      "loss": 0.8884,
      "step": 480
    },
    {
      "epoch": 80.0,
      "eval_brier_0th_event": 0.08684803929145216,
      "eval_brier_0th_event_n": 398,
      "eval_brier_1th_event": 0.09374652596645254,
      "eval_brier_1th_event_n": 381,
      "eval_brier_avg": 0.09029728262895234,
      "eval_brier_weighted_avg": 0.09022201030964874,
      "eval_ipcw": 0.7988150374595687,
      "eval_ipcw_0th_event": 0.8020206901290751,
      "eval_ipcw_0th_event_0.25": 0.8708457439955132,
      "eval_ipcw_0th_event_0.5": 0.8491973248236315,
      "eval_ipcw_0th_event_0.75": 0.8330555531059944,
      "eval_ipcw_0th_event_1.0": 0.8020206901290751,
      "eval_ipcw_0th_event_n": 398,
      "eval_ipcw_1th_event": 0.7954663504189822,
      "eval_ipcw_1th_event_0.25": 0.8864859335038363,
      "eval_ipcw_1th_event_0.5": 0.8548271527598645,
      "eval_ipcw_1th_event_0.75": 0.8229054591047722,
      "eval_ipcw_1th_event_1.0": 0.7954663504189822,
      "eval_ipcw_1th_event_n": 381,
      "eval_ipcw_avg": 0.8393505259802088,
      "eval_ipcw_avg_0th_event": 0.8387798280135536,
      "eval_ipcw_avg_1th_event": 0.8399212239468639,
      "eval_ipcw_weighted_avg": 0.8393380717241969,
      "eval_loss": 0.5003946423530579,
      "eval_runtime": 0.259,
      "eval_samples_per_second": 5146.144,
      "eval_steps_per_second": 11.582,
      "step": 480
    },
    {
      "epoch": 81.72727272727273,
      "grad_norm": 0.6356555223464966,
      "learning_rate": 0.002012415978647558,
      "loss": 0.9416,
      "step": 490
    },
    {
      "epoch": 81.72727272727273,
      "eval_brier_0th_event": 0.0865849129048882,
      "eval_brier_0th_event_n": 398,
      "eval_brier_1th_event": 0.08839454307641298,
      "eval_brier_1th_event_n": 381,
      "eval_brier_avg": 0.08748972799065059,
      "eval_brier_weighted_avg": 0.0874699823469305,
      "eval_ipcw": 0.7994509775081736,
      "eval_ipcw_0th_event": 0.8046052937825431,
      "eval_ipcw_0th_event_0.25": 0.8690949879872369,
      "eval_ipcw_0th_event_0.5": 0.8496823126174261,
      "eval_ipcw_0th_event_0.75": 0.8334465030555825,
      "eval_ipcw_0th_event_1.0": 0.8046052937825431,
      "eval_ipcw_0th_event_n": 398,
      "eval_ipcw_1th_event": 0.7940666786178873,
      "eval_ipcw_1th_event_0.25": 0.8837101449275362,
      "eval_ipcw_1th_event_0.5": 0.8545896746139956,
      "eval_ipcw_1th_event_0.75": 0.8217405899517124,
      "eval_ipcw_1th_event_1.0": 0.7940666786178873,
      "eval_ipcw_1th_event_n": 381,
      "eval_ipcw_avg": 0.83886702319424,
      "eval_ipcw_avg_0th_event": 0.8392072743606972,
      "eval_ipcw_avg_1th_event": 0.8385267720277828,
      "eval_ipcw_weighted_avg": 0.8388744484443423,
      "eval_loss": 0.49304836988449097,
      "eval_runtime": 0.2611,
      "eval_samples_per_second": 5104.404,
      "eval_steps_per_second": 11.488,
      "step": 490
    },
    {
      "epoch": 83.36363636363636,
      "grad_norm": 0.6104196310043335,
      "learning_rate": 0.0019526419053170106,
      "loss": 0.8731,
      "step": 500
    },
    {
      "epoch": 83.36363636363636,
      "eval_brier_0th_event": 0.08774294128661152,
      "eval_brier_0th_event_n": 398,
      "eval_brier_1th_event": 0.08901724792960398,
      "eval_brier_1th_event_n": 381,
      "eval_brier_avg": 0.08838009460810775,
      "eval_brier_weighted_avg": 0.08836619010686843,
      "eval_ipcw": 0.7991831861362563,
      "eval_ipcw_0th_event": 0.8036499214200691,
      "eval_ipcw_0th_event_0.25": 0.870428897326876,
      "eval_ipcw_0th_event_0.5": 0.8490506058271895,
      "eval_ipcw_0th_event_0.75": 0.8319767664029959,
      "eval_ipcw_0th_event_1.0": 0.8036499214200691,
      "eval_ipcw_0th_event_n": 398,
      "eval_ipcw_1th_event": 0.7945171477032972,
      "eval_ipcw_1th_event_0.25": 0.8803478260869565,
      "eval_ipcw_1th_event_0.5": 0.8542989686078458,
      "eval_ipcw_1th_event_0.75": 0.8206015430212574,
      "eval_ipcw_1th_event_1.0": 0.7945171477032972,
      "eval_ipcw_1th_event_n": 381,
      "eval_ipcw_avg": 0.838108959549561,
      "eval_ipcw_avg_0th_event": 0.8387765477442827,
      "eval_ipcw_avg_1th_event": 0.8374413713548392,
      "eval_ipcw_weighted_avg": 0.8381235282264675,
      "eval_loss": 0.49466031789779663,
      "eval_runtime": 0.2543,
      "eval_samples_per_second": 5241.661,
      "eval_steps_per_second": 11.797,
      "step": 500
    },
    {
      "epoch": 85.0,
      "grad_norm": 0.7783521413803101,
      "learning_rate": 0.0018927394731752735,
      "loss": 0.899,
      "step": 510
    },
    {
      "epoch": 85.0,
      "eval_brier_0th_event": 0.09091887761380654,
      "eval_brier_0th_event_n": 398,
      "eval_brier_1th_event": 0.08918248264525061,
      "eval_brier_1th_event_n": 381,
      "eval_brier_avg": 0.09005068012952858,
      "eval_brier_weighted_avg": 0.09006962667283118,
      "eval_ipcw": 0.8004282281900265,
      "eval_ipcw_0th_event": 0.8050131557655946,
      "eval_ipcw_0th_event_0.25": 0.8738318819490234,
      "eval_ipcw_0th_event_0.5": 0.851206559969352,
      "eval_ipcw_0th_event_0.75": 0.8337816030123723,
      "eval_ipcw_0th_event_1.0": 0.8050131557655946,
      "eval_ipcw_0th_event_n": 398,
      "eval_ipcw_1th_event": 0.7956387237935013,
      "eval_ipcw_1th_event_0.25": 0.8803614663256607,
      "eval_ipcw_1th_event_0.5": 0.8501185343503949,
      "eval_ipcw_1th_event_0.75": 0.8205757207986527,
      "eval_ipcw_1th_event_1.0": 0.7956387237935013,
      "eval_ipcw_1th_event_n": 381,
      "eval_ipcw_avg": 0.838815955745569,
      "eval_ipcw_avg_0th_event": 0.8409583001740855,
      "eval_ipcw_avg_1th_event": 0.8366736113170524,
      "eval_ipcw_weighted_avg": 0.8388627078062683,
      "eval_loss": 0.49717268347740173,
      "eval_runtime": 0.2515,
      "eval_samples_per_second": 5299.824,
      "eval_steps_per_second": 11.928,
      "step": 510
    },
    {
      "epoch": 86.72727272727273,
      "grad_norm": 0.9835603833198547,
      "learning_rate": 0.0018327728272470754,
      "loss": 0.9271,
      "step": 520
    },
    {
      "epoch": 86.72727272727273,
      "eval_brier_0th_event": 0.08666013643560905,
      "eval_brier_0th_event_n": 398,
      "eval_brier_1th_event": 0.08715693724172409,
      "eval_brier_1th_event_n": 381,
      "eval_brier_avg": 0.08690853683866656,
      "eval_brier_weighted_avg": 0.08690311603397853,
      "eval_ipcw": 0.8009320139562228,
      "eval_ipcw_0th_event": 0.8062478249208105,
      "eval_ipcw_0th_event_0.25": 0.8756660072910272,
      "eval_ipcw_0th_event_0.5": 0.8523273300810622,
      "eval_ipcw_0th_event_0.75": 0.8353277659708933,
      "eval_ipcw_0th_event_1.0": 0.8062478249208105,
      "eval_ipcw_0th_event_n": 398,
      "eval_ipcw_1th_event": 0.7953790145758926,
      "eval_ipcw_1th_event_0.25": 0.8829667519181585,
      "eval_ipcw_1th_event_0.5": 0.8538117289637355,
      "eval_ipcw_1th_event_0.75": 0.8197494096752999,
      "eval_ipcw_1th_event_1.0": 0.7953790145758926,
      "eval_ipcw_1th_event_n": 381,
      "eval_ipcw_avg": 0.8401844791746099,
      "eval_ipcw_avg_0th_event": 0.8423922320659483,
      "eval_ipcw_avg_1th_event": 0.8379767262832716,
      "eval_ipcw_weighted_avg": 0.8402326586343697,
      "eval_loss": 0.49225521087646484,
      "eval_runtime": 0.2575,
      "eval_samples_per_second": 5176.14,
      "eval_steps_per_second": 11.649,
      "step": 520
    }
  ],
  "logging_steps": 10,
  "max_steps": 1000,
  "num_input_tokens_seen": 0,
  "num_train_epochs": 200,
  "save_steps": 10,
  "stateful_callbacks": {
    "EarlyStoppingCallback": {
      "args": {
        "early_stopping_patience": 10,
        "early_stopping_threshold": 0.0
      },
      "attributes": {
        "early_stopping_patience_counter": 10
      }
    },
    "TrainerControl": {
      "args": {
        "should_epoch_stop": false,
        "should_evaluate": false,
        "should_log": false,
        "should_save": true,
        "should_training_stop": true
      },
      "attributes": {}
    }
  },
  "total_flos": 252827879040.0,
  "train_batch_size": 256,
  "trial_name": null,
  "trial_params": null
}
